Workbook

Sheet Backlinks
A1: Referring page title | B1: Referring page URL | C1: Language | D1: Platform | E1: Referring page HTTP code | F1: Domain rating | G1: UR | H1: Domain traffic | I1: Referring domains | J1: Linked domains | K1: External links | L1: Page traffic | M1: Keywords | N1: Target URL | O1: Left context | P1: Anchor | Q1: Right context | R1: Redirect Chain URLs | S1: Redirect Chain status codes | T1: Type | U1: Is spam | V1: Content | W1: Nofollow | X1: UGC | Y1: Sponsored | Z1: Rendered | AA1: Raw | AB1: Lost status | AC1: Drop reason | AD1: Discovered status | AE1: First seen | AF1: Last seen | AG1: Lost | AH1: Author | AI1: Page type | AJ1: Page category
A2: Pikeland Property Group LLC | BBB Business Profile | Better Business Bureau | B2: https://www.bbb.org/us/pa/phoenixville/profile/home-buyers/pikeland-property-group-llc-0241-236072398 | C2: en | E2: 200 | F2: 93 | G2: 4.5 | H2: 3593412 | I2: 0 | J2: 10 | K2: 17 | L2: 0 | M2: 0 | N2: https://www.pikelandpropertygroup.com/ | P2: Visit Website | T2: text | U2: FALSE | V2: FALSE | W2: TRUE | X2: FALSE | Y2: FALSE | Z2: FALSE | AA2: TRUE | AD2: linkfound | AE2: 45935.997 | AF2: 46182.579
A3: 👲 Domain Report 👲 | B3: https://screenshots.wiki/report/50888 | C3: en | E3: 200 | F3: 41 | G3: 0 | H3: 0 | I3: 0 | J3: 3702 | K3: 4156 | L3: 0 | M3: 0 | N3: https://www.pikelandpropertygroup.com/ | O3: Homepage | P3: pikelandpropertygroup.com | Q3: &nbsp | R3: https://pikelandpropertygroup.com/ | S3: 301 | T3: text | U3: TRUE | V3: TRUE | W3: TRUE | X3: FALSE | Y3: FALSE | Z3: FALSE | AA3: TRUE | AD3: linkfound | AE3: 46132.774 | AF3: 46132.774 | AI3: Site page > Services | AJ3: Internet > Web services > Development
A4: 🛸 Dark Side Links – Dark/White Hat Link Building Services – Global Waste Commodities | B4: https://gwc.spottedcow.media/2026/02/21/dark-side-links-dark-white-hat-link-building-1342/ | C4: en | D4: wordpress | E4: 200 | F4: 15 | G4: 0 | H4: 6 | I4: 0 | J4: 3119 | K4: 3419 | L4: 0 | M4: 0 | N4: https://www.pikelandpropertygroup.com/ | O4: DARK HAT AND WHITE HAT BACKLINKS | P4: JOIN OUR TELEGRAM https://t.me/s/darksidelinks | Q4: FOR CHEAP AND GOOGLE FRIENDLY BACKLINKS | T4: text | U4: TRUE | V4: FALSE | W4: TRUE | X4: FALSE | Y4: FALSE | Z4: FALSE | AA4: TRUE | AD4: pagefound | AE4: 46135.343 | AF4: 46212.496 | AI4: Site page > Services | AJ4: Internet > Web services > SEO and marketing; Business > Business services
A5: seowarez.shop — The 120-Day Traffic Services Case Study for Financial Advisory — Placements, Anchors, Rankings Before and After | B5: https://seowarez.shop/a3dl99t-build-unstoppable-law-firm-serp-local-seo-crowd-links-traffic-playbook/ | C5: en | E5: 200 | F5: 0.7 | G5: 0 | H5: 0 | I5: 2 | J5: 5175 | K5: 6070 | L5: 0 | M5: 0 | N5: https://www.pikelandpropertygroup.com/ | P5: Boost pikelandpropertygroup.com using high-DR backlinks, editorial guest posts, on-page SEO, local SEO, web development, SaaS tools and automation tools for sustained DR/DA/TF uplift with full transparency. | R5: https://pikelandpropertygroup.com/ | S5: 301 | T5: text | U5: TRUE | V5: FALSE | W5: TRUE | X5: FALSE | Y5: FALSE | Z5: FALSE | AA5: TRUE | AD5: pagefound | AE5: 46204.364 | AF5: 46232.417 | AI5: Article > Research | AJ5: Business > Marketing > Marketing; Internet > Web services > SEO and marketing; Finance > Management > Portfolio
A6: The 120-Day Traffic Services Case Study for Financial Advisory — Placements, Anchors, Rankings Before and After — rankdeals.shop | B6: https://rankdeals.shop/a3dl99t-build-unstoppable-law-firm-serp-local-seo-crowd-links-traffic-playbook/ | C6: en | E6: 200 | F6: 0.8 | G6: 0 | H6: 0 | I6: 0 | J6: 5175 | K6: 6065 | L6: 0 | M6: 0 | N6: https://www.pikelandpropertygroup.com/ | P6: Boost pikelandpropertygroup.com using high-DR backlinks, editorial guest posts, on-page SEO, local SEO, web development, SaaS tools and automation tools for sustained DR/DA/TF uplift with full transparency. | R6: https://pikelandpropertygroup.com/ | S6: 301 | T6: text | U6: TRUE | V6: FALSE | W6: TRUE | X6: FALSE | Y6: FALSE | Z6: FALSE | AA6: TRUE | AD6: linkfound | AE6: 46206.348 | AF6: 46220.429 | AI6: Article > Research | AJ6: Business > Marketing > Marketing; Internet > Web services > SEO and marketing; Finance > Management > Portfolio
A7: How to Build an Unstoppable Insurance SERP Presence Using PBN Backlinks, On-Page SEO, and Traffic — Full Playbook — Complete With hands-on strategy notes, quality-control requirements, and competitive search-positioning lessons — Site Rank Service — Managed professional services for site-wide SEO, keyword visibility and organic growth to turn search visibility into consistent website growth | B7: https://siterankservice.shop/d81d8072e-18-month-pbn-backlinks-journey-saas-zero-rankings-to-dr50-measurable-results-blueprint-planning-testing-and-tracking-for-scalable-seo-performance/ | C7: en | E7: 200 | F7: 0 | G7: 0 | H7: 0 | I7: 0 | J7: 6729 | K7: 7855 | L7: 0 | M7: 0 | N7: https://www.pikelandpropertygroup.com/ | P7: Everything pikelandpropertygroup.com needs: guest posts and backlinks, on-page SEO, local SEO, web development, SaaS integrations and automation tools — a strong DR/DA/TF increase worldwide. The strategy also covers competitor research, natural anchor distribution, quality verification, and clear monthly performance reporting. · Site Rank Service — Managed professional services for site-wide ... | R7: https://pikelandpropertygroup.com/ | S7: 301 | T7: text | U7: TRUE | V7: FALSE | W7: TRUE | X7: FALSE | Y7: FALSE | Z7: FALSE | AA7: TRUE | AD7: linkfound | AE7: 46227.747 | AF7: 46227.747 | AI7: Article > Guide | AJ7: Internet > Web services > SEO and marketing; Business > Marketing > Marketing
A8: 🛸 Dark Side Links – Dark/White Hat Link Building Services – Revan | B8: https://revan-me.com/bez-rubriki/dark-side-links-dark-white-hat-link-building-1342/ | C8: en | D8: wordpress | E8: 200 | F8: 8 | G8: 0 | H8: 0 | I8: 0 | J8: 3118 | K8: 3419 | L8: 0 | M8: 0 | N8: https://www.pikelandpropertygroup.com/ | O8: DARK HAT AND WHITE HAT BACKLINKS | P8: JOIN OUR TELEGRAM https://t.me/s/darksidelinks | Q8: FOR CHEAP AND GOOGLE FRIENDLY BACKLINKS | T8: text | U8: TRUE | V8: FALSE | W8: TRUE | X8: FALSE | Y8: FALSE | Z8: FALSE | AA8: TRUE | AD8: pagefound | AE8: 46154.768 | AF8: 46228.002 | AI8: Site page > Services | AJ8: Internet > Web services > SEO and marketing; Business > Marketing > Marketing
A9: Site Rank Builders — Growth builders specializing in site-wide SEO, keyword visibility and organic growth to improve website trust and sustainable search performance — How I Stacked PBN Backlinks With Web Development for Real Estate — The Dual Strategy That Doubled My Ranking Speed — Explaining a detailed execution roadmap, technical considerations, and safer scaling recommendations | B9: https://siterankbuilders.shop/efbb44080-do-crowd-links-still-work-2026-insurance-tested-10-placements-tracked-detailed-campaign-breakdown-budget-links-and-content-for-long-term-search-success/ | C9: en | E9: 200 | F9: 0 | G9: 0 | H9: 0 | I9: 0 | J9: 6735 | K9: 7857 | L9: 0 | M9: 0 | N9: https://www.pikelandpropertygroup.com/ | P9: Power up pikelandpropertygroup.com: guest posts, backlinks, on-page and local SEO, web development, SaaS tools and workflow automation tools for a clear DR/DA/TF lift in any language. Every delivery follows a structured plan for content relevance, link diversity, authority checks, traffic measurement, and ongoing optimization. · Site Rank Builders — Growth builders specializing in site-wide ... | R9: https://pikelandpropertygroup.com/ | S9: 301 | T9: text | U9: TRUE | V9: FALSE | W9: TRUE | X9: FALSE | Y9: FALSE | Z9: FALSE | AA9: TRUE | AD9: pagefound | AE9: 46229.313 | AF9: 46229.313 | AI9: Article > Guide | AJ9: Internet > Web services > SEO and marketing
A10: ✅ Website Stats 📊 | B10: https://optimizeflow.top/stats/50888 | C10: en | E10: 200 | F10: 41 | G10: 0 | H10: 0 | I10: 0 | J10: 3702 | K10: 4157 | L10: 0 | M10: 0 | N10: https://www.pikelandpropertygroup.com/ | O10: Homepage | P10: pikelandpropertygroup.com | Q10: &nbsp | R10: https://pikelandpropertygroup.com/ | S10: 301 | T10: text | U10: FALSE | V10: TRUE | W10: TRUE | X10: FALSE | Y10: FALSE | Z10: FALSE | AA10: TRUE | AD10: linkfound | AE10: 46068.119 | AF10: 46131.873 | AI10: Listing collection > Business | AJ10: Internet > Web services > Analytics; Reference
A11: Why Our Agency Stopped Manual Outreach Forever After Discovering Professional Link Building Results — linkrankpro.shop | B11: https://linkrankpro.shop/du3olt6-professional-link-campaign-biggest-agency-success-story/ | C11: en | E11: 200 | F11: 54 | G11: 0 | H11: 0 | I11: 4 | J11: 8299 | K11: 9726 | L11: 0 | M11: 0 | N11: https://www.pikelandpropertygroup.com/ | P11: Professional backlinks for pikelandpropertygroup.com from agency that built authority for 400 websites | R11: https://pikelandpropertygroup.com/ | S11: 301 | T11: text | U11: TRUE | V11: FALSE | W11: TRUE | X11: FALSE | Y11: FALSE | Z11: FALSE | AA11: TRUE | AD11: pagefound | AE11: 46149.883 | AF11: 46220.16 | AI11: Article > Story | AJ11: Internet > Web services > SEO and marketing; Business > Marketing > Marketing
A12: High-DA Guest Posts vs Crowd Links for Medical — Which One Moves Rankings Faster and Holds Longer? — Breaking Down hands-on strategy notes, technical considerations, and durable ranking strategies — Top Rank Company — A full-service company delivering top-position SEO, competitive visibility and ranking growth for reliable rankings, stronger authority and organic reach | B12: https://toprankcompany.shop/d67f93d69-used-traffic-services-rebuilt-dr-after-domain-migration-travel-site-month-by-month-progress-complete-implementation-guide-tools-tactics-and-insights-for-sustainable-organic-growth/ | C12: en | E12: 200 | F12: 0 | G12: 0 | H12: 0 | I12: 0 | J12: 6729 | K12: 7856 | L12: 0 | M12: 0 | N12: https://www.pikelandpropertygroup.com/ | P12: pikelandpropertygroup.com gets guest posts and backlinks, on-page SEO, local SEO, web development, SaaS integrations and automation tools, together driving a noticeable DR/DA/TF rise with proven results. The complete process includes website review, competitor benchmarking, anchor-risk control, placement validation, and practical growth recommendations. · Top Rank Company — A full-service ... | R12: https://pikelandpropertygroup.com/ | S12: 301 | T12: text | U12: TRUE | V12: FALSE | W12: TRUE | X12: FALSE | Y12: FALSE | Z12: FALSE | AA12: TRUE | AD12: linkfound | AE12: 46227.438 | AF12: 46227.438 | AI12: Article > Comparison | AJ12: Internet > Web services > SEO and marketing; Business > Marketing > Marketing
A13: The 120-Day Traffic Services Case Study for Financial Advisory — Placements, Anchors, Rankings Before and After — seostash.shop | B13: https://seostash.shop/a3dl99t-build-unstoppable-law-firm-serp-local-seo-crowd-links-traffic-playbook/ | C13: en | E13: 200 | F13: 0.7 | G13: 0 | H13: 0 | I13: 1 | J13: 5175 | K13: 6066 | L13: 0 | M13: 0 | N13: https://www.pikelandpropertygroup.com/ | P13: Boost pikelandpropertygroup.com using high-DR backlinks, editorial guest posts, on-page SEO, local SEO, web development, SaaS tools and automation tools for sustained DR/DA/TF uplift with full transparency. | R13: https://pikelandpropertygroup.com/ | S13: 301 | T13: text | U13: TRUE | V13: FALSE | W13: TRUE | X13: FALSE | Y13: FALSE | Z13: FALSE | AA13: TRUE | AD13: linkfound | AE13: 46205.864 | AF13: 46219.916 | AI13: Article > Research | AJ13: Business > Marketing > Marketing; Internet > Web services > SEO and marketing; Finance > Management > Portfolio
A14: Page 1 Rankings for Law Firm Using Only Link Insertions — Is This Possible in 2026? My Real Experiment — backlinkzeno.shop | B14: https://backlinkzeno.shop/alrp01b-90-day-serp-climb-saas-combined-editorial-links-traffic-services-position1/ | C14: en | E14: 200 | F14: 0.8 | G14: 0 | H14: 0 | I14: 5 | J14: 5693 | K14: 6661 | L14: 0 | M14: 0 | N14: https://www.pikelandpropertygroup.com/ | P14: Take pikelandpropertygroup.com to page one with contextual backlinks, premium guest posts, on-page SEO, local SEO, custom web development, SaaS tools plus automation tools — sustained DR/DA/TF uplift for every sector. | R14: https://pikelandpropertygroup.com/ | S14: 301 | T14: text | U14: TRUE | V14: FALSE | W14: TRUE | X14: FALSE | Y14: FALSE | Z14: FALSE | AA14: TRUE | AD14: pagefound | AE14: 46195.465 | AF14: 46224.675 | AI14: Article > Opinion | AJ14: Internet > Web services > SEO and marketing; Business > Marketing > Marketing; Government > Legal
A15: seocartly.shop — The 120-Day Traffic Services Case Study for Financial Advisory — Placements, Anchors, Rankings Before and After | B15: https://seocartly.shop/a3dl99t-build-unstoppable-law-firm-serp-local-seo-crowd-links-traffic-playbook/ | C15: en | E15: 200 | F15: 0.7 | G15: 0 | H15: 0 | I15: 6 | J15: 5175 | K15: 6070 | L15: 0 | M15: 0 | N15: https://www.pikelandpropertygroup.com/ | P15: Boost pikelandpropertygroup.com using high-DR backlinks, editorial guest posts, on-page SEO, local SEO, web development, SaaS tools and automation tools for sustained DR/DA/TF uplift with full transparency. | R15: https://pikelandpropertygroup.com/ | S15: 301 | T15: text | U15: TRUE | V15: FALSE | W15: TRUE | X15: FALSE | Y15: FALSE | Z15: FALSE | AA15: TRUE | AD15: pagefound | AE15: 46201.9 | AF15: 46229.932 | AI15: Article > Research | AJ15: Business > Marketing > Marketing; Internet > Web services > SEO and marketing; Finance > Management
A16: Ranking Velocity Blueprint for SaaS — How to Rank Using Guest Posts and Tiered Link Building — linkwares.shop | B16: https://linkwares.shop/qayi9jj-45-day-press-release-links-case-study-law-firm-placements-anchors-rankings/ | C16: en | E16: 200 | F16: 0.8 | G16: 0 | H16: 0 | I16: 8 | J16: 6204 | K16: 7245 | L16: 0 | M16: 0 | N16: https://www.pikelandpropertygroup.com/ | P16: Grow pikelandpropertygroup.com with guest posts, backlinks, on-page and local SEO, web development, SaaS tools and workflow automation tools — balanced DR/DA/TF growth for any business size. | R16: https://pikelandpropertygroup.com/ | S16: 301 | T16: text | U16: TRUE | V16: FALSE | W16: TRUE | X16: FALSE | Y16: FALSE | Z16: FALSE | AA16: TRUE | AD16: pagefound | AE16: 46194.696 | AF16: 46223.121 | AI16: Article > Guide | AJ16: Internet > Web services > SEO and marketing; Business > Marketing > Marketing
A17: seoagency.sale — Rank on Page One, Faster — Contextual Dofollow Links Google Values (Update-Safe, DR/DA/TF Up) | B17: https://seoagency.sale/d5qujh-rank-on-page-1-with-seo-and-backlinks/ | C17: en | E17: 200 | F17: 30 | G17: 0 | H17: 0 | I17: 2 | J17: 8232 | K17: 9501 | L17: 0 | M17: 0 | N17: https://www.pikelandpropertygroup.com/ | P17: pikelandpropertygroup.com — rank faster — clean PBN mix; grow Moz DA. | Visit Buyseolink.com for any Query | R17: https://pikelandpropertygroup.com/ | S17: 301 | T17: text | U17: TRUE | V17: FALSE | W17: TRUE | X17: FALSE | Y17: FALSE | Z17: FALSE | AA17: TRUE | AD17: pagefound | AE17: 46012.551 | AF17: 46230.366 | AI17: Listing > Service | AJ17: Internet > Web services > SEO and marketing; Business > Marketing > Marketing
A18: ✅ Website Stats 📊 | B18: https://optimizeflow.top/stats/50887 | C18: en | E18: 200 | F18: 41 | G18: 0 | H18: 0 | I18: 0 | J18: 3702 | K18: 4156 | L18: 0 | M18: 0 | N18: https://www.pikelandpropertygroup.com/ | O18: Homepage | P18: pikelandpropertygroup.com | Q18: &nbsp | R18: https://pikelandpropertygroup.com/ | S18: 301 | T18: text | U18: FALSE | V18: TRUE | W18: TRUE | X18: FALSE | Y18: FALSE | Z18: FALSE | AA18: TRUE | AD18: pagefound | AE18: 46058.975 | AF18: 46116.956 | AI18: Listing collection > Business | AJ18: Internet > Web services > Analytics; Reference
A19: From DR 2 to Full Recovery in Legal — The 30-Day Strategy Built Entirely on DR Boost Services — Explaining measurable performance checkpoints, provider evaluation criteria, and competitive search-positioning lessons — BBF101229 | B19: https://organicrankdirect.shop/bbf101229-high-da-guest-posts-grew-domain-authority-past-dr30-law-firm-money-site-every-dollar-ranking-tracked-measurable-results-blueprint-research-execution-and-analysis-for-reliable-page-one-progress/ | C19: en | E19: 200 | F19: 0 | G19: 0 | H19: 0 | I19: 0 | J19: 6729 | K19: 7851 | L19: 0 | M19: 0 | N19: https://www.pikelandpropertygroup.com/ | P19: Everything pikelandpropertygroup.com needs: contextual backlinks, premium guest posts, on-page SEO, local SEO, custom web development, SaaS tools plus automation tools — a measurable DR/DA/TF boost across any niche. The strategy also covers competitor research, natural anchor distribution, quality verification, and clear monthly performance reporting. · bbf101229 | R19: https://pikelandpropertygroup.com/ | S19: 301 | T19: text | U19: TRUE | V19: FALSE | W19: TRUE | X19: FALSE | Y19: FALSE | Z19: FALSE | AA19: TRUE | AD19: pagefound | AE19: 46224.298 | AF19: 46224.298 | AI19: Article > Guide | AJ19: Business > Marketing > Marketing; Jobs and education > Education > Certification; Internet > Web services > SEO and marketing; Government > Legal
A20: The 120-Day Traffic Services Case Study for Financial Advisory — Placements, Anchors, Rankings Before and After — seoprime.shop | B20: https://seoprime.shop/a3dl99t-build-unstoppable-law-firm-serp-local-seo-crowd-links-traffic-playbook/ | C20: en | E20: 200 | F20: 0.7 | G20: 0 | H20: 0 | I20: 0 | J20: 5183 | K20: 6067 | L20: 0 | M20: 0 | N20: https://www.pikelandpropertygroup.com/ | P20: Boost pikelandpropertygroup.com using high-DR backlinks, editorial guest posts, on-page SEO, local SEO, web development, SaaS tools and automation tools for sustained DR/DA/TF uplift with full transparency. | R20: https://pikelandpropertygroup.com/ | S20: 301 | T20: text | U20: TRUE | V20: FALSE | W20: TRUE | X20: FALSE | Y20: FALSE | Z20: FALSE | AA20: TRUE | AD20: linkfound | AE20: 46205.846 | AF20: 46219.85 | AI20: Article > Research | AJ20: Business > Marketing > Marketing; Internet > Web services > SEO and marketing; Finance > Management > Portfolio
A21: How I Used Guest Posts and recovered lost traffic fully for My Law Firm Site — Month-by-Month Progress Documentation — backlinkmart.shop | B21: https://backlinkmart.shop/i9y7o5a-30-day-local-seo-journey-b2b-page3-to-10x-traffic/ | C21: en | E21: 200 | F21: 0.7 | G21: 0 | H21: 0 | I21: 7 | J21: 8298 | K21: 9740 | L21: 0 | M21: 0 | N21: https://www.pikelandpropertygroup.com/ | P21: Everything pikelandpropertygroup.com needs: high-DR backlinks, editorial guest posts, on-page SEO, local SEO, web development, SaaS tools and automation tools — real DR/DA/TF improvement in competitive markets. | R21: https://pikelandpropertygroup.com/ | S21: 301 | T21: text | U21: TRUE | V21: FALSE | W21: TRUE | X21: FALSE | Y21: FALSE | Z21: FALSE | AA21: TRUE | AD21: pagefound | AE21: 46196.163 | AF21: 46224.217 | AI21: Article > Guide | AJ21: Internet > Web services > SEO and marketing; Government > Legal > Services; Business
A22: linkstock.shop — How I Used Authority Link Packages and recovered from a Google penalty in 60 days for My Fintech Site — Month-by-Month Progress Documentation | B22: https://linkstock.shop/ad5l39m-used-traffic-services-doubled-organic-revenue-90-days-saas-site-month-by-month-progress/ | C22: en | E22: 200 | F22: 0.7 | G22: 0 | H22: 0 | I22: 0 | J22: 8298 | K22: 9728 | L22: 0 | M22: 0 | N22: https://www.pikelandpropertygroup.com/ | P22: Boost pikelandpropertygroup.com using guest posts and backlinks, on-page SEO, local SEO, web development, SaaS integrations and automation tools for rising DR/DA/TF scores with relevance-first placements. | R22: https://pikelandpropertygroup.com/ | S22: 301 | T22: text | U22: TRUE | V22: FALSE | W22: TRUE | X22: FALSE | Y22: FALSE | Z22: FALSE | AA22: TRUE | AD22: pagefound | AE22: 46204.402 | AF22: 46232.47 | AI22: Article > Guide | AJ22: Internet > Web services > SEO and marketing; Finance > Management > Portfolio; Business > Marketing > Marketing
A23: The Flow Backlink Strategy That Worked for My New Website From the Very First Month — seorankflow.shop | B23: https://seorankflow.shop/du3olt6-consistent-flow-link-building-result-095-page-one-any-niche-worldwide/ | C23: en | E23: 200 | F23: 54 | G23: 0 | H23: 0 | I23: 10 | J23: 8299 | K23: 9741 | L23: 0 | M23: 0 | N23: https://www.pikelandpropertygroup.com/ | P23: Flow DR improvement for pikelandpropertygroup.com with genuine high-authority referring domain links | R23: https://pikelandpropertygroup.com/ | S23: 301 | T23: text | U23: TRUE | V23: FALSE | W23: TRUE | X23: FALSE | Y23: FALSE | Z23: FALSE | AA23: TRUE | AD23: pagefound | AE23: 46195.999 | AF23: 46224.459 | AI23: Article > Guide | AJ23: Internet > Web services > SEO and marketing; Business > Marketing > Marketing
A24: Categories Blumen | Free pdf textbooks download online | B24: https://www.pdfbookee.com/category/blumen/ | C24: en | E24: 200 | F24: 0 | G24: 0 | H24: 0 | I24: 0 | J24: 9 | K24: 10 | L24: 0 | M24: 0 | N24: https://www.pikelandpropertygroup.com/ | P24: Download | T24: text | U24: TRUE | V24: FALSE | W24: FALSE | X24: FALSE | Y24: FALSE | Z24: FALSE | AA24: TRUE | AD24: linkfound | AE24: 46211.658 | AF24: 46211.658
A25: Where to buy 🚀 aged domains and backlinks 🔥 | 1204-6378 | B25: https://wonvision.com/1add20ae4edb6e37d8ff4b4d2677f240-l/ | C25: en | D25: wordpress | E25: 200 | F25: 0.8 | G25: 0 | H25: 0 | I25: 0 | J25: 9169 | K25: 9997 | L25: 0 | M25: 0 | N25: https://www.pikelandpropertygroup.com/ | O25: pikelandia.com pikelandmotors.com | P25: pikelandpropertygroup.com | Q25: pikelandscape.com pikelandschools.com | R25: https://pikelandpropertygroup.com/ | S25: 301 | T25: text | U25: TRUE | V25: FALSE | W25: FALSE | X25: FALSE | Y25: FALSE | Z25: FALSE | AA25: TRUE | AD25: linkfound | AE25: 46164.877 | AF25: 46164.877 | AI25: Listing > Product | AJ25: Internet > Web services > SEO and marketing
A26: 👲 Domain Report 👲 | B26: https://atomizelink.icu/report/50888 | C26: en | E26: 200 | F26: 43 | G26: 0 | H26: 0 | I26: 0 | J26: 3701 | K26: 4156 | L26: 0 | M26: 0 | N26: https://www.pikelandpropertygroup.com/ | O26: Homepage | P26: pikelandpropertygroup.com | Q26: &nbsp | R26: https://pikelandpropertygroup.com/ | S26: 301 | T26: text | U26: FALSE | V26: TRUE | W26: TRUE | X26: FALSE | Y26: FALSE | Z26: FALSE | AA26: TRUE | AD26: pagefound | AE26: 46018.703 | AF26: 46131.869 | AI26: Site page > Services | AJ26: Internet > Web services > Development
A27: Link Growth Source — A trusted information and service source for authority link acquisition, referral visibility and ranking growth for better keyword positions and lasting digital authority — Do PBN Backlinks Still Work in 2025 for Healthcare Websites? I Tested 10 Placements and Tracked Every Move — Explaining actionable ranking improvements, provider evaluation criteria, and lasting traffic-growth insights | B27: https://linkgrowthsource.shop/f6b960faf-ranking-recovery-blueprint-medical-rank-using-authority-link-packages-local-seo-step-by-step-strategy-research-execution-and-analysis-for-reliable-page-one-progress/ | C27: en | E27: 200 | F27: 0 | G27: 0 | H27: 0 | I27: 0 | J27: 6729 | K27: 7855 | L27: 0 | M27: 0 | N27: https://www.pikelandpropertygroup.com/ | P27: Power up pikelandpropertygroup.com: contextual backlinks, premium guest posts, on-page SEO, local SEO, custom web development, SaaS tools plus automation tools for DR/DA/TF that climbs steadily with proven results. The service also includes technical review, content alignment, backlink-quality screening, conversion considerations, and transparent milestone reporting. · Link Growth Source — A ... | R27: https://pikelandpropertygroup.com/ | S27: 301 | T27: text | U27: TRUE | V27: FALSE | W27: TRUE | X27: FALSE | Y27: FALSE | Z27: FALSE | AA27: TRUE | AD27: linkfound | AE27: 46227.66 | AF27: 46227.66 | AI27: Article > Guide | AJ27: Internet > Web services > SEO and marketing; Health > Medical services; Business
A28: seomart.shop — The 120-Day Traffic Services Case Study for Financial Advisory — Placements, Anchors, Rankings Before and After | B28: https://seomart.shop/a3dl99t-build-unstoppable-law-firm-serp-local-seo-crowd-links-traffic-playbook/ | C28: en | E28: 200 | F28: 0.8 | G28: 0 | H28: 0 | I28: 0 | J28: 5174 | K28: 6071 | L28: 0 | M28: 0 | N28: https://www.pikelandpropertygroup.com/ | P28: Boost pikelandpropertygroup.com using high-DR backlinks, editorial guest posts, on-page SEO, local SEO, web development, SaaS tools and automation tools for sustained DR/DA/TF uplift with full transparency. | R28: https://pikelandpropertygroup.com/ | S28: 301 | T28: text | U28: TRUE | V28: FALSE | W28: TRUE | X28: FALSE | Y28: FALSE | Z28: FALSE | AA28: TRUE | AD28: pagefound | AE28: 46204.92 | AF28: 46232.963 | AI28: Article > Research | AJ28: Business > Marketing > Marketing; Internet > Web services > SEO and marketing; Finance > Management
A29: How Crowd Links restored rankings after an algorithm update for My Dental Money Site — Every Dollar Spent, Every Ranking Gained, Tracked — Complete With clear planning and execution details, realistic outcome expectations, and competitive search-positioning lessons — Rank SEO Masters — Experienced specialists in ranking strategy, technical optimization and authority signals for reliable rankings, stronger authority and organic reach | B29: https://rankseomasters.shop/f89672fda-editorial-links-took-every-keyword-page1-ymyl-money-site-every-dollar-ranking-tracked-detailed-campaign-breakdown-budget-links-and-content-for-higher-search-visibility/ | C29: en | E29: 200 | F29: 0 | G29: 0 | H29: 0 | I29: 0 | J29: 6729 | K29: 7855 | L29: 0 | M29: 0 | N29: https://www.pikelandpropertygroup.com/ | P29: Power up pikelandpropertygroup.com: guest posts, backlinks, on-page and local SEO, web development, SaaS tools and workflow automation tools for a noticeable DR/DA/TF rise for local or global targets. Results are supported by relevant placements, sensible link velocity, documented checks, competitor comparisons, and clear evidence of progress. · Rank SEO Masters — Experienced specialists in ... | R29: https://pikelandpropertygroup.com/ | S29: 301 | T29: text | U29: TRUE | V29: FALSE | W29: TRUE | X29: FALSE | Y29: FALSE | Z29: FALSE | AA29: TRUE | AD29: linkfound | AE29: 46226.909 | AF29: 46226.909 | AI29: Article > Guide | AJ29: Internet > Web services > SEO and marketing; Business > Marketing > Marketing
A30: seolinkkart.shop — The 120-Day Traffic Services Case Study for Financial Advisory — Placements, Anchors, Rankings Before and After | B30: https://seolinkkart.shop/a3dl99t-build-unstoppable-law-firm-serp-local-seo-crowd-links-traffic-playbook/ | C30: en | E30: 200 | F30: 0.8 | G30: 0 | H30: 0 | I30: 0 | J30: 5173 | K30: 6070 | L30: 0 | M30: 0 | N30: https://www.pikelandpropertygroup.com/ | P30: Boost pikelandpropertygroup.com using high-DR backlinks, editorial guest posts, on-page SEO, local SEO, web development, SaaS tools and automation tools for sustained DR/DA/TF uplift with full transparency. | R30: https://pikelandpropertygroup.com/ | S30: 301 | T30: text | U30: TRUE | V30: FALSE | W30: TRUE | X30: FALSE | Y30: FALSE | Z30: FALSE | AA30: TRUE | AD30: pagefound | AE30: 46204.354 | AF30: 46232.356 | AI30: Article > Research | AJ30: Internet > Web services > SEO and marketing; Business > Marketing > Marketing; Finance
A31: The 60-Day SERP Climb for Financial Advisory — How I Combined Sidebar Links and Traffic Services to Reach Position 1 — Covering hands-on strategy notes, provider evaluation criteria, and durable ranking strategies — BF177064C | B31: https://pageseopartners.shop/bf177064c-stacked-on-page-seo-dr-boost-services-real-estate-dual-strategy-doubled-ranking-speed-advanced-growth-framework-mistakes-risks-and-solutions-for-stronger-domain-authority/ | C31: en | E31: 200 | F31: 0 | G31: 0 | H31: 0 | I31: 0 | J31: 6721 | K31: 7846 | L31: 0 | M31: 0 | N31: https://www.pikelandpropertygroup.com/ | P31: pikelandpropertygroup.com: high-quality backlinks, guest posts, on-page and local SEO, custom web development, SaaS tools and automation tools, all driving long-term DR/DA/TF gains with full transparency. Every campaign includes niche-relevance checks, diversified anchor planning, placement review, and transparent progress tracking. · bf177064c | R31: https://pikelandpropertygroup.com/ | S31: 301 | T31: text | U31: TRUE | V31: FALSE | W31: TRUE | X31: FALSE | Y31: FALSE | Z31: FALSE | AA31: TRUE | AD31: pagefound | AE31: 46226.012 | AF31: 46226.012 | AI31: Article > Guide | AJ31: Internet > Web services > SEO and marketing; Finance > Management > Portfolio; Business > Marketing > Marketing
A32: ranktrove.shop — The 120-Day Traffic Services Case Study for Financial Advisory — Placements, Anchors, Rankings Before and After | B32: https://ranktrove.shop/a3dl99t-build-unstoppable-law-firm-serp-local-seo-crowd-links-traffic-playbook/ | C32: en | E32: 200 | F32: 0.7 | G32: 0 | H32: 0 | I32: 0 | J32: 5175 | K32: 6070 | L32: 0 | M32: 0 | N32: https://www.pikelandpropertygroup.com/ | P32: Boost pikelandpropertygroup.com using high-DR backlinks, editorial guest posts, on-page SEO, local SEO, web development, SaaS tools and automation tools for sustained DR/DA/TF uplift with full transparency. | R32: https://pikelandpropertygroup.com/ | S32: 301 | T32: text | U32: TRUE | V32: FALSE | W32: TRUE | X32: FALSE | Y32: FALSE | Z32: FALSE | AA32: TRUE | AD32: pagefound | AE32: 46204.402 | AF32: 46232.466 | AI32: Article > Research | AJ32: Business > Marketing > Marketing; Internet > Web services > SEO and marketing; Finance > Management > Portfolio
A33: The 18-Month SERP Climb for SaaS — How I Combined Blogroll Links and High-DA Guest Posts to Reach Position 1 — Explaining actionable ranking improvements, common mistakes to avoid, and future campaign planning — 6E724A3AE — Search Rank Builders — Growth builders specializing in keyword rankings, search visibility and competitive SEO performance to turn search visibility into consistent website growth | B33: https://searchrankbuilders.shop/6e724a3ae-topical-authority-blueprint-financial-advisory-rank-using-tiered-link-building-dofollow-backlinks-measurable-results-blueprint-research-execution-and-analysis-for-consistent-traffic-growth/ | C33: en | E33: 200 | F33: 0 | G33: 0 | H33: 0 | I33: 0 | J33: 6721 | K33: 7844 | L33: 0 | M33: 0 | N33: https://www.pikelandpropertygroup.com/ | P33: Strengthen pikelandpropertygroup.com through guest posts and backlinks, on-page SEO, local SEO, web development, SaaS integrations and automation tools for a measurable DR/DA/TF boost across any niche. Every delivery follows a structured plan for content relevance, link diversity, authority checks, traffic measurement, and ongoing optimization. · 6e724a3ae | R33: https://pikelandpropertygroup.com/ | S33: 301 | T33: text | U33: TRUE | V33: FALSE | W33: TRUE | X33: FALSE | Y33: FALSE | Z33: FALSE | AA33: TRUE | AD33: linkfound | AE33: 46224.583 | AF33: 46224.583 | AI33: Article > Guide | AJ33: Internet > Web services > SEO and marketing; Business
A34: The 120-Day Traffic Services Case Study for Financial Advisory — Placements, Anchors, Rankings Before and After — seocrate.shop | B34: https://seocrate.shop/a3dl99t-build-unstoppable-law-firm-serp-local-seo-crowd-links-traffic-playbook/ | C34: en | E34: 200 | F34: 0.7 | G34: 0 | H34: 0 | I34: 0 | J34: 5175 | K34: 6065 | L34: 0 | M34: 0 | N34: https://www.pikelandpropertygroup.com/ | P34: Boost pikelandpropertygroup.com using high-DR backlinks, editorial guest posts, on-page SEO, local SEO, web development, SaaS tools and automation tools for sustained DR/DA/TF uplift with full transparency. | R34: https://pikelandpropertygroup.com/ | S34: 301 | T34: text | U34: TRUE | V34: FALSE | W34: TRUE | X34: FALSE | Y34: FALSE | Z34: FALSE | AA34: TRUE | AD34: pagefound | AE34: 46192.325 | AF34: 46220.345 | AI34: Article > Research | AJ34: Business > Marketing > Marketing; Internet > Web services > SEO and marketing; Finance > Management > Portfolio
A35: rankstash.shop — The 120-Day Traffic Services Case Study for Financial Advisory — Placements, Anchors, Rankings Before and After | B35: https://rankstash.shop/a3dl99t-build-unstoppable-law-firm-serp-local-seo-crowd-links-traffic-playbook/ | C35: en | E35: 200 | F35: 0.7 | G35: 0 | H35: 0 | I35: 3 | J35: 5175 | K35: 6070 | L35: 0 | M35: 0 | N35: https://www.pikelandpropertygroup.com/ | P35: Boost pikelandpropertygroup.com using high-DR backlinks, editorial guest posts, on-page SEO, local SEO, web development, SaaS tools and automation tools for sustained DR/DA/TF uplift with full transparency. | R35: https://pikelandpropertygroup.com/ | S35: 301 | T35: text | U35: TRUE | V35: FALSE | W35: TRUE | X35: FALSE | Y35: FALSE | Z35: FALSE | AA35: TRUE | AD35: pagefound | AE35: 46201.999 | AF35: 46230.034 | AI35: Article > Research | AJ35: Business > Marketing > Marketing; Internet > Web services > SEO and marketing; Finance > Management
A36: ✅ Website Stats 📊 | B36: https://metamagic.top/stats/50888 | C36: en | E36: 200 | F36: 42 | G36: 0 | H36: 0 | I36: 0 | J36: 3700 | K36: 4150 | L36: 0 | M36: 0 | N36: https://www.pikelandpropertygroup.com/ | O36: Homepage | P36: pikelandpropertygroup.com | Q36: &nbsp | R36: https://pikelandpropertygroup.com/ | S36: 301 | T36: text | U36: FALSE | V36: TRUE | W36: TRUE | X36: FALSE | Y36: FALSE | Z36: FALSE | AA36: TRUE | AD36: pagefound | AE36: 46066.139 | AF36: 46066.139 | AI36: Listing collection > Business | AJ36: Internet > Web services > Analytics; Reference
A37: Backlink Builders — Growth builders specializing in editorial backlinks, authority placements and off-page SEO for better keyword positions and lasting digital authority — DR Growth Blueprint for Dental — How to Rank Using DR Boost Services and Traffic Services — Featuring actionable ranking improvements, content and link-quality checks, and long-term organic growth lessons | B37: https://backlinkbuilders.shop/956300d60-best-sidebar-links-medical-2026-compared-15-providers-roi-advanced-growth-framework-data-progress-and-outcomes-for-stronger-domain-authority/ | C37: en | E37: 200 | F37: 0 | G37: 0 | H37: 0 | I37: 0 | J37: 6720 | K37: 7846 | L37: 0 | M37: 0 | N37: https://www.pikelandpropertygroup.com/ | P37: Power up pikelandpropertygroup.com: high-DR backlinks, editorial guest posts, on-page SEO, local SEO, web development, SaaS tools and automation tools for long-term DR/DA/TF gains with editorial standards. We also prioritize topical relevance, clean placement standards, sensible campaign pacing, and reporting that connects work to outcomes. · Backlink Builders — Growth builders specializing in ... | R37: https://pikelandpropertygroup.com/ | S37: 301 | T37: text | U37: TRUE | V37: FALSE | W37: TRUE | X37: FALSE | Y37: FALSE | Z37: FALSE | AA37: TRUE | AD37: pagefound | AE37: 46228.6 | AF37: 46228.6 | AI37: Site page > Services | AJ37: Internet > Web services > SEO and marketing; Business > Marketing > Marketing
A38: Pikeland Property Group | The Org | B38: https://theorg.com/org/pikeland-property-group | C38: en | E38: 200 | F38: 76 | G38: 0 | H38: 98474 | I38: 0 | J38: 5 | K38: 6 | L38: 0 | M38: 0 | N38: https://www.pikelandpropertygroup.com/ | P38: View the website | T38: text | U38: FALSE | V38: FALSE | W38: FALSE | X38: FALSE | Y38: FALSE | Z38: FALSE | AA38: TRUE | AD38: linkfound | AE38: 46191.94 | AF38: 46191.94
A39: 6-Month Blogroll Link Experiment for Automotive — Final Verdict on Whether These Links Are Worth Buying in a Competitive Market — TopLinkRanker — The Agency That Ranks Websites Others Cannot. | B39: https://toplinkranker.shop/1f1h6zd-pbn-links-strategically-hit-targets-photography-portfolio-page1-traffic/ | C39: en | E39: 200 | F39: 53 | G39: 0 | H39: 0 | I39: 0 | J39: 8287 | K39: 9899 | L39: 0 | M39: 0 | N39: https://www.pikelandpropertygroup.com/ | P39: Power pikelandpropertygroup.com with Expert Professional Guest Posting + Dofollow Link Building — Increase Ahrefs Domain Rating DR • Moz Domain Authority DA • Majestic Trust Flow TF Certified — Any Website • Any Niche • Any Language | R39: https://pikelandpropertygroup.com/ | S39: 301 | T39: text | U39: TRUE | V39: FALSE | W39: TRUE | X39: FALSE | Y39: FALSE | Z39: FALSE | AA39: TRUE | AD39: linkfound | AE39: 46153.742 | AF39: 46167.863 | AI39: Article > Review | AJ39: Internet > Web services > SEO and marketing; Business > Marketing > Marketing; Autos > Vehicle shopping
A40: Rank Growth Group — A professional services group for organic ranking growth, keyword visibility and website authority to build trust, visibility and competitive keyword positions — Scaling Blogroll Links for Insurance Agencies — How to Manage Hundreds of Monthly Placements at Quality — Explaining hands-on strategy notes, budget allocation guidance, and safer scaling recommendations | B40: https://rankgrowthgroup.shop/766c2ea96-90-day-homepage-links-journey-insurance-dr5-to-serp-domination-measurable-results-blueprint-quality-checks-and-reporting-for-competitive-serp-results/ | C40: en | E40: 200 | F40: 0 | G40: 0 | H40: 0 | I40: 0 | J40: 6729 | K40: 7855 | L40: 0 | M40: 0 | N40: https://www.pikelandpropertygroup.com/ | P40: Scale pikelandpropertygroup.com with guest posts, backlinks, on-page and local SEO, web development, SaaS tools and workflow automation tools, earning a measurable DR/DA/TF boost tailored to your vertical. Campaign quality is protected through manual review, realistic pacing, diversified sources, accurate reporting, and continuous performance checks. · Rank Growth Group — A professional ... | R40: https://pikelandpropertygroup.com/ | S40: 301 | T40: text | U40: TRUE | V40: FALSE | W40: TRUE | X40: FALSE | Y40: FALSE | Z40: FALSE | AA40: TRUE | AD40: pagefound | AE40: 46227.002 | AF40: 46227.002 | AI40: Article > Guide | AJ40: Internet > Web services > SEO and marketing; Business > Marketing > Marketing
A41: Rank SEO Alliance — A strategic professional alliance for ranking strategy, technical optimization and authority signals for reliable rankings, stronger authority and organic reach — Ranking Recovery Blueprint for Law Firm — How to Rank Using Editorial Links and Crowd Links — With step-by-step optimization guidance, common mistakes to avoid, and lasting traffic-growth insights | B41: https://rankseoalliance.shop/e7595751b-best-dofollow-backlinks-real-estate-2025-compared-15-providers-roi-measurable-results-blueprint-planning-testing-and-tracking-for-reliable-page-one-progress/ | C41: en | E41: 200 | F41: 0 | G41: 0 | H41: 0 | I41: 0 | J41: 6720 | K41: 7848 | L41: 0 | M41: 0 | N41: https://www.pikelandpropertygroup.com/ | P41: pikelandpropertygroup.com gets premium guest posts, contextual backlinks, on-page and local SEO, conversion-focused web development, SaaS tools and automation tools, together driving real DR/DA/TF improvement for any business size. Every delivery follows a structured plan for content relevance, link diversity, authority checks, traffic measurement, and ongoing optimization. · Rank SEO Alliance ... | R41: https://pikelandpropertygroup.com/ | S41: 301 | T41: text | U41: TRUE | V41: FALSE | W41: TRUE | X41: FALSE | Y41: FALSE | Z41: FALSE | AA41: TRUE | AD41: pagefound | AE41: 46231.859 | AF41: 46231.859 | AI41: Article > Guide | AJ41: Internet > Web services > SEO and marketing; Business > Business services > Consulting
A42: Do Editorial Links Still Work in 2026 for Insurance Websites? I Tested 10 Placements and Tracked Every Move — With step-by-step optimization guidance, quality-control requirements, and future campaign planning — Rank Growth Partners — Trusted strategic partners for organic ranking growth, keyword visibility and website authority to support stronger visibility, traffic quality and authority | B42: https://rankgrowthpartners.shop/6fb4d55cb-60-day-web-development-case-study-financial-advisory-placements-anchors-rankings-real-world-action-plan-tools-tactics-and-insights-for-better-google-positions/ | C42: en | E42: 200 | F42: 0 | G42: 0 | H42: 0 | I42: 0 | J42: 6721 | K42: 7846 | L42: 0 | M42: 0 | N42: https://www.pikelandpropertygroup.com/ | P42: pikelandpropertygroup.com: guest posts, backlinks, on-page and local SEO, web development, SaaS tools and workflow automation tools, all driving DR/DA/TF gains that hold at a sustainable pace. The complete process includes website review, competitor benchmarking, anchor-risk control, placement validation, and practical growth recommendations. · Rank Growth Partners — Trusted strategic partners ... | R42: https://pikelandpropertygroup.com/ | S42: 301 | T42: text | U42: TRUE | V42: FALSE | W42: TRUE | X42: FALSE | Y42: FALSE | Z42: FALSE | AA42: TRUE | AD42: linkfound | AE42: 46226.925 | AF42: 46226.925 | AI42: Article > Guide | AJ42: Internet > Web services > SEO and marketing; Business > Marketing > Marketing
A43: Domain Rank Results — A results-focused platform for domain authority, trust signals and search competitiveness for stronger rankings and sustainable organic visibility — I Bought Web Development for My Law Firm Site — Full 60-Day Review of Metrics, Rankings, and Traffic Impact — Plus step-by-step optimization guidance, important risk checks, and competitive search-positioning lessons | B43: https://domainrankresults.shop/7c3d65bca-stacked-editorial-links-homepage-links-legal-dual-strategy-doubled-ranking-speed-measurable-results-blueprint-quality-checks-and-reporting-for-consistent-traffic-growth/ | C43: en | E43: 200 | F43: 0 | G43: 0 | H43: 0 | I43: 0 | J43: 6729 | K43: 7855 | L43: 0 | M43: 0 | N43: https://www.pikelandpropertygroup.com/ | P43: pikelandpropertygroup.com: high-DR backlinks, editorial guest posts, on-page SEO, local SEO, web development, SaaS tools and automation tools, all driving steady DR/DA/TF growth with relevance-first placements. Campaign quality is protected through manual review, realistic pacing, diversified sources, accurate reporting, and continuous performance checks. · Domain Rank Results — A ... | R43: https://pikelandpropertygroup.com/ | S43: 301 | T43: text | U43: TRUE | V43: FALSE | W43: TRUE | X43: FALSE | Y43: FALSE | Z43: FALSE | AA43: TRUE | AD43: pagefound | AE43: 46227.279 | AF43: 46227.279 | AI43: Article > Guide | AJ43: Internet > Web services > SEO and marketing
A44: Rank SEO Partners — Trusted strategic partners for ranking strategy, technical optimization and authority signals to improve website trust and sustainable search performance — How I Stacked Automation Tools With Sidebar Links for Dental — The Dual Strategy That Doubled My Ranking Speed — Including clear planning and execution details, budget allocation guidance, and lasting traffic-growth insights | B44: https://rankseopartners.shop/ab6399fd0-used-high-da-guest-posts-page5-to-page1-pharmaceutical-site-month-by-month-progress-step-by-step-strategy-planning-testing-and-tracking-for-stronger-domain-authority/ | C44: en | E44: 200 | F44: 0 | G44: 0 | H44: 0 | I44: 0 | J44: 6720 | K44: 7848 | L44: 0 | M44: 0 | N44: https://www.pikelandpropertygroup.com/ | P44: Complete SEO for pikelandpropertygroup.com: guest posts, backlinks, on-page and local SEO, web development, SaaS tools and workflow automation tools, delivering compounding DR/DA/TF in any language. The service also includes technical review, content alignment, backlink-quality screening, conversion considerations, and transparent milestone reporting. · Rank SEO Partners — Trusted strategic ... | R44: https://pikelandpropertygroup.com/ | S44: 301 | T44: text | U44: TRUE | V44: FALSE | W44: TRUE | X44: FALSE | Y44: FALSE | Z44: FALSE | AA44: TRUE | AD44: linkfound | AE44: 46231.479 | AF44: 46231.479 | AI44: Article > Guide | AJ44: Internet > Web services > SEO and marketing; Business > Marketing > Marketing
A45: SEO Boost Agency — A specialist digital agency for SEO acceleration, visibility improvements and authority growth to improve website trust and sustainable search performance — How I Used Niche Edits and recovered lost traffic fully for My Dental Site — Month-by-Month Progress Documentation — Covering actionable ranking improvements, content and link-quality checks, and repeatable SEO takeaways | B45: https://seoboostagency.shop/967eb4a99-30-day-serp-climb-b2b-combined-high-da-guest-posts-guest-posts-position1-practical-execution-roadmap-cost-timeline-and-results-for-stronger-domain-authority/ | C45: en | E45: 200 | F45: 0 | G45: 0 | H45: 0 | I45: 0 | J45: 6729 | K45: 7843 | L45: 0 | M45: 0 | N45: https://www.pikelandpropertygroup.com/ | P45: Power up pikelandpropertygroup.com: premium guest posts, high-quality backlinks, on-page SEO, local SEO, web development, SaaS tools and automation tools for real DR/DA/TF improvement tailored to your vertical. Each project is supported by careful prospect selection, manual quality checks, balanced link velocity, and measurable ranking analysis. · SEO Boost Agency — A specialist digital agency ... | R45: https://pikelandpropertygroup.com/ | S45: 301 | T45: text | U45: TRUE | V45: FALSE | W45: TRUE | X45: FALSE | Y45: FALSE | Z45: FALSE | AA45: TRUE | AD45: pagefound | AE45: 46228.614 | AF45: 46228.614 | AI45: Article > Guide | AJ45: Internet > Web services > SEO and marketing; Business > Marketing > Marketing
A46: ranklinkerpro.shop — Smart Link Building Result 162: How Real Authority Links Delivered Page One Rankings in Any Niche | B46: https://ranklinkerpro.shop/du3olt6-smart-strategic-link-building-result-077-page-one-any-niche-worldwide/ | C46: en | E46: 200 | F46: 54 | G46: 0 | H46: 0 | I46: 4 | J46: 8299 | K46: 9730 | L46: 0 | M46: 0 | N46: https://www.pikelandpropertygroup.com/ | P46: Smart PBN links for pikelandpropertygroup.com working in gambling adult crypto and all restricted niches | R46: https://pikelandpropertygroup.com/ | S46: 301 | T46: text | U46: TRUE | V46: FALSE | W46: TRUE | X46: FALSE | Y46: FALSE | Z46: FALSE | AA46: TRUE | AD46: pagefound | AE46: 46148.835 | AF46: 46233.196 | AI46: Article > Guide | AJ46: Internet > Web services > SEO and marketing
A47: ✅ Website Stats 📊 | B47: https://www.ready.pro/stats/50887 | C47: en | E47: 200 | F47: 35 | G47: 0 | H47: 0 | I47: 0 | J47: 3713 | K47: 4169 | L47: 0 | M47: 0 | N47: https://www.pikelandpropertygroup.com/ | O47: Homepage | P47: pikelandpropertygroup.com | Q47: &nbsp | R47: https://pikelandpropertygroup.com/ | S47: 301 | T47: text | U47: TRUE | V47: TRUE | W47: TRUE | X47: FALSE | Y47: FALSE | Z47: FALSE | AA47: TRUE | AD47: pagefound | AE47: 46155.06 | AF47: 46220.068 | AI47: Listing collection > Business | AJ47: Internet > Web services > Analytics; Reference
A48: QuarterLinks- Dofollow Article Links just for 25 cents. – Global Waste Commodities | B48: http://gwc.spottedcow.media/2025/05/15/quarterlinks-dofollow-article-links-just-for-25-5330/ | C48: en | D48: wordpress | E48: 200 | F48: 15 | G48: 0 | H48: 6 | I48: 0 | J48: 520 | K48: 568 | L48: 0 | M48: 0 | N48: https://www.pikelandpropertygroup.com/ | O48: DOFOLLOW ARTICLE LINKS ONLY FOR $0,25 | P48: OUR TELEGRAM CHANEL https://t.me/s/quarterlinks25 | Q48: WE DON’T TAKE PREPAYMENTS, LINKS ARE 100% SAFE | T48: text | U48: TRUE | V48: TRUE | W48: TRUE | X48: FALSE | Y48: FALSE | Z48: FALSE | AA48: TRUE | AD48: pagefound | AE48: 46144.55 | AF48: 46207.205 | AI48: Site page > Services | AJ48: Internet > Web services > SEO and marketing; Business > Business services > E-commerce
A49: Where to buy 🚀 aged domains and backlinks 🔥 | 1204-6378 | B49: https://www.wallpapers.pro/1add20ae4edb6e37d8ff4b4d2677f240-l/ | C49: en | D49: wordpress | E49: 200 | F49: 2.2 | G49: 0 | H49: 0 | I49: 0 | J49: 9173 | K49: 9997 | L49: 0 | M49: 0 | N49: https://www.pikelandpropertygroup.com/ | O49: pikelandia.com pikelandmotors.com | P49: pikelandpropertygroup.com | Q49: pikelandscape.com pikelandschools.com | R49: https://pikelandpropertygroup.com/ | S49: 301 | T49: text | U49: TRUE | V49: FALSE | W49: FALSE | X49: FALSE | Y49: FALSE | Z49: FALSE | AA49: TRUE | AD49: pagefound | AE49: 46166.938 | AF49: 46224.048 | AI49: Listing > Product | AJ49: Internet > Web services > SEO and marketing
A50: Buy High Quality Dofollow Seo Backlinks to Rank on 1st Page — Seo Backlinks For Rank on 1st page | B50: https://buybacklinks.agency/th8c-get-ranking-on-1st-page-with-us/ | C50: en | E50: 200 | F50: 71 | G50: 0 | H50: 0 | I50: 59 | J50: 5198 | K50: 6052 | L50: 0 | M50: 0 | N50: https://www.pikelandpropertygroup.com/ | P50: Google first page for pikelandpropertygroup.com: authoritative guest posts + backlinks; DR/DA/TF surge — global markets. | Visit buybacklinks.agency for any Query | R50: https://pikelandpropertygroup.com/ | S50: 301 | T50: text | U50: TRUE | V50: FALSE | W50: TRUE | X50: FALSE | Y50: FALSE | Z50: FALSE | AA50: TRUE | AD50: pagefound | AE50: 46108.468 | AF50: 46170.302 | AI50: Listing > Product | AJ50: Internet > Web services > SEO and marketing
A51: linkrank.shop — The 18-Month Editorial Links Case Study for eCommerce — Placements, Anchors, Rankings Before and After | B51: https://linkrank.shop/wtyzgjq-60-day-pbn-backlinks-case-study-fintech-placements-anchors-rankings/ | C51: en | E51: 200 | F51: 0.7 | G51: 0 | H51: 0 | I51: 0 | J51: 8296 | K51: 9741 | L51: 0 | M51: 0 | N51: https://www.pikelandpropertygroup.com/ | P51: Strengthen pikelandpropertygroup.com through high-DR backlinks, editorial guest posts, on-page SEO, local SEO, web development, SaaS tools and automation tools for a noticeable DR/DA/TF rise with full transparency. | R51: https://pikelandpropertygroup.com/ | S51: 301 | T51: text | U51: TRUE | V51: FALSE | W51: TRUE | X51: FALSE | Y51: FALSE | Z51: FALSE | AA51: TRUE | AD51: pagefound | AE51: 46203.137 | AF51: 46231.192 | AI51: Article > Research | AJ51: Internet > Web services > SEO and marketing; Business > Marketing > Marketing; Shopping
A52: Where to buy 🚀 aged domains and backlinks 🔥 | 1204-6378 | B52: https://www.websiterace.com/1add20ae4edb6e37d8ff4b4d2677f240-l/ | C52: en | D52: wordpress | E52: 200 | F52: 10 | G52: 0 | H52: 0 | I52: 0 | J52: 9172 | K52: 9997 | L52: 0 | M52: 0 | N52: https://www.pikelandpropertygroup.com/ | O52: pikelandia.com pikelandmotors.com | P52: pikelandpropertygroup.com | Q52: pikelandscape.com pikelandschools.com | R52: https://pikelandpropertygroup.com/ | S52: 301 | T52: text | U52: TRUE | V52: FALSE | W52: FALSE | X52: FALSE | Y52: FALSE | Z52: FALSE | AA52: TRUE | AD52: linkfound | AE52: 46183.831 | AF52: 46183.831 | AI52: Listing > Product | AJ52: Internet > Web services > SEO and marketing
A53: 👲 Domain Report 👲 | B53: https://byteshort.xyz/report/50888 | C53: en | E53: 200 | F53: 44 | G53: 0 | H53: 0 | I53: 0 | J53: 3704 | K53: 4156 | L53: 0 | M53: 0 | N53: https://www.pikelandpropertygroup.com/ | O53: Homepage | P53: pikelandpropertygroup.com | Q53: &nbsp | R53: https://pikelandpropertygroup.com/ | S53: 301 | T53: text | U53: FALSE | V53: TRUE | W53: TRUE | X53: FALSE | Y53: FALSE | Z53: FALSE | AA53: TRUE | AD53: linkfound | AE53: 46111.043 | AF53: 46111.043 | AI53: Site page > Services | AJ53: Internet > Web services > Development
A54: 🛸 Dark Side Links - Dark/White Hat Link Building Services - .:: Agroinsur - Comercializadora y Exportadora de Panela Natural ::. | B54: https://agroinsursas.com/dark-side-links-dark-white-hat-link-building-1342/ | C54: en, es | D54: wordpress | E54: 200 | F54: 14 | G54: 0 | H54: 0 | I54: 0 | J54: 3118 | K54: 3410 | L54: 0 | M54: 0 | N54: https://www.pikelandpropertygroup.com/ | O54: DARK HAT AND WHITE HAT BACKLINKS | P54: JOIN OUR TELEGRAM https://t.me/s/darksidelinks | Q54: FOR CHEAP AND GOOGLE FRIENDLY BACKLINKS | T54: text | U54: TRUE | V54: FALSE | W54: TRUE | X54: FALSE | Y54: FALSE | Z54: FALSE | AA54: TRUE | AD54: pagefound | AE54: 46197.3 | AF54: 46233.176 | AI54: Site page > Services | AJ54: Business > Forestry > Seed; Internet > Web services > Development
A55: The 120-Day Traffic Services Case Study for Financial Advisory — Placements, Anchors, Rankings Before and After — rankkit.shop | B55: https://rankkit.shop/a3dl99t-build-unstoppable-law-firm-serp-local-seo-crowd-links-traffic-playbook/ | C55: en | E55: 200 | F55: 0.7 | G55: 0 | H55: 0 | I55: 2 | J55: 5175 | K55: 6066 | L55: 0 | M55: 0 | N55: https://www.pikelandpropertygroup.com/ | P55: Boost pikelandpropertygroup.com using high-DR backlinks, editorial guest posts, on-page SEO, local SEO, web development, SaaS tools and automation tools for sustained DR/DA/TF uplift with full transparency. | R55: https://pikelandpropertygroup.com/ | S55: 301 | T55: text | U55: TRUE | V55: FALSE | W55: TRUE | X55: FALSE | Y55: FALSE | Z55: FALSE | AA55: TRUE | AD55: linkfound | AE55: 46205.887 | AF55: 46219.893 | AI55: Article > Research | AJ55: Business > Marketing > Marketing; Internet > Web services > SEO and marketing; Finance > Management > Portfolio
A56: Link Insertions vs PBN Backlinks for SaaS — Which One Moves Rankings Faster and Holds Longer? — linkory.shop | B56: https://linkory.shop/qi9ru4l-build-unstoppable-fintech-serp-local-seo-sidebar-links-traffic-playbook/ | C56: en | E56: 200 | F56: 0.8 | G56: 0 | H56: 0 | I56: 8 | J56: 8297 | K56: 9723 | L56: 0 | M56: 0 | N56: https://www.pikelandpropertygroup.com/ | P56: For pikelandpropertygroup.com, we deliver premium guest posts, contextual backlinks, on-page and local SEO, conversion-focused web development, SaaS tools and automation tools — compounding DR/DA/TF across all markets. | R56: https://pikelandpropertygroup.com/ | S56: 301 | T56: text | U56: TRUE | V56: FALSE | W56: TRUE | X56: FALSE | Y56: FALSE | Z56: FALSE | AA56: TRUE | AD56: pagefound | AE56: 46193.766 | AF56: 46221.877 | AI56: Article > Comparison | AJ56: Internet > Web services > SEO and marketing; Business > Marketing > Marketing
A57: The 60-Day Web Development Case Study for Financial Advisory — Placements, Anchors, Rankings Before and After — Including tested workflow recommendations, common mistakes to avoid, and future campaign planning — BC6E0F6F6 | B57: https://linkseocollective.shop/bc6e0f6f6-dr5-to-dr40-insurance-60-day-strategy-only-guest-posts-detailed-campaign-breakdown-budget-links-and-content-for-lasting-ranking-improvements/ | C57: en | E57: 200 | F57: 0 | G57: 0 | H57: 0 | I57: 0 | J57: 6728 | K57: 7850 | L57: 0 | M57: 0 | N57: https://www.pikelandpropertygroup.com/ | P57: Take pikelandpropertygroup.com to page one with backlinks and guest posts, on-page SEO, local SEO, custom web development, SaaS integrations and automation tools — stronger DR, DA and TF for any business size. Every campaign includes niche-relevance checks, diversified anchor planning, placement review, and transparent progress tracking. · bc6e0f6f6 | R57: https://pikelandpropertygroup.com/ | S57: 301 | T57: text | U57: TRUE | V57: FALSE | W57: TRUE | X57: FALSE | Y57: FALSE | Z57: FALSE | AA57: TRUE | AD57: pagefound | AE57: 46222.897 | AF57: 46222.897 | AI57: Article > Research | AJ57: Internet > Web services > SEO and marketing; Business > Business services > Consulting; Finance > Management > Portfolio
A58: Where to buy 🚀 aged domains and backlinks 🔥 | 1204-6378 | B58: https://indexaward.com/1add20ae4edb6e37d8ff4b4d2677f240-l/ | C58: en | D58: wordpress | E58: 200 | F58: 6 | G58: 0 | H58: 0 | I58: 0 | J58: 9166 | K58: 9997 | L58: 0 | M58: 0 | N58: https://www.pikelandpropertygroup.com/ | O58: pikelandia.com pikelandmotors.com | P58: pikelandpropertygroup.com | Q58: pikelandscape.com pikelandschools.com | R58: https://pikelandpropertygroup.com/ | S58: 301 | T58: text | U58: TRUE | V58: FALSE | W58: FALSE | X58: FALSE | Y58: FALSE | Z58: FALSE | AA58: TRUE | AD58: pagefound | AE58: 46189.054 | AF58: 46232.591 | AI58: Listing > Product | AJ58: Internet > Web services > SEO and marketing
A59: seochest.shop — The 120-Day Traffic Services Case Study for Financial Advisory — Placements, Anchors, Rankings Before and After | B59: https://seochest.shop/a3dl99t-build-unstoppable-law-firm-serp-local-seo-crowd-links-traffic-playbook/ | C59: en | E59: 200 | F59: 0.7 | G59: 0 | H59: 0 | I59: 4 | J59: 5173 | K59: 6070 | L59: 0 | M59: 0 | N59: https://www.pikelandpropertygroup.com/ | P59: Boost pikelandpropertygroup.com using high-DR backlinks, editorial guest posts, on-page SEO, local SEO, web development, SaaS tools and automation tools for sustained DR/DA/TF uplift with full transparency. | R59: https://pikelandpropertygroup.com/ | S59: 301 | T59: text | U59: TRUE | V59: FALSE | W59: TRUE | X59: FALSE | Y59: FALSE | Z59: FALSE | AA59: TRUE | AD59: pagefound | AE59: 46201.293 | AF59: 46229.412 | AI59: Article > Research | AJ59: Business > Marketing > Marketing; Internet > Web services > SEO and marketing; Finance > Management
A60: How Web Development cleaned toxic links and grew traffic 40% for My eCommerce Money Site — Every Dollar Spent, Every Ranking Gained, Tracked — Supported by a detailed execution roadmap, content and link-quality checks, and safer scaling recommendations — D451C9373 | B60: https://linkgrowthstudio.shop/d451c9373-stacked-automation-tools-guest-posts-ymyl-dual-strategy-doubled-ranking-speed-long-term-seo-method-planning-testing-and-tracking-for-sustainable-organic-growth/ | C60: en | E60: 200 | F60: 0 | G60: 0 | H60: 0 | I60: 0 | J60: 6721 | K60: 7844 | L60: 0 | M60: 0 | N60: https://www.pikelandpropertygroup.com/ | P60: pikelandpropertygroup.com gets contextual backlinks, premium guest posts, on-page SEO, local SEO, custom web development, SaaS tools plus automation tools, together driving rising DR/DA/TF scores with proven results. The strategy also covers competitor research, natural anchor distribution, quality verification, and clear monthly performance reporting. · d451c9373 | R60: https://pikelandpropertygroup.com/ | S60: 301 | T60: text | U60: TRUE | V60: FALSE | W60: TRUE | X60: FALSE | Y60: FALSE | Z60: FALSE | AA60: TRUE | AD60: pagefound | AE60: 46222.397 | AF60: 46222.397 | AI60: Article > Guide | AJ60: Internet > Web services > SEO and marketing; Business > Marketing > Marketing; Finance
A61: Page 1 Rankings for Law Firm Using Only Link Insertions — Is This Possible in 2026? My Real Experiment — guestpostlinks.shop | B61: https://guestpostlinks.shop/alrp01b-90-day-serp-climb-saas-combined-editorial-links-traffic-services-position1/ | C61: en | E61: 200 | F61: 0.7 | G61: 0 | H61: 0 | I61: 0 | J61: 5701 | K61: 6662 | L61: 0 | M61: 0 | N61: https://www.pikelandpropertygroup.com/ | P61: Take pikelandpropertygroup.com to page one with contextual backlinks, premium guest posts, on-page SEO, local SEO, custom web development, SaaS tools plus automation tools — sustained DR/DA/TF uplift for every sector. | R61: https://pikelandpropertygroup.com/ | S61: 301 | T61: text | U61: TRUE | V61: FALSE | W61: TRUE | X61: FALSE | Y61: FALSE | Z61: FALSE | AA61: TRUE | AD61: linkfound | AE61: 46213.325 | AF61: 46213.325 | AI61: Article > Opinion | AJ61: Internet > Web services > SEO and marketing; Business > Marketing > Marketing; Government > Legal
A62: Search Rank Central — A central strategy and resource hub for keyword rankings, search visibility and competitive SEO performance for practical SEO progress across competitive search results — How I Stacked Contextual Backlinks With PBN Backlinks for Financial Advisory — The Dual Strategy That Doubled My Ranking Speed — Complete With step-by-step optimization guidance, realistic outcome expectations, and lasting traffic-growth insights | B62: https://searchrankcentral.shop/90eb84177-used-contextual-backlinks-recovered-from-google-penalty-60-days-medical-site-month-by-month-progress-full-ranking-workflow-planning-testing-and-tracking-for-sustainable-organic-growth/ | C62: en | E62: 200 | F62: 0 | G62: 0 | H62: 0 | I62: 0 | J62: 6735 | K62: 7857 | L62: 0 | M62: 0 | N62: https://www.pikelandpropertygroup.com/ | P62: Everything pikelandpropertygroup.com needs: premium guest posts, high-quality backlinks, on-page SEO, local SEO, web development, SaaS tools and automation tools — long-term DR/DA/TF gains in competitive markets. The plan remains focused on natural relevance, credible sources, balanced optimization, measurable search gains, and sustainable long-term execution. · Search Rank Central — A ... | R62: https://pikelandpropertygroup.com/ | S62: 301 | T62: text | U62: TRUE | V62: FALSE | W62: TRUE | X62: FALSE | Y62: FALSE | Z62: FALSE | AA62: TRUE | AD62: pagefound | AE62: 46232.116 | AF62: 46232.116 | AI62: Article > Guide | AJ62: Internet > Web services > SEO and marketing; Business > Marketing > Marketing
A63: seoedge.shop — The 120-Day Traffic Services Case Study for Financial Advisory — Placements, Anchors, Rankings Before and After | B63: https://seoedge.shop/a3dl99t-build-unstoppable-law-firm-serp-local-seo-crowd-links-traffic-playbook/ | C63: en | E63: 200 | F63: 0.7 | G63: 0 | H63: 0 | I63: 0 | J63: 5183 | K63: 6068 | L63: 0 | M63: 0 | N63: https://www.pikelandpropertygroup.com/ | P63: Boost pikelandpropertygroup.com using high-DR backlinks, editorial guest posts, on-page SEO, local SEO, web development, SaaS tools and automation tools for sustained DR/DA/TF uplift with full transparency. | R63: https://pikelandpropertygroup.com/ | S63: 301 | T63: text | U63: TRUE | V63: FALSE | W63: TRUE | X63: FALSE | Y63: FALSE | Z63: FALSE | AA63: TRUE | AD63: pagefound | AE63: 46204.103 | AF63: 46232.165 | AI63: Article > Research | AJ63: Business > Marketing > Marketing; Internet > Web services > SEO and marketing; Finance > Management
A64: Page 1 Rankings for Law Firm Using Only Link Insertions — Is This Possible in 2026? My Real Experiment — primebacklinks.shop | B64: https://primebacklinks.shop/alrp01b-90-day-serp-climb-saas-combined-editorial-links-traffic-services-position1/ | C64: en | E64: 200 | F64: 0.8 | G64: 0 | H64: 0 | I64: 0 | J64: 5693 | K64: 6661 | L64: 0 | M64: 0 | N64: https://www.pikelandpropertygroup.com/ | P64: Take pikelandpropertygroup.com to page one with contextual backlinks, premium guest posts, on-page SEO, local SEO, custom web development, SaaS tools plus automation tools — sustained DR/DA/TF uplift for every sector. | R64: https://pikelandpropertygroup.com/ | S64: 301 | T64: text | U64: TRUE | V64: FALSE | W64: TRUE | X64: FALSE | Y64: FALSE | Z64: FALSE | AA64: TRUE | AD64: pagefound | AE64: 46194.616 | AF64: 46223.234 | AI64: Article > Opinion | AJ64: Internet > Web services > SEO and marketing; Business > Marketing > Marketing; Government > Legal
A65: 🛸 Dark Side Links – Dark/White Hat Link Building Services – Eleotin Spanish | B65: https://m.eleotinspanish.com/bez-rubriki/dark-side-links-dark-white-hat-link-building-1342/ | C65: en | D65: ecommerce, wordpress | E65: 200 | F65: 8 | G65: 0 | H65: 0 | I65: 0 | J65: 3105 | K65: 3386 | L65: 0 | M65: 0 | N65: https://www.pikelandpropertygroup.com/ | O65: DARK HAT AND WHITE HAT BACKLINKS | P65: JOIN OUR TELEGRAM https://t.me/s/darksidelinks | Q65: FOR CHEAP AND GOOGLE FRIENDLY BACKLINKS | T65: text | U65: FALSE | V65: FALSE | W65: TRUE | X65: FALSE | Y65: FALSE | Z65: FALSE | AA65: TRUE | AD65: linkfound | AE65: 46139.112 | AF65: 46139.112 | AI65: Site page > Services | AJ65: Internet > Web services > SEO and marketing; Business > Marketing > Marketing
A66: linksnexa.shop — Page 1 Rankings for Law Firm Using Only Link Insertions — Is This Possible in 2026? My Real Experiment | B66: https://linksnexa.shop/alrp01b-90-day-serp-climb-saas-combined-editorial-links-traffic-services-position1/ | C66: en | E66: 200 | F66: 0.7 | G66: 0 | H66: 0 | I66: 0 | J66: 5695 | K66: 6664 | L66: 0 | M66: 0 | N66: https://www.pikelandpropertygroup.com/ | P66: Take pikelandpropertygroup.com to page one with contextual backlinks, premium guest posts, on-page SEO, local SEO, custom web development, SaaS tools plus automation tools — sustained DR/DA/TF uplift for every sector. | R66: https://pikelandpropertygroup.com/ | S66: 301 | T66: text | U66: TRUE | V66: FALSE | W66: TRUE | X66: FALSE | Y66: FALSE | Z66: FALSE | AA66: TRUE | AD66: pagefound | AE66: 46204.375 | AF66: 46232.452 | AI66: Article > Opinion | AJ66: Internet > Web services > SEO and marketing; Business > Marketing > Marketing; Government > Legal
A67: How Crowd Links Compares to Sidebar Links for Medical — Cost, Speed, Quality, and Final Ranking Outcomes — linkchest.shop | B67: https://linkchest.shop/w4g3ttx-18-month-saas-tools-journey-dental-page5-to-dr40/ | C67: en | E67: 200 | F67: 0.7 | G67: 0 | H67: 0 | I67: 11 | J67: 8297 | K67: 9736 | L67: 0 | M67: 0 | N67: https://www.pikelandpropertygroup.com/ | P67: Boost pikelandpropertygroup.com using premium guest posts, contextual backlinks, on-page and local SEO, conversion-focused web development, SaaS tools and automation tools for durable DR/DA/TF gains across any niche. | R67: https://pikelandpropertygroup.com/ | S67: 301 | T67: text | U67: TRUE | V67: FALSE | W67: TRUE | X67: FALSE | Y67: FALSE | Z67: FALSE | AA67: TRUE | AD67: pagefound | AE67: 46194.115 | AF67: 46222.168 | AI67: Article > Comparison | AJ67: Internet > Web services > SEO and marketing; Business > Marketing > Marketing
A68: How I Used a Traffic Service to Validate My Ymyl Niche Before Investing in Full SEO — The Smart Way to Test Markets — AuthorityBacklinks — Where Domain Authority Is Built Not Promised. | B68: https://authoritybacklinks.shop/98iq3cx-rankings-that-stick-post-penalty-seo-services-durable-medical-vs-cheap-bulk/ | C68: en | E68: 200 | F68: 54 | G68: 0 | H68: 0 | I68: 0 | J68: 8287 | K68: 9899 | L68: 0 | M68: 0 | N68: https://www.pikelandpropertygroup.com/ | P68: No-Risk Strategic Guest Posts + High-TF Dofollow Backlinks for pikelandpropertygroup.com — Skyrocket Ahrefs Domain Rating DR • Moz Domain Authority DA • Majestic Trust Flow TF Guaranteed — Outrank Every Competitor on Google — Any Niche • Any Language • Worldwide | R68: https://pikelandpropertygroup.com/ | S68: 301 | T68: text | U68: TRUE | V68: FALSE | W68: TRUE | X68: FALSE | Y68: FALSE | Z68: FALSE | AA68: TRUE | AD68: linkfound | AE68: 46152.204 | AF68: 46166.219 | AI68: Article > Guide | AJ68: Internet > Web services > SEO and marketing; Business > Marketing > Marketing
A69: The 120-Day Traffic Services Case Study for Financial Advisory — Placements, Anchors, Rankings Before and After — seobox.shop | B69: https://seobox.shop/a3dl99t-build-unstoppable-law-firm-serp-local-seo-crowd-links-traffic-playbook/ | C69: en | E69: 200 | F69: 0.7 | G69: 0 | H69: 0 | I69: 0 | J69: 5174 | K69: 6062 | L69: 0 | M69: 0 | N69: https://www.pikelandpropertygroup.com/ | P69: Boost pikelandpropertygroup.com using high-DR backlinks, editorial guest posts, on-page SEO, local SEO, web development, SaaS tools and automation tools for sustained DR/DA/TF uplift with full transparency. | R69: https://pikelandpropertygroup.com/ | S69: 301 | T69: text | U69: TRUE | V69: FALSE | W69: TRUE | X69: FALSE | Y69: FALSE | Z69: FALSE | AA69: TRUE | AD69: linkfound | AE69: 46213.338 | AF69: 46213.338 | AI69: Article > Research | AJ69: Business > Marketing > Marketing; Internet > Web services > SEO and marketing; Finance > Management > Portfolio
A70: How Blogroll Links Helped My Local Business Site rebuilt DR after a domain migration — The Complete Case Study With Full Data Transparency — linkbundle.shop | B70: https://linkbundle.shop/dha0jp7-serp-domination-blueprint-real-estate-rank-using-guest-posts-crowd-links/ | C70: en | E70: 200 | F70: 0.8 | G70: 0 | H70: 0 | I70: 11 | J70: 8297 | K70: 9736 | L70: 0 | M70: 0 | N70: https://www.pikelandpropertygroup.com/ | P70: Rank pikelandpropertygroup.com higher with guest posts and backlinks, on-page SEO, local SEO, web development, SaaS integrations and automation tools — durable DR/DA/TF gains with clean reporting. | R70: https://pikelandpropertygroup.com/ | S70: 301 | T70: text | U70: TRUE | V70: FALSE | W70: TRUE | X70: FALSE | Y70: FALSE | Z70: FALSE | AA70: TRUE | AD70: pagefound | AE70: 46194.292 | AF70: 46222.34 | AI70: Article > Research | AJ70: Internet > Web services > SEO and marketing; Business > Marketing > Marketing
A71: seopicks.shop — The 120-Day Traffic Services Case Study for Financial Advisory — Placements, Anchors, Rankings Before and After | B71: https://seopicks.shop/a3dl99t-build-unstoppable-law-firm-serp-local-seo-crowd-links-traffic-playbook/ | C71: en | E71: 200 | F71: 0.7 | G71: 0 | H71: 0 | I71: 18 | J71: 5183 | K71: 6068 | L71: 0 | M71: 0 | N71: https://www.pikelandpropertygroup.com/ | P71: Boost pikelandpropertygroup.com using high-DR backlinks, editorial guest posts, on-page SEO, local SEO, web development, SaaS tools and automation tools for sustained DR/DA/TF uplift with full transparency. | R71: https://pikelandpropertygroup.com/ | S71: 301 | T71: text | U71: TRUE | V71: FALSE | W71: TRUE | X71: FALSE | Y71: FALSE | Z71: FALSE | AA71: TRUE | AD71: pagefound | AE71: 46201.977 | AF71: 46230.014 | AI71: Article > Research | AJ71: Business > Marketing > Marketing; Internet > Web services > SEO and marketing; Finance > Management
A72: seowares.shop — The 120-Day Traffic Services Case Study for Financial Advisory — Placements, Anchors, Rankings Before and After | B72: https://seowares.shop/a3dl99t-build-unstoppable-law-firm-serp-local-seo-crowd-links-traffic-playbook/ | C72: en | E72: 200 | F72: 0.7 | G72: 0 | H72: 0 | I72: 0 | J72: 5175 | K72: 6071 | L72: 0 | M72: 0 | N72: https://www.pikelandpropertygroup.com/ | P72: Boost pikelandpropertygroup.com using high-DR backlinks, editorial guest posts, on-page SEO, local SEO, web development, SaaS tools and automation tools for sustained DR/DA/TF uplift with full transparency. | R72: https://pikelandpropertygroup.com/ | S72: 301 | T72: text | U72: TRUE | V72: FALSE | W72: TRUE | X72: FALSE | Y72: FALSE | Z72: FALSE | AA72: TRUE | AD72: pagefound | AE72: 46202.68 | AF72: 46230.694 | AI72: Article > Research | AJ72: Internet > Web services > SEO and marketing; Business > Marketing > Marketing; Finance
A73: 🛸 Dark Side Links – Dark/White Hat Link Building Services – CTT Beats | B73: https://cttbeats.capetownthing.co.za/2026/02/21/dark-side-links-dark-white-hat-link-building-1342/ | C73: en | D73: wordpress | E73: 200 | F73: 11 | G73: 0 | H73: 0 | I73: 0 | J73: 3111 | K73: 3391 | L73: 0 | M73: 0 | N73: https://www.pikelandpropertygroup.com/ | O73: DARK HAT AND WHITE HAT BACKLINKS | P73: JOIN OUR TELEGRAM https://t.me/s/darksidelinks | Q73: FOR CHEAP AND GOOGLE FRIENDLY BACKLINKS | T73: text | U73: FALSE | V73: FALSE | W73: TRUE | X73: FALSE | Y73: FALSE | Z73: FALSE | AA73: TRUE | AD73: linkfound | AE73: 46131.653 | AF73: 46131.653 | AI73: Site page > Services | AJ73: Internet > Web services > SEO and marketing; Business > Marketing > Marketing
A74: Organic Rank Systems — Advanced systems designed for organic rankings, qualified traffic and sustainable search growth to strengthen search presence and attract relevant visitors — How I Stacked SaaS Tools With Tiered Link Building for YMYL — The Dual Strategy That Doubled My Ranking Speed — Featuring real campaign examples, budget allocation guidance, and future campaign planning | B74: https://organicranksystems.shop/31c0bcb9b-homepage-links-helped-law-firm-site-restored-rankings-after-algorithm-update-complete-case-study-data-full-ranking-workflow-research-execution-and-analysis-for-long-term-search-success/ | C74: en | E74: 200 | F74: 0 | G74: 0 | H74: 0 | I74: 0 | J74: 6721 | K74: 7849 | L74: 0 | M74: 0 | N74: https://www.pikelandpropertygroup.com/ | P74: pikelandpropertygroup.com: high-quality backlinks, guest posts, on-page and local SEO, custom web development, SaaS tools and automation tools, all driving long-term DR/DA/TF gains for any business size. Every campaign includes niche-relevance checks, diversified anchor planning, placement review, and transparent progress tracking. · Organic Rank Systems — Advanced systems designed for organic ... | R74: https://pikelandpropertygroup.com/ | S74: 301 | T74: text | U74: TRUE | V74: FALSE | W74: TRUE | X74: FALSE | Y74: FALSE | Z74: FALSE | AA74: TRUE | AD74: pagefound | AE74: 46232.702 | AF74: 46232.702 | AI74: Article > Guide | AJ74: Internet > Web services > SEO and marketing; Business > Marketing > Marketing
A75: How I Used Local SEO and recovered lost traffic fully for My YMYL Site — Month-by-Month Progress Documentation — Breaking Down a complete cost and timeline breakdown, budget allocation guidance, and repeatable SEO takeaways — B803FAD0E | B75: https://domainrankteam.shop/b803fad0e-ranking-velocity-blueprint-law-firm-rank-using-niche-edits-high-da-guest-posts-practical-execution-roadmap-mistakes-risks-and-solutions-for-competitive-serp-results/ | C75: en | E75: 200 | F75: 0 | G75: 0 | H75: 0 | I75: 0 | J75: 6729 | K75: 7852 | L75: 0 | M75: 0 | N75: https://www.pikelandpropertygroup.com/ | P75: Complete SEO for pikelandpropertygroup.com: guest posts, backlinks, on-page and local SEO, web development, SaaS tools and workflow automation tools, delivering steady DR/DA/TF growth for local or global targets. The complete process includes website review, competitor benchmarking, anchor-risk control, placement validation, and practical growth recommendations. · b803fad0e | R75: https://pikelandpropertygroup.com/ | S75: 301 | T75: text | U75: TRUE | V75: FALSE | W75: TRUE | X75: FALSE | Y75: FALSE | Z75: FALSE | AA75: TRUE | AD75: pagefound | AE75: 46225.97 | AF75: 46225.97 | AI75: Article > Guide | AJ75: Internet > Web services > SEO and marketing; Business > Marketing > Marketing
A76: The 120-Day Traffic Services Case Study for Financial Advisory — Placements, Anchors, Rankings Before and After — rankcart.shop | B76: https://rankcart.shop/a3dl99t-build-unstoppable-law-firm-serp-local-seo-crowd-links-traffic-playbook/ | C76: en | E76: 200 | F76: 0.7 | G76: 0 | H76: 0 | I76: 4 | J76: 5183 | K76: 6068 | L76: 0 | M76: 0 | N76: https://www.pikelandpropertygroup.com/ | P76: Boost pikelandpropertygroup.com using high-DR backlinks, editorial guest posts, on-page SEO, local SEO, web development, SaaS tools and automation tools for sustained DR/DA/TF uplift with full transparency. | R76: https://pikelandpropertygroup.com/ | S76: 301 | T76: text | U76: TRUE | V76: FALSE | W76: TRUE | X76: FALSE | Y76: FALSE | Z76: FALSE | AA76: TRUE | AD76: linkfound | AE76: 46206.309 | AF76: 46220.343 | AI76: Article > Research | AJ76: Business > Marketing > Marketing; Internet > Web services > SEO and marketing; Finance > Management > Portfolio
A77: backlinkshop.shop — Link Insertions for New Health & Wellness Websites — Is It Safe to Start From Day 1 or Should You Wait 3 Months? | B77: https://backlinkshop.shop/pignhys-saas-tools-vs-niche-edits-saas-cost-speed-quality-ranking-outcomes/ | C77: en | E77: 200 | F77: 0.8 | G77: 0 | H77: 0 | I77: 5 | J77: 8308 | K77: 9756 | L77: 0 | M77: 0 | N77: https://www.pikelandpropertygroup.com/ | P77: Boost pikelandpropertygroup.com using backlinks and guest posts, on-page SEO, local SEO, custom web development, SaaS integrations and automation tools for rising DR/DA/TF scores across all markets. | R77: https://pikelandpropertygroup.com/ | S77: 301 | T77: text | U77: TRUE | V77: FALSE | W77: TRUE | X77: FALSE | Y77: FALSE | Z77: FALSE | AA77: TRUE | AD77: pagefound | AE77: 46184.449 | AF77: 46226.651 | AI77: Article > Guide | AJ77: Internet > Web services > SEO and marketing; Health > Medical services > Doctors' offices
A78: Savvy - Pikeland Property Group | B78: https://jobs.trysavvy.co/c/pikeland-property-group | C78: en | E78: 200 | F78: 1.1 | G78: 0 | H78: 0 | I78: 0 | J78: 4 | K78: 5 | L78: 0 | M78: 0 | N78: https://www.pikelandpropertygroup.com/ | P78: Pikeland Property Group's website | R78: https://pikelandpropertygroup.com/ | S78: 301 | T78: text | U78: TRUE | V78: FALSE | W78: FALSE | X78: FALSE | Y78: FALSE | Z78: FALSE | AA78: TRUE | AD78: pagefound | AE78: 45886.688 | AF78: 46231.771
A79: pikelandpropertygroup.com Traffic, Tech Stack & Company Profile | Real Estate Listings [June 2026] | Klazify | B79: https://www.klazify.com/website/pikelandpropertygroup.com | C79: en | E79: 200 | F79: 29 | G79: 0 | H79: 7401 | I79: 0 | J79: 4 | K79: 7 | L79: 0 | M79: 0 | N79: https://www.pikelandpropertygroup.com/ | P79: pikelandpropertygroup.com | R79: https://pikelandpropertygroup.com/ | S79: 301 | T79: text | U79: FALSE | V79: FALSE | W79: FALSE | X79: FALSE | Y79: FALSE | Z79: FALSE | AA79: TRUE | AD79: pagefound | AE79: 46196.231 | AF79: 46196.231 | AH79: Klazify Inc
A80: Best Sidebar Link Services for News in 2025 — I Reviewed Every Major Provider and Only 3 Actually Delivered Real Authority Gains — pbnseolinks.shop | B80: https://pbnseolinks.shop/yna9erf-pbn-backlinks-brand-new-portfolio-sites-smart-fresh-domain-or-wait/ | C80: en | E80: 200 | F80: 53 | G80: 0 | H80: 0 | I80: 6 | J80: 8294 | K80: 9899 | L80: 0 | M80: 0 | N80: https://www.pikelandpropertygroup.com/ | P80: pikelandpropertygroup.com Page 1 Guaranteed: Manual Outreach Guest Posts + Dofollow Backlinks + Majestic Trust Flow TF • Ahrefs Domain Rating DR • Moz Domain Authority DA + Dominate Google Search Results | R80: https://pikelandpropertygroup.com/ | S80: 301 | T80: text | U80: TRUE | V80: FALSE | W80: TRUE | X80: FALSE | Y80: FALSE | Z80: FALSE | AA80: TRUE | AD80: pagefound | AE80: 46149.681 | AF80: 46219.978 | AI80: Article > Review | AJ80: Internet > Web services > SEO and marketing; Business > Marketing > Marketing
A81: Link Growth Insights — Research, guidance and practical insights for authority link acquisition, referral visibility and ranking growth to strengthen search presence and attract relevant visitors — How PBN Backlinks Compares to Web Development for Local Business — Cost, Speed, Quality, and Final Ranking Outcomes — Covering step-by-step optimization guidance, quality-control requirements, and future campaign planning | B81: https://linkgrowthinsights.shop/962d3b9d8-algorithm-hit-to-dr50-finance-18-month-strategy-only-dofollow-backlinks-complete-implementation-guide-budget-links-and-content-for-consistent-traffic-growth/ | C81: en | E81: 200 | F81: 0 | G81: 0 | H81: 0 | I81: 0 | J81: 6735 | K81: 7857 | L81: 0 | M81: 0 | N81: https://www.pikelandpropertygroup.com/ | P81: Complete SEO for pikelandpropertygroup.com: high-quality backlinks, guest posts, on-page and local SEO, custom web development, SaaS tools and automation tools, delivering stronger DR, DA and TF worldwide. Every delivery follows a structured plan for content relevance, link diversity, authority checks, traffic measurement, and ongoing optimization. · Link Growth Insights — Research, guidance ... | R81: https://pikelandpropertygroup.com/ | S81: 301 | T81: text | U81: TRUE | V81: FALSE | W81: TRUE | X81: FALSE | Y81: FALSE | Z81: FALSE | AA81: TRUE | AD81: linkfound | AE81: 46226.178 | AF81: 46226.178 | AI81: Article > Comparison | AJ81: Internet > Web services > SEO and marketing; Business > Marketing > Marketing
A82: The 120-Day Tiered Link Building Case Study for Fintech — Placements, Anchors, Rankings Before and After — Breaking Down clear planning and execution details, transparent measurement methods, and competitive search-positioning lessons — 7DC238EE8 — SEO Growth Pipeline — A structured performance pipeline for sustainable SEO growth, content visibility and qualified organic traffic for measurable search performance and long-term website growth | B82: https://seogrowthpipeline.shop/7dc238ee8-roi-dr-boost-services-ymyl-cost-per-link-vs-revenue-12-months-full-ranking-workflow-research-execution-and-analysis-for-competitive-serp-results/ | C82: en | E82: 200 | F82: 0 | G82: 0 | H82: 0 | I82: 0 | J82: 6721 | K82: 7844 | L82: 0 | M82: 0 | N82: https://www.pikelandpropertygroup.com/ | P82: Take pikelandpropertygroup.com to page one with high-quality backlinks, guest posts, on-page and local SEO, custom web development, SaaS tools and automation tools — a clear DR/DA/TF lift for any industry. Every delivery follows a structured plan for content relevance, link diversity, authority checks, traffic measurement, and ongoing optimization. · 7dc238ee8 | R82: https://pikelandpropertygroup.com/ | S82: 301 | T82: text | U82: TRUE | V82: FALSE | W82: TRUE | X82: FALSE | Y82: FALSE | Z82: FALSE | AA82: TRUE | AD82: linkfound | AE82: 46224.071 | AF82: 46224.071 | AI82: Article > Research | AJ82: Internet > Web services > SEO and marketing; Business > Marketing > Marketing; Finance > Investing
A83: I Bought On-Page SEO for My Medical Site — Full 12-Month Review of Metrics, Rankings, and Traffic Impact — Supported by step-by-step optimization guidance, technical considerations, and sustainable search visibility recommendations — 74D4C360B | B83: https://linkcollective.shop/74d4c360b-blogroll-links-helped-health-site-grew-domain-authority-past-dr30-complete-case-study-data-complete-implementation-guide-authority-traffic-and-conversions-for-better-google-positions/ | C83: en | E83: 200 | F83: 0 | G83: 0 | H83: 0 | I83: 0 | J83: 6721 | K83: 7846 | L83: 0 | M83: 0 | N83: https://www.pikelandpropertygroup.com/ | P83: pikelandpropertygroup.com gets premium guest posts, contextual backlinks, on-page and local SEO, conversion-focused web development, SaaS tools and automation tools, together driving a measurable DR/DA/TF boost tailored to your vertical. The strategy also covers competitor research, natural anchor distribution, quality verification, and clear monthly performance reporting. · 74d4c360b | R83: https://pikelandpropertygroup.com/ | S83: 301 | T83: text | U83: TRUE | V83: FALSE | W83: TRUE | X83: FALSE | Y83: FALSE | Z83: FALSE | AA83: TRUE | AD83: pagefound | AE83: 46227.168 | AF83: 46227.168 | AI83: Article > Review | AJ83: Internet > Web services > SEO and marketing; Business > Marketing > Marketing; Health > Medical services > Doctors' offices
A84: ✅ Website Stats 📊 | B84: https://ready.pro/stats/50887 | C84: en | E84: 200 | F84: 35 | G84: 0 | H84: 0 | I84: 0 | J84: 3717 | K84: 4182 | L84: 0 | M84: 0 | N84: https://www.pikelandpropertygroup.com/ | O84: Homepage | P84: pikelandpropertygroup.com | Q84: &nbsp | R84: https://pikelandpropertygroup.com/ | S84: 301 | T84: text | U84: TRUE | V84: TRUE | W84: TRUE | X84: FALSE | Y84: FALSE | Z84: FALSE | AA84: TRUE | AD84: pagefound | AE84: 46102.855 | AF84: 46221.926 | AI84: Listing collection > Business | AJ84: Internet > Web services > Analytics; Reference
A85: Allinone.co.in | B85: https://www.allinone.co.in/domains/210228/7878597970d2c2560979b208f3db6c22/ | C85: en | E85: 200 | F85: 8 | G85: 0 | H85: 0 | I85: 0 | J85: 1039 | K85: 1207 | L85: 0 | M85: 0 | N85: https://www.pikelandpropertygroup.com/ | P85: pikelandpropertygroup.com | Q85: Other Pages | R85: https://pikelandpropertygroup.com/ | S85: 301 | T85: text | U85: TRUE | V85: TRUE | W85: TRUE | X85: FALSE | Y85: FALSE | Z85: FALSE | AA85: TRUE | AD85: linkfound | AE85: 46170.281 | AF85: 46222.778
A86: I Bought Curated Niche Edit Backlinks for My Affiliate Site — The Honest Before-and-After Ranking Report With Full Data — linkseopro.shop | B86: https://linkseopro.shop/foaho4d-proven-serp-domination-strategy-cbd-traffic-links-on-page-seo-rank/ | C86: en | E86: 200 | F86: 53 | G86: 0 | H86: 0 | I86: 1 | J86: 8292 | K86: 9899 | L86: 0 | M86: 0 | N86: https://www.pikelandpropertygroup.com/ | P86: pikelandpropertygroup.com Permanent Top Google Rankings: Fast-Index Guest Posts + Quality Dofollow Backlinks • Raise Ahrefs Domain Rating DR + Moz Domain Authority DA + Majestic Trust Flow TF | R86: https://pikelandpropertygroup.com/ | S86: 301 | T86: text | U86: TRUE | V86: FALSE | W86: TRUE | X86: FALSE | Y86: FALSE | Z86: FALSE | AA86: TRUE | AD86: pagefound | AE86: 46151.281 | AF86: 46221.459 | AI86: Article > Review | AJ86: Internet > Web services > SEO and marketing; Business > Marketing > Marketing
A87: Where to buy 🚀 aged domains and backlinks 🔥 | 1204-6378 | B87: https://www.getwebsiteworth.com/1add20ae4edb6e37d8ff4b4d2677f240-l/ | C87: en | D87: wordpress | E87: 200 | F87: 18 | G87: 0 | H87: 0 | I87: 0 | J87: 9164 | K87: 9997 | L87: 0 | M87: 0 | N87: https://www.pikelandpropertygroup.com/ | O87: pikelandia.com pikelandmotors.com | P87: pikelandpropertygroup.com | Q87: pikelandscape.com pikelandschools.com | R87: https://pikelandpropertygroup.com/ | S87: 301 | T87: text | U87: TRUE | V87: FALSE | W87: FALSE | X87: FALSE | Y87: FALSE | Z87: FALSE | AA87: TRUE | AD87: pagefound | AE87: 46051.485 | AF87: 46209.836 | AI87: Listing > Product | AJ87: Internet > Web services > SEO and marketing
A88: rankgoods.shop — The 120-Day Traffic Services Case Study for Financial Advisory — Placements, Anchors, Rankings Before and After | B88: https://rankgoods.shop/a3dl99t-build-unstoppable-law-firm-serp-local-seo-crowd-links-traffic-playbook/ | C88: en | E88: 200 | F88: 0.7 | G88: 0 | H88: 0 | I88: 8 | J88: 5175 | K88: 6070 | L88: 0 | M88: 0 | N88: https://www.pikelandpropertygroup.com/ | P88: Boost pikelandpropertygroup.com using high-DR backlinks, editorial guest posts, on-page SEO, local SEO, web development, SaaS tools and automation tools for sustained DR/DA/TF uplift with full transparency. | R88: https://pikelandpropertygroup.com/ | S88: 301 | T88: text | U88: TRUE | V88: FALSE | W88: TRUE | X88: FALSE | Y88: FALSE | Z88: FALSE | AA88: TRUE | AD88: pagefound | AE88: 46201.334 | AF88: 46229.353 | AI88: Article > Research | AJ88: Business > Marketing > Marketing; Internet > Web services > SEO and marketing; Finance
A89: Link SEO Insights — Research, guidance and practical insights for contextual backlinks, link strategy and organic search optimization to improve authority, relevance and qualified search traffic — SERP Climb Blueprint for Real Estate — How to Rank Using Press Release Links and Sidebar Links — Covering a detailed execution roadmap, content and link-quality checks, and long-term organic growth lessons | B89: https://linkseoinsights.shop/9159153f0-best-guest-posts-dental-2026-compared-8-providers-roi-proven-optimization-process-research-execution-and-analysis-for-reliable-page-one-progress/ | C89: en | E89: 200 | F89: 0 | G89: 0 | H89: 0 | I89: 0 | J89: 6735 | K89: 7857 | L89: 0 | M89: 0 | N89: https://www.pikelandpropertygroup.com/ | P89: Take pikelandpropertygroup.com to page one with premium guest posts, contextual backlinks, on-page and local SEO, conversion-focused web development, SaaS tools and automation tools — a healthier DR/DA/TF profile for new or established sites. The service also includes technical review, content alignment, backlink-quality screening, conversion considerations, and transparent milestone reporting. ... | R89: https://pikelandpropertygroup.com/ | S89: 301 | T89: text | U89: TRUE | V89: FALSE | W89: TRUE | X89: FALSE | Y89: FALSE | Z89: FALSE | AA89: TRUE | AD89: linkfound | AE89: 46231.891 | AF89: 46231.891 | AI89: Article > Guide | AJ89: Internet > Web services > SEO and marketing; Real estate > Real estate services; Business > Marketing > Marketing
A90: Acquire.co.in | B90: https://www.acquire.co.in/domains/210228/d2fb8156e0b5b4a7a0b0708356bfd041/ | C90: en | E90: 200 | F90: 11 | G90: 0 | H90: 0 | I90: 0 | J90: 1038 | K90: 1204 | L90: 0 | M90: 0 | N90: https://www.pikelandpropertygroup.com/ | P90: pikelandpropertygroup.com | Q90: Other Pages | R90: https://pikelandpropertygroup.com/ | S90: 301 | T90: text | U90: TRUE | V90: TRUE | W90: TRUE | X90: FALSE | Y90: FALSE | Z90: FALSE | AA90: TRUE | AD90: pagefound | AE90: 46164.846 | AF90: 46164.846
A91: seosupply.shop — The 120-Day Traffic Services Case Study for Financial Advisory — Placements, Anchors, Rankings Before and After | B91: https://seosupply.shop/a3dl99t-build-unstoppable-law-firm-serp-local-seo-crowd-links-traffic-playbook/ | C91: en | E91: 200 | F91: 0.7 | G91: 0 | H91: 0 | I91: 0 | J91: 5183 | K91: 6068 | L91: 0 | M91: 0 | N91: https://www.pikelandpropertygroup.com/ | P91: Boost pikelandpropertygroup.com using high-DR backlinks, editorial guest posts, on-page SEO, local SEO, web development, SaaS tools and automation tools for sustained DR/DA/TF uplift with full transparency. | R91: https://pikelandpropertygroup.com/ | S91: 301 | T91: text | U91: TRUE | V91: FALSE | W91: TRUE | X91: FALSE | Y91: FALSE | Z91: FALSE | AA91: TRUE | AD91: pagefound | AE91: 46204.148 | AF91: 46232.192 | AI91: Article > Research | AJ91: Internet > Web services > SEO and marketing; Business > Marketing > Marketing; Finance
A92: rankdepot.shop — The 120-Day Traffic Services Case Study for Financial Advisory — Placements, Anchors, Rankings Before and After | B92: https://rankdepot.shop/a3dl99t-build-unstoppable-law-firm-serp-local-seo-crowd-links-traffic-playbook/ | C92: en | E92: 200 | F92: 0.7 | G92: 0 | H92: 0 | I92: 11 | J92: 5183 | K92: 6068 | L92: 0 | M92: 0 | N92: https://www.pikelandpropertygroup.com/ | P92: Boost pikelandpropertygroup.com using high-DR backlinks, editorial guest posts, on-page SEO, local SEO, web development, SaaS tools and automation tools for sustained DR/DA/TF uplift with full transparency. | R92: https://pikelandpropertygroup.com/ | S92: 301 | T92: text | U92: TRUE | V92: FALSE | W92: TRUE | X92: FALSE | Y92: FALSE | Z92: FALSE | AA92: TRUE | AD92: pagefound | AE92: 46204.854 | AF92: 46232.862 | AI92: Article > Research | AJ92: Business > Marketing > Marketing; Internet > Web services > SEO and marketing; Finance > Management
A93: Where to buy 🚀 aged domains and backlinks 🔥 | 1204-6378 | B93: https://tunca.org/1add20ae4edb6e37d8ff4b4d2677f240-l/ | C93: en | D93: wordpress | E93: 200 | F93: 4.3 | G93: 0 | H93: 0 | I93: 0 | J93: 9167 | K93: 9997 | L93: 0 | M93: 0 | N93: https://www.pikelandpropertygroup.com/ | O93: pikelandia.com pikelandmotors.com | P93: pikelandpropertygroup.com | Q93: pikelandscape.com pikelandschools.com | R93: https://pikelandpropertygroup.com/ | S93: 301 | T93: text | U93: TRUE | V93: FALSE | W93: FALSE | X93: FALSE | Y93: FALSE | Z93: FALSE | AA93: TRUE | AD93: linkfound | AE93: 46068.124 | AF93: 46142.051 | AI93: Listing > Product | AJ93: Internet > Web services > SEO and marketing
A94: Page 1 Rankings for YMYL Using Only Niche Edits — Is This Possible in 2025? My Real Experiment — Featuring a detailed execution roadmap, common mistakes to avoid, and competitive search-positioning lessons — SEO Link Central — A central strategy and resource hub for strategic link building, authority development and search optimization for practical SEO progress across competitive search results | B94: https://seolinkcentral.shop/e37eb4393-used-tiered-link-building-took-every-keyword-page1-legal-site-month-by-month-progress-practical-execution-roadmap-planning-testing-and-tracking-for-better-google-positions/ | C94: en | E94: 200 | F94: 0 | G94: 0 | H94: 0 | I94: 0 | J94: 6735 | K94: 7857 | L94: 0 | M94: 0 | N94: https://www.pikelandpropertygroup.com/ | P94: Strengthen pikelandpropertygroup.com through backlinks and guest posts, on-page SEO, local SEO, custom web development, SaaS integrations and automation tools for real DR/DA/TF improvement for any business size. The service also includes technical review, content alignment, backlink-quality screening, conversion considerations, and transparent milestone reporting. · SEO Link Central — A central ... | R94: https://pikelandpropertygroup.com/ | S94: 301 | T94: text | U94: TRUE | V94: FALSE | W94: TRUE | X94: FALSE | Y94: FALSE | Z94: FALSE | AA94: TRUE | AD94: linkfound | AE94: 46227.292 | AF94: 46227.292 | AI94: Article > Guide | AJ94: Internet > Web services > SEO and marketing
A95: backlinkvault.shop — The 18-Month Authority Link Packages Case Study for Travel — Placements, Anchors, Rankings Before and After | B95: https://backlinkvault.shop/cyrihvi-invisible-to-page1-dental-6-month-strategy-only-tiered-link-building/ | C95: en | E95: 200 | F95: 0.8 | G95: 0 | H95: 0 | I95: 4 | J95: 8297 | K95: 9725 | L95: 0 | M95: 0 | N95: https://www.pikelandpropertygroup.com/ | P95: Everything pikelandpropertygroup.com needs: premium guest posts, high-quality backlinks, on-page SEO, local SEO, web development, SaaS tools and automation tools — real DR/DA/TF improvement built to last. | R95: https://pikelandpropertygroup.com/ | S95: 301 | T95: text | U95: TRUE | V95: FALSE | W95: TRUE | X95: FALSE | Y95: FALSE | Z95: FALSE | AA95: TRUE | AD95: pagefound | AE95: 46186.319 | AF95: 46229.008 | AI95: Article > Research | AJ95: Internet > Web services > SEO and marketing; Travel > Travel agencies > Other; Business > Marketing > Marketing
A96: The 120-Day Traffic Services Case Study for Financial Advisory — Placements, Anchors, Rankings Before and After — seodepot.shop | B96: https://seodepot.shop/a3dl99t-build-unstoppable-law-firm-serp-local-seo-crowd-links-traffic-playbook/ | C96: en | E96: 200 | F96: 0.7 | G96: 0 | H96: 0 | I96: 0 | J96: 5183 | K96: 6068 | L96: 0 | M96: 0 | N96: https://www.pikelandpropertygroup.com/ | P96: Boost pikelandpropertygroup.com using high-DR backlinks, editorial guest posts, on-page SEO, local SEO, web development, SaaS tools and automation tools for sustained DR/DA/TF uplift with full transparency. | R96: https://pikelandpropertygroup.com/ | S96: 301 | T96: text | U96: TRUE | V96: FALSE | W96: TRUE | X96: FALSE | Y96: FALSE | Z96: FALSE | AA96: TRUE | AD96: linkfound | AE96: 46206.298 | AF96: 46220.505 | AI96: Article > Research | AJ96: Business > Marketing > Marketing; Internet > Web services > SEO and marketing; Finance > Management > Portfolio
A97: I Bought Niche Edits for My Insurance Site — Full 18-Month Review of Metrics, Rankings, and Traffic Impact — Breaking Down step-by-step optimization guidance, reporting and tracking methods, and long-term organic growth lessons — SEO Link Company — A full-service company delivering strategic link building, authority development and search optimization for competitive rankings and dependable organic discovery | B97: https://seolinkcompany.shop/7302b1fd4-best-dofollow-backlinks-pharmaceutical-2026-compared-6-providers-roi-complete-implementation-guide-quality-checks-and-reporting-for-long-term-search-success/ | C97: en | E97: 200 | F97: 0 | G97: 0 | H97: 0 | I97: 0 | J97: 6720 | K97: 7845 | L97: 0 | M97: 0 | N97: https://www.pikelandpropertygroup.com/ | P97: Scale pikelandpropertygroup.com with high-quality backlinks, guest posts, on-page and local SEO, custom web development, SaaS tools and automation tools, earning DR/DA/TF gains that hold across any niche. We also prioritize topical relevance, clean placement standards, sensible campaign pacing, and reporting that connects work to outcomes. · SEO Link Company — A full-service company delivering ... | R97: https://pikelandpropertygroup.com/ | S97: 301 | T97: text | U97: TRUE | V97: FALSE | W97: TRUE | X97: FALSE | Y97: FALSE | Z97: FALSE | AA97: TRUE | AD97: linkfound | AE97: 46227.932 | AF97: 46227.932 | AI97: Article > Guide | AJ97: Internet > Web services > SEO and marketing; Business > Marketing > Marketing
A98: rankstock.shop — The 120-Day Traffic Services Case Study for Financial Advisory — Placements, Anchors, Rankings Before and After | B98: https://rankstock.shop/a3dl99t-build-unstoppable-law-firm-serp-local-seo-crowd-links-traffic-playbook/ | C98: en | E98: 200 | F98: 0.7 | G98: 0 | H98: 0 | I98: 9 | J98: 5175 | K98: 6070 | L98: 0 | M98: 0 | N98: https://www.pikelandpropertygroup.com/ | P98: Boost pikelandpropertygroup.com using high-DR backlinks, editorial guest posts, on-page SEO, local SEO, web development, SaaS tools and automation tools for sustained DR/DA/TF uplift with full transparency. | R98: https://pikelandpropertygroup.com/ | S98: 301 | T98: text | U98: TRUE | V98: FALSE | W98: TRUE | X98: FALSE | Y98: FALSE | Z98: FALSE | AA98: TRUE | AD98: pagefound | AE98: 46203.946 | AF98: 46231.967 | AI98: Article > Research | AJ98: Business > Marketing > Marketing; Internet > Web services > SEO and marketing; Finance > Management
A99: Backlink Partners — Trusted strategic partners for editorial backlinks, authority placements and off-page SEO to turn search visibility into consistent website growth — My 18-Month Automation Tools Journey for Financial Advisory — From Invisible to Top 5 for Every Keyword Using a Strategic SEO Service Stack — Along With step-by-step optimization guidance, budget allocation guidance, and stronger authority-building decisions | B99: https://backlinkpartners.shop/c48ce9025-stacked-high-da-guest-posts-dr-boost-services-saas-dual-strategy-doubled-ranking-speed-real-world-action-plan-planning-testing-and-tracking-for-sustainable-organic-growth/ | C99: en | E99: 200 | F99: 0 | G99: 0 | H99: 0 | I99: 0 | J99: 6729 | K99: 7854 | L99: 0 | M99: 0 | N99: https://www.pikelandpropertygroup.com/ | P99: pikelandpropertygroup.com: contextual backlinks, premium guest posts, on-page SEO, local SEO, custom web development, SaaS tools plus automation tools, all driving DR/DA/TF gains that hold at a sustainable pace. The service also includes technical review, content alignment, backlink-quality screening, conversion considerations, and transparent milestone reporting. · Backlink Partners — Trusted ... | R99: https://pikelandpropertygroup.com/ | S99: 301 | T99: text | U99: TRUE | V99: FALSE | W99: TRUE | X99: FALSE | Y99: FALSE | Z99: FALSE | AA99: TRUE | AD99: pagefound | AE99: 46231.624 | AF99: 46231.624 | AI99: Article > Guide | AJ99: Internet > Web services > SEO and marketing; Business > Marketing > Marketing
A100: linktrove.shop — My 45-Day Sidebar Links Journey for Healthcare — From Invisible to First-Page Domination Using a Strategic SEO Service Stack | B100: https://linktrove.shop/jopuv0n-page10-to-dr40-financial-advisory-6-month-strategy-only-crowd-links/ | C100: en | E100: 200 | F100: 0.7 | G100: 0 | H100: 0 | I100: 0 | J100: 8308 | K100: 9756 | L100: 0 | M100: 0 | N100: https://www.pikelandpropertygroup.com/ | P100: Everything pikelandpropertygroup.com needs: contextual backlinks, premium guest posts, on-page SEO, local SEO, custom web development, SaaS tools plus automation tools — stronger DR, DA and TF for any industry. | R100: https://pikelandpropertygroup.com/ | S100: 301 | T100: text | U100: TRUE | V100: FALSE | W100: TRUE | X100: FALSE | Y100: FALSE | Z100: FALSE | AA100: TRUE | AD100: pagefound | AE100: 46199.79 | AF100: 46227.815 | AI100: Article > Story | AJ100: Internet > Web services > SEO and marketing; Health > Medical services > Doctors' offices; Business > Business services > Consulting
...

Sheet Unique Anchor
A1: Anchor | B1: Count
A2: {=UNIQUE(Backlinks!P2:P179)} -> Visit Website | B2: =COUNTIF(Backlinks!P$2:P$179,"="&A2) -> 1
A3: pikelandpropertygroup.com | B3: =COUNTIF(Backlinks!P$2:P$179,"="&A3) -> 32
A4: JOIN OUR TELEGRAM https://t.me/s/darksidelinks | B4: =COUNTIF(Backlinks!P$2:P$179,"="&A4) -> 12
A5: Boost pikelandpropertygroup.com using high-DR backlinks, editorial guest posts, on-page SEO, local SEO, web development, SaaS tools and automation tools for sustained DR/DA/TF uplift with full transparency. | B5: =COUNTIF(Backlinks!P$2:P$179,"="&A5) -> 39
A6: Everything pikelandpropertygroup.com needs: guest posts and backlinks, on-page SEO, local SEO, web development, SaaS integrations and automation tools — a strong DR/DA/TF increase worldwide. The strategy also covers competitor research, natural anchor distribution, quality verification, and clear monthly performance reporting. · Site Rank Service — Managed professional services for site-wide ... | B6: =COUNTIF(Backlinks!P$2:P$179,"="&A6) -> 1
A7: Power up pikelandpropertygroup.com: guest posts, backlinks, on-page and local SEO, web development, SaaS tools and workflow automation tools for a clear DR/DA/TF lift in any language. Every delivery follows a structured plan for content relevance, link diversity, authority checks, traffic measurement, and ongoing optimization. · Site Rank Builders — Growth builders specializing in site-wide ... | B7: =COUNTIF(Backlinks!P$2:P$179,"="&A7) -> 1
A8: Professional backlinks for pikelandpropertygroup.com from agency that built authority for 400 websites | B8: =COUNTIF(Backlinks!P$2:P$179,"="&A8) -> 1
A9: pikelandpropertygroup.com gets guest posts and backlinks, on-page SEO, local SEO, web development, SaaS integrations and automation tools, together driving a noticeable DR/DA/TF rise with proven results. The complete process includes website review, competitor benchmarking, anchor-risk control, placement validation, and practical growth recommendations. · Top Rank Company — A full-service ... | B9: =COUNTIF(Backlinks!P$2:P$179,"="&A9) -> 1
A10: Take pikelandpropertygroup.com to page one with contextual backlinks, premium guest posts, on-page SEO, local SEO, custom web development, SaaS tools plus automation tools — sustained DR/DA/TF uplift for every sector. | B10: =COUNTIF(Backlinks!P$2:P$179,"="&A10) -> 6
A11: Grow pikelandpropertygroup.com with guest posts, backlinks, on-page and local SEO, web development, SaaS tools and workflow automation tools — balanced DR/DA/TF growth for any business size. | B11: =COUNTIF(Backlinks!P$2:P$179,"="&A11) -> 1
A12: pikelandpropertygroup.com — rank faster — clean PBN mix; grow Moz DA. | Visit Buyseolink.com for any Query | B12: =COUNTIF(Backlinks!P$2:P$179,"="&A12) -> 1
A13: Everything pikelandpropertygroup.com needs: contextual backlinks, premium guest posts, on-page SEO, local SEO, custom web development, SaaS tools plus automation tools — a measurable DR/DA/TF boost across any niche. The strategy also covers competitor research, natural anchor distribution, quality verification, and clear monthly performance reporting. · bbf101229 | B13: =COUNTIF(Backlinks!P$2:P$179,"="&A13) -> 1
A14: Everything pikelandpropertygroup.com needs: high-DR backlinks, editorial guest posts, on-page SEO, local SEO, web development, SaaS tools and automation tools — real DR/DA/TF improvement in competitive markets. | B14: =COUNTIF(Backlinks!P$2:P$179,"="&A14) -> 1
... A94: Scale pikelandpropertygroup.com with backlinks and guest posts, on-page SEO, local SEO, custom web development, SaaS integrations and automation tools, earning long-term DR/DA/TF gains with clean reporting. Each campaign combines strategic research, safe anchor variation, editorial quality control, progress monitoring, and recommendations for the next stage. · Top Rank Service — Managed ... | B94: =COUNTIF(Backlinks!P$2:P$179,"="&A94) -> 1
