Workbook

Sheet Referring domains
A1: Domain | B1: Is spam | C1: DR | D1: Dofollow ref. domains | E1: Dofollow linked domains | F1: Traffic | G1: Keywords | H1: Links to target | I1: New links | J1: Lost links | K1: Dofollow links | L1: First seen | M1: Lost
A2: ovh.net | B2: FALSE | C2: 90 | D2: 31648 | E2: 33092 | F2: 201070 | G2: 3130 | H2: 2 | I2: 0 | J2: 0 | K2: 0 | L2: 45641.893
A3: itxoft.com | B3: TRUE | C3: 84 | D3: 2565 | E3: 7 | F3: 0 | G3: 0 | H3: 3 | I3: 0 | J3: 3 | K3: 0 | L3: 45716.106 | M3: 46133.702
A4: eventcaddy.com | B4: FALSE | C4: 80 | D4: 2344 | E4: 2641 | F4: 1668 | G4: 231 | H4: 2 | I4: 0 | J4: 2 | K4: 0 | L4: 45723.656 | M4: 46057.477
A5: ewp.live | B5: FALSE | C5: 79 | D5: 3818 | E5: 4576 | F5: 27 | G5: 2 | H5: 2 | I5: 2 | J5: 0 | K5: 0 | L5: 46004.087
A6: buybacklinks.agency | B6: TRUE | C6: 77 | D6: 318 | E6: 1 | F6: 0 | G6: 0 | H6: 3 | I6: 3 | J6: 0 | K6: 0 | L6: 46121.624
A7: wanderlog.com | B7: TRUE | C7: 77 | D7: 15809 | E7: 1059353 | F7: 1980193 | G7: 652744 | H7: 7 | I7: 7 | J7: 0 | K7: 7 | L7: 46092.893
A8: temp-site.link | B8: FALSE | C8: 76 | D8: 2445 | E8: 20344 | F8: 15 | G8: 4 | H8: 9 | I8: 6 | J8: 0 | K8: 0 | L8: 45889.031
A9: mapcarta.com | B9: FALSE | C9: 75 | D9: 11463 | E9: 28 | F9: 375302 | G9: 225520 | H9: 2 | I9: 2 | J9: 0 | K9: 0 | L9: 46017.757
A10: rank-your.site | B10: TRUE | C10: 75 | D10: 1487 | E10: 0 | F10: 7 | G10: 1 | H10: 1 | I10: 0 | J10: 1 | K10: 0 | L10: 45773.078 | M10: 46050.591
A11: hol.es | B11: FALSE | C11: 74 | D11: 6852 | E11: 17243 | F11: 33 | G11: 19 | H11: 6 | I11: 6 | J11: 0 | K11: 0 | L11: 45988.429
A12: xrea.jp | B12: FALSE | C12: 74 | D12: 9356 | E12: 57859 | F12: 11694 | G12: 1056 | H12: 2 | I12: 0 | J12: 2 | K12: 0 | L12: 45886.889 | M12: 46140.361
A13: yogonet.com | B13: FALSE | C13: 74 | D13: 11424 | E13: 9427 | F13: 49669 | G13: 5393 | H13: 32 | I13: 8 | J13: 14 | K13: 32 | L13: 45715.927
A14: factmags.com | B14: TRUE | C14: 73 | D14: 4987 | E14: 39241294 | F14: 0 | G14: 0 | H14: 1 | I14: 1 | J14: 0 | K14: 0 | L14: 46149.596
A15: rankyour.website | B15: TRUE | C15: 73 | D15: 45 | E15: 0 | F15: 0 | G15: 0 | H15: 3 | I15: 3 | J15: 0 | K15: 0 | L15: 46136.358
A16: rank-top.click | B16: TRUE | C16: 72 | D16: 43 | E16: 1 | F16: 0 | G16: 0 | H16: 3 | I16: 3 | J16: 0 | K16: 0 | L16: 46120.837
A17: goedbegin.nl | B17: TRUE | C17: 70 | D17: 3069 | E17: 191789 | F17: 633 | G17: 571 | H17: 2 | I17: 0 | J17: 0 | K17: 2 | L17: 45984.272
A18: backlinker.shop | B18: TRUE | C18: 65 | D18: 506 | E18: 0 | F18: 0 | G18: 0 | H18: 3 | I18: 0 | J18: 0 | K18: 0 | L18: 45940.338
A19: bahamaslocal.com | B19: FALSE | C19: 65 | D19: 9473 | E19: 19015 | F19: 11032 | G19: 4267 | H19: 102 | I19: 0 | J19: 0 | K19: 102 | L19: 45205.475
A20: clodura.ai | B20: TRUE | C20: 64 | D20: 4342 | E20: 615900 | F20: 4320 | G20: 2428 | H20: 1 | I20: 0 | J20: 1 | K20: 1 | L20: 45736.499 | M20: 46113.955
A21: bnt.bs | B21: FALSE | C21: 62 | D21: 1194 | E21: 201 | F21: 1806 | G21: 244 | H21: 2 | I21: 0 | J21: 0 | K21: 2 | L21: 45714.739
A22: 6te.net | B22: FALSE | C22: 62 | D22: 10692 | E22: 20009 | F22: 3892 | G22: 942 | H22: 1 | I22: 1 | J22: 1 | K22: 0 | L22: 46019.115 | M22: 46068.985
A23: ioerj.com.br | B23: FALSE | C23: 61 | D23: 2050 | E23: 11396 | F23: 25038 | G23: 378 | H23: 1 | I23: 0 | J23: 0 | K23: 0 | L23: 45861.969
A24: heavenarticle.com | B24: TRUE | C24: 59 | D24: 7104 | E24: 3493588 | F24: 0 | G24: 0 | H24: 4 | I24: 0 | J24: 0 | K24: 4 | L24: 45732.332
A25: creativecreation.io | B25: FALSE | C25: 59 | D25: 136 | E25: 47 | F25: 31 | G25: 3 | H25: 2 | I25: 0 | J25: 1 | K25: 0 | L25: 45972.766
A26: host.io | B26: FALSE | C26: 58 | D26: 6825 | E26: 7 | F26: 8255 | G26: 136 | H26: 2 | I26: 1 | J26: 1 | K26: 0 | L26: 45914.533
A27: loneus.biz | B27: FALSE | C27: 58 | D27: 1911 | E27: 986 | F27: 51 | G27: 16 | H27: 1 | I27: 1 | J27: 1 | K27: 0 | L27: 46032.375 | M27: 46053.192
A28: promozionebranding.com | B28: TRUE | C28: 57 | D28: 120 | E28: 3574 | F28: 48 | G28: 6 | H28: 1 | I28: 1 | J28: 0 | K28: 0 | L28: 46003.041
A29: peaktech.nz | B29: TRUE | C29: 55 | D29: 1933 | E29: 110 | F29: 0 | G29: 0 | H29: 1 | I29: 0 | J29: 1 | K29: 0 | L29: 45893.898 | M29: 46107.268
A30: food-stadium.com | B30: FALSE | C30: 55 | D30: 2787 | E30: 2751 | F30: 4109 | G30: 1069 | H30: 43 | I30: 37 | J30: 43 | K30: 0 | L30: 45672.135 | M30: 46053.836
A31: kingranks.com | B31: TRUE | C31: 55 | D31: 4962 | E31: 6203816 | F31: 0 | G31: 0 | H31: 4 | I31: 0 | J31: 2 | K31: 4 | L31: 45714.041
A32: bounceme.net | B32: FALSE | C32: 55 | D32: 1442 | E32: 869 | F32: 0 | G32: 3 | H32: 1 | I32: 1 | J32: 0 | K32: 0 | L32: 46004.98
A33: gamingboardbahamas.com | B33: FALSE | C33: 54 | D33: 208 | E33: 102 | F33: 120 | G33: 39 | H33: 2 | I33: 0 | J33: 0 | K33: 2 | L33: 45717.4
A34: rankxlinks.shop | B34: TRUE | C34: 54 | D34: 16 | E34: 2 | F34: 0 | G34: 0 | H34: 3 | I34: 3 | J34: 0 | K34: 0 | L34: 46142.087
A35: linkrankpro.shop | B35: TRUE | C35: 54 | D35: 16 | E35: 2 | F35: 0 | G35: 0 | H35: 3 | I35: 3 | J35: 0 | K35: 0 | L35: 46144.795
A36: ranklinkerpro.shop | B36: TRUE | C36: 54 | D36: 16 | E36: 2 | F36: 0 | G36: 0 | H36: 3 | I36: 3 | J36: 0 | K36: 0 | L36: 46145.995
A37: starcourts.com | B37: TRUE | C37: 51 | D37: 1458 | E37: 4414137 | F37: 0 | G37: 1 | H37: 2 | I37: 0 | J37: 0 | K37: 2 | L37: 45715.214
A38: sante.gov.mg | B38: FALSE | C38: 50 | D38: 3554 | E38: 15203 | F38: 15 | G38: 22 | H38: 1 | I38: 1 | J38: 0 | K38: 0 | L38: 46053.177
A39: anlis.gov.ar | B39: TRUE | C39: 50 | D39: 428 | E39: 5202 | F39: 0 | G39: 1 | H39: 3 | I39: 0 | J39: 0 | K39: 0 | L39: 45930.085
A40: exlinko.net | B40: TRUE | C40: 50 | D40: 1841 | E40: 0 | F40: 0 | G40: 0 | H40: 3 | I40: 0 | J40: 3 | K40: 0 | L40: 45716.477 | M40: 46133.489
A41: adsflourish.com | B41: TRUE | C41: 50 | D41: 829 | E41: 20364 | F41: 5 | G41: 2 | H41: 1 | I41: 1 | J41: 0 | K41: 0 | L41: 45992.598
A42: seoflx.net | B42: TRUE | C42: 50 | D42: 1592 | E42: 0 | F42: 0 | G42: 0 | H42: 3 | I42: 0 | J42: 3 | K42: 0 | L42: 45685.019 | M42: 46044.629
A43: infospiritual.com | B43: FALSE | C43: 49 | D43: 646 | E43: 2601 | F43: 0 | G43: 0 | H43: 1 | I43: 0 | J43: 0 | K43: 1 | L43: 45646.897
A44: 1directory.org | B44: TRUE | C44: 49 | D44: 2642 | E44: 147911 | F44: 0 | G44: 0 | H44: 53 | I44: 53 | J44: 0 | K44: 53 | L44: 46151.274
A45: bye.fyi | B45: TRUE | C45: 48 | D45: 736 | E45: 18 | F45: 0 | G45: 1 | H45: 4 | I45: 4 | J45: 1 | K45: 0 | L45: 46025.224
A46: thebestbacklinksavailable.click | B46: TRUE | C46: 47 | D46: 129 | E46: 0 | F46: 0 | G46: 0 | H46: 1 | I46: 0 | J46: 1 | K46: 1 | L46: 45860.07 | M46: 46105.344
A47: openflightmaps.org | B47: FALSE | C47: 47 | D47: 889 | E47: 27 | F47: 19 | G47: 11 | H47: 2 | I47: 0 | J47: 1 | K47: 0 | L47: 45919.3
A48: quero.party | B48: TRUE | C48: 47 | D48: 399 | E48: 18 | F48: 0 | G48: 0 | H48: 5 | I48: 5 | J48: 0 | K48: 0 | L48: 46038.075
A49: teatrocervantes.gob.ar | B49: FALSE | C49: 47 | D49: 1088 | E49: 512 | F49: 11236 | G49: 400 | H49: 4 | I49: 1 | J49: 4 | K49: 0 | L49: 45868.523 | M49: 46034.792
A50: success.ai | B50: FALSE | C50: 46 | D50: 3324 | E50: 616119 | F50: 3166 | G50: 689 | H50: 2 | I50: 2 | J50: 0 | K50: 2 | L50: 46045.047
A51: vila-seca.cat | B51: FALSE | C51: 46 | D51: 1217 | E51: 523 | F51: 3166 | G51: 398 | H51: 1 | I51: 1 | J51: 1 | K51: 0 | L51: 46023.74 | M51: 46050.052
A52: sport-life.club | B52: TRUE | C52: 46 | D52: 1142 | E52: 9294 | F52: 0 | G52: 0 | H52: 1 | I52: 1 | J52: 1 | K52: 1 | L52: 46016.859 | M52: 46087.082
A53: itriangle.in | B53: FALSE | C53: 46 | D53: 1472 | E53: 17 | F53: 10 | G53: 4 | H53: 1 | I53: 0 | J53: 1 | K53: 0 | L53: 45920.884 | M53: 46005.391
A54: udi.edu.co | B54: FALSE | C54: 45 | D54: 2894 | E54: 1550 | F54: 5684 | G54: 550 | H54: 2 | I54: 0 | J54: 2 | K54: 0 | L54: 45769.711 | M54: 46008.974
A55: developmentmi.com | B55: TRUE | C55: 45 | D55: 1625 | E55: 4868048 | F55: 0 | G55: 0 | H55: 2 | I55: 0 | J55: 0 | K55: 2 | L55: 45712.799
A56: rankva.com | B56: TRUE | C56: 44 | D56: 829 | E56: 0 | F56: 0 | G56: 0 | H56: 1 | I56: 0 | J56: 1 | K56: 0 | L56: 45744.873 | M56: 46032.679
A57: linkz.us | B57: TRUE | C57: 43 | D57: 2500 | E57: 32175 | F57: 3 | G57: 5 | H57: 1 | I57: 0 | J57: 1 | K57: 0 | L57: 45672.101 | M57: 46153.177
A58: ournews.bs | B58: FALSE | C58: 43 | D58: 985 | E58: 183 | F58: 421 | G58: 248 | H58: 24129 | I58: 922 | J58: 24128 | K58: 24129 | L58: 45268.941
A59: aaaecommerce.com | B59: FALSE | C59: 43 | D59: 2596 | E59: 9400 | F59: 24 | G59: 10 | H59: 1 | I59: 0 | J59: 0 | K59: 0 | L59: 45762.143
A60: rikor.com | B60: TRUE | C60: 43 | D60: 4429 | E60: 100121 | F60: 616 | G60: 61 | H60: 9 | I60: 5 | J60: 3 | K60: 0 | L60: 45889.17
A61: creativeposts.top | B61: TRUE | C61: 42 | D61: 79 | E61: 18 | F61: 0 | G61: 0 | H61: 6 | I61: 6 | J61: 0 | K61: 0 | L61: 46029.873
A62: kupangkota.go.id | B62: TRUE | C62: 42 | D62: 4221 | E62: 59011 | F62: 5627 | G62: 581 | H62: 3 | I62: 0 | J62: 0 | K62: 0 | L62: 45870.135
A63: heroes.app | B63: FALSE | C63: 41 | D63: 4685 | E63: 11131 | F63: 8 | G63: 4 | H63: 1 | I63: 0 | J63: 0 | K63: 0 | L63: 45844.002
A64: near-place.com | B64: FALSE | C64: 41 | D64: 4948 | E64: 2 | F64: 117321 | G64: 58695 | H64: 12 | I64: 0 | J64: 0 | K64: 0 | L64: 45742.344
A65: atomizelink.icu | B65: TRUE | C65: 41 | D65: 440 | E65: 18 | F65: 0 | G65: 0 | H65: 6 | I65: 6 | J65: 2 | K65: 0 | L65: 46025.984
A66: analyticshaven.top | B66: TRUE | C66: 40 | D66: 101 | E66: 18 | F66: 0 | G66: 0 | H66: 2 | I66: 2 | J66: 0 | K66: 0 | L66: 46054.862
A67: blogsphere.top | B67: TRUE | C67: 40 | D67: 64 | E67: 18 | F67: 0 | G67: 0 | H67: 3 | I67: 2 | J67: 1 | K67: 0 | L67: 45937.237
A68: onecooldir.com | B68: TRUE | C68: 40 | D68: 1550 | E68: 89967 | F68: 0 | G68: 0 | H68: 404 | I68: 404 | J68: 0 | K68: 404 | L68: 46151.307
A69: ageddomainsforeverytaste.club | B69: TRUE | C69: 40 | D69: 106 | E69: 0 | F69: 0 | G69: 0 | H69: 3 | I69: 0 | J69: 3 | K69: 3 | L69: 45813.285 | M69: 46063.608
A70: deepbluedirectory.com | B70: TRUE | C70: 40 | D70: 3430 | E70: 42619 | F70: 0 | G70: 0 | H70: 17 | I70: 0 | J70: 2 | K70: 17 | L70: 45707.792
A71: byteshort.xyz | B71: TRUE | C71: 39 | D71: 136 | E71: 18 | F71: 0 | G71: 0 | H71: 6 | I71: 6 | J71: 2 | K71: 0 | L71: 46024.726
A72: metamagic.top | B72: TRUE | C72: 39 | D72: 77 | E72: 18 | F72: 0 | G72: 0 | H72: 4 | I72: 4 | J72: 0 | K72: 0 | L72: 46018.116
A73: screenshots.wiki | B73: TRUE | C73: 39 | D73: 63 | E73: 47 | F73: 0 | G73: 0 | H73: 4 | I73: 4 | J73: 2 | K73: 0 | L73: 46058.213
A74: securelivelihoods.org | B74: TRUE | C74: 38 | D74: 759 | E74: 98 | F74: 0 | G74: 0 | H74: 4 | I74: 0 | J74: 4 | K74: 0 | L74: 45939.048 | M74: 46001.673
A75: optimizeflow.top | B75: TRUE | C75: 38 | D75: 139 | E75: 18 | F75: 0 | G75: 0 | H75: 4 | I75: 4 | J75: 1 | K75: 0 | L75: 46027.792
A76: dailymusings.top | B76: TRUE | C76: 38 | D76: 49 | E76: 18 | F76: 0 | G76: 0 | H76: 2 | I76: 2 | J76: 0 | K76: 0 | L76: 46104.558
A77: yaari.co.in | B77: TRUE | C77: 38 | D77: 2464 | E77: 36661 | F77: 0 | G77: 0 | H77: 2 | I77: 1 | J77: 0 | K77: 0 | L77: 45722.76
A78: jake.eu | B78: TRUE | C78: 38 | D78: 108 | E78: 1275 | F78: 0 | G78: 0 | H78: 4 | I78: 4 | J78: 2 | K78: 0 | L78: 46029.215
A79: montesoriigrachki.com | B79: TRUE | C79: 37 | D79: 1326 | E79: 99 | F79: 0 | G79: 0 | H79: 2 | I79: 0 | J79: 2 | K79: 0 | L79: 45927.071 | M79: 46001.264
A80: mccoypress.net | B80: TRUE | C80: 37 | D80: 474 | E80: 2201 | F80: 1 | G80: 1 | H80: 2 | I80: 0 | J80: 2 | K80: 0 | L80: 45610.957 | M80: 46047.819
A81: wdi.net | B81: TRUE | C81: 37 | D81: 1585 | E81: 15529 | F81: 0 | G81: 2 | H81: 2 | I81: 2 | J81: 1 | K81: 0 | L81: 45992.948
A82: brownedgedirectory.com | B82: TRUE | C82: 37 | D82: 1404 | E82: 47662 | F82: 0 | G82: 1 | H82: 4 | I82: 1 | J82: 0 | K82: 4 | L82: 45696.542
A83: qhtycw.com | B83: TRUE | C83: 36 | D83: 1422 | E83: 9242 | F83: 0 | G83: 0 | H83: 1 | I83: 1 | J83: 1 | K83: 1 | L83: 46013.194 | M83: 46096.57
A84: kgzxkf.com | B84: TRUE | C84: 36 | D84: 1325 | E84: 5 | F84: 0 | G84: 0 | H84: 1 | I84: 1 | J84: 0 | K84: 1 | L84: 46036.282
A85: hzdlpq.com | B85: TRUE | C85: 36 | D85: 1535 | E85: 18118 | F85: 0 | G85: 0 | H85: 1 | I85: 1 | J85: 1 | K85: 1 | L85: 46030.618 | M85: 46087.791
A86: prolinkbox.com | B86: TRUE | C86: 36 | D86: 521 | E86: 0 | F86: 0 | G86: 0 | H86: 2 | I86: 0 | J86: 2 | K86: 0 | L86: 45807.08 | M86: 46059.492
A87: obmain.com | B87: TRUE | C87: 36 | D87: 1291 | E87: 128 | F87: 0 | G87: 0 | H87: 1 | I87: 1 | J87: 1 | K87: 1 | L87: 46032.781 | M87: 46065.858
A88: dsnylu.com | B88: TRUE | C88: 36 | D88: 1432 | E88: 8 | F88: 0 | G88: 0 | H88: 1 | I88: 1 | J88: 1 | K88: 1 | L88: 46031.983 | M88: 46088.129
A89: seo-high-ranking.shop | B89: TRUE | C89: 35 | D89: 1258 | E89: 138 | F89: 0 | G89: 0 | H89: 3 | I89: 3 | J89: 2 | K89: 0 | L89: 46131.66
A90: kawaiishop.shop | B90: TRUE | C90: 35 | D90: 792 | E90: 151 | F90: 0 | G90: 0 | H90: 5 | I90: 5 | J90: 2 | K90: 0 | L90: 46135.345
A91: theseorankinghigh.shop | B91: TRUE | C91: 35 | D91: 788 | E91: 141 | F91: 0 | G91: 0 | H91: 3 | I91: 3 | J91: 2 | K91: 0 | L91: 46141.54
A92: seoexpress.site | B92: TRUE | C92: 35 | D92: 794 | E92: 151 | F92: 0 | G92: 0 | H92: 1 | I92: 1 | J92: 0 | K92: 0 | L92: 46147.485
A93: therankboostseo.shop | B93: TRUE | C93: 34 | D93: 791 | E93: 151 | F93: 0 | G93: 0 | H93: 3 | I93: 3 | J93: 0 | K93: 0 | L93: 46144.894
A94: theguestpost.shop | B94: TRUE | C94: 34 | D94: 789 | E94: 151 | F94: 0 | G94: 0 | H94: 3 | I94: 3 | J94: 0 | K94: 0 | L94: 46143.292
A95: seoexpress.space | B95: TRUE | C95: 34 | D95: 782 | E95: 151 | F95: 0 | G95: 0 | H95: 2 | I95: 2 | J95: 0 | K95: 0 | L95: 46152.049
A96: theseomasterhigh.shop | B96: TRUE | C96: 34 | D96: 782 | E96: 151 | F96: 0 | G96: 0 | H96: 3 | I96: 3 | J96: 0 | K96: 0 | L96: 46146.418
A97: highseoranking.shop | B97: TRUE | C97: 34 | D97: 793 | E97: 141 | F97: 0 | G97: 0 | H97: 3 | I97: 3 | J97: 2 | K97: 0 | L97: 46150.242
A98: seohighranking.shop | B98: TRUE | C98: 34 | D98: 781 | E98: 151 | F98: 0 | G98: 0 | H98: 3 | I98: 3 | J98: 0 | K98: 0 | L98: 46147.083
A99: seoexpress.website | B99: TRUE | C99: 34 | D99: 811 | E99: 151 | F99: 0 | G99: 0 | H99: 3 | I99: 3 | J99: 2 | K99: 0 | L99: 46144.404
A100: shopbetreiber-blog.shop | B100: TRUE | C100: 34 | D100: 792 | E100: 142 | F100: 0 | G100: 0 | H100: 3 | I100: 3 | J100: 0 | K100: 0 | L100: 46135.907
...

Sheet Cost of backlinks (with low tra
A1: DR range | B1: value per backlink | C1: min (not inclusive) | D1: max (not inclusive) | E1: total backlinks (wrong) | F1: with low traffic: | G1: referring domains | H1: backlinks | I1: value | J1: without low traffic: | K1: referring domains | L1: backlinks | M1: value | P1: =A2 -> 70-100 | Q1: =A3 -> 40-70 | R1: =A4 -> 30-40 | S1: =A5 -> 10-30 | T1: =A6 -> 0-10
A2: 70-100 | B2: 750 | C2: 69 | D2: 101 | E2: =sumifs('Referring domains'!$D:$D, 'Referring domains'!B:B,"<"&D2, 'Referring domains'!B:B,">"&C2, 'Referring domains'!K:K,">1000") -> 0 | G2: {=COUNTIFS( INDIRECT("'Referring domains'!"&SUBSTITUTE(ADDRESS(1,MATCH("DR",'Referring domains'!$A$1:$M$1,0),4),1,"")&":"&SUBSTITUTE(ADDRESS(1,MATCH("DR",'Referring domains'!$A$1:$M$1,0),4),1,"")),"<"&D2, INDIRECT("'Referring domains'!"&SUBSTITUTE(ADDRESS(1,MATCH("DR",'Referring domains'!$A$1:$M$1,0),4),1,"")&":"&SUBSTITUTE(ADDRESS(1,MATCH("DR",'Referring domains'!$A$1:$M$1,0),4),1,"")),">"&C2 )} -> 16 | H2: {=sumifs(INDIRECT("'Referring domains'!"&SUBSTITUTE(ADDRESS(1,MATCH("Links to target",'Referring domains'!$A$1:$M$1,0),4),1,"")&":"&SUBSTITUTE(ADDRESS(1,MATCH("Links to target",'Referring domains'!$A$1:$M$1,0),4),1,"")), INDIRECT("'Referring domains'!"&SUBSTITUTE(ADDRESS(1,MATCH("DR",'Referring domains'!$A$1:$M$1,0),4),1,"")&":"&SUBSTITUTE(ADDRESS(1,MATCH("DR",'Referring domains'!$A$1:$M$1,0),4),1,"")),"<"&D2, INDIRECT("'Referring domains'!"&SUBSTITUTE(ADDRESS(1,MATCH("DR",'Referring domains'!$A$1:$M$1,0),4),1,"")&":"&SUBSTITUTE(ADDRESS(1,MATCH("DR",'Referring domains'!$A$1:$M$1,0),4),1,"")),">"&C2)} -> 80 | I2: =H2*B2 -> 60000 | K2: {=COUNTIFS( INDIRECT("'Referring domains'!"&SUBSTITUTE(ADDRESS(1,MATCH("Domain Rating (desc)",'Referring domains'!$A$1:$M$1,0),4),1,"")&":"&SUBSTITUTE(ADDRESS(1,MATCH("Domain Rating (desc)",'Referring domains'!$A$1:$M$1,0),4),1,"")),"<"&D2, INDIRECT("'Referring domains'!"&SUBSTITUTE(ADDRESS(1,MATCH("Domain Rating (desc)",'Referring domains'!$A$1:$M$1,0),4),1,"")&":"&SUBSTITUTE(ADDRESS(1,MATCH("Domain Rating (desc)",'Referring domains'!$A$1:$M$1,0),4),1,"")),">"&C2, INDIRECT("'Referring domains'!"&SUBSTITUTE(ADDRESS(1,MATCH("Organic Traffic",'Referring domains'!$A$1:$M$1,0),4),1,"")&":"&SUBSTITUTE(ADDRESS(1,MATCH("Organic Traffic",'Referring domains'!$A$1:$M$1,0),4),1,"")),">1000" )} -> 0 | L2: {=sumifs(INDIRECT("'Referring domains'!"&SUBSTITUTE(ADDRESS(1,MATCH("Total Backlinks",'Referring domains'!$A$1:$M$1,0),4),1,"")&":"&SUBSTITUTE(ADDRESS(1,MATCH("Total Backlinks",'Referring domains'!$A$1:$M$1,0),4),1,"")), INDIRECT("'Referring domains'!"&SUBSTITUTE(ADDRESS(1,MATCH("Domain Rating (desc)",'Referring domains'!$A$1:$M$1,0),4),1,"")&":"&SUBSTITUTE(ADDRESS(1,MATCH("Domain Rating (desc)",'Referring domains'!$A$1:$M$1,0),4),1,"")),"<"&D2, INDIRECT("'Referring domains'!"&SUBSTITUTE(ADDRESS(1,MATCH("Domain Rating (desc)",'Referring domains'!$A$1:$M$1,0),4),1,"")&":"&SUBSTITUTE(ADDRESS(1,MATCH("Domain Rating (desc)",'Referring domains'!$A$1:$M$1,0),4),1,"")),">"&C2, INDIRECT("'Referring domains'!"&SUBSTITUTE(ADDRESS(1,MATCH("Organic Traffic",'Referring domains'!$A$1:$M$1,0),4),1,"")&":"&SUBSTITUTE(ADDRESS(1,MATCH("Organic Traffic",'Referring domains'!$A$1:$M$1,0),4),1,"")),">1000")} -> #N/A | M2: =L2*B2 -> #N/A | P2: =IFERROR(__xludf.DUMMYFUNCTION("FILTER('Referring domains'!$A$2:$A788, 'Referring domains'!$B$2:$B788<101, 'Referring domains'!$B$2:$B788>69, 'Referring domains'!$K$1:$K788>$G$13)"),"#N/A") -> #N/A | Q2: =IFERROR(__xludf.DUMMYFUNCTION("FILTER('Referring domains'!$A$2:$A788, 'Referring domains'!$B$2:$B788<70, 'Referring domains'!$B$2:$B788>39, 'Referring domains'!$E$2:$E788>$G$13)"),"#N/A") -> #N/A | R2: =IFERROR(__xludf.DUMMYFUNCTION("FILTER('Referring domains'!$A$2:$A788, 'Referring domains'!$B$2:$B788<40, 'Referring domains'!$B$2:$B788>29, 'Referring domains'!$K$1:$K788>$G$13)"),"#N/A") -> #N/A | S2: =IFERROR(__xludf.DUMMYFUNCTION("FILTER('Referring domains'!$A$2:$A788, 'Referring domains'!$B$2:$B788<30, 'Referring domains'!$B$2:$B788>9, 'Referring domains'!$K$1:$K788>$G$13)"),"#N/A") -> #N/A | T2: =IFERROR(__xludf.DUMMYFUNCTION("FILTER('Referring domains'!$A$2:$A788, 'Referring domains'!$B$2:$B788<10, 'Referring domains'!$B$2:$B788>-1, 'Referring domains'!$K$1:$K788>$G$13)"),"#N/A") -> #N/A
A3: 40-70 | B3: 300 | C3: 39 | D3: 70 | E3: =sumifs('Referring domains'!$D:$D,'Referring domains'!B:B,"<"&D3,'Referring domains'!B:B,">"&C3,'Referring domains'!K:K,">1000") -> 0 | G3: {=COUNTIFS( INDIRECT("'Referring domains'!"&SUBSTITUTE(ADDRESS(1,MATCH("DR",'Referring domains'!$A$1:$M$1,0),4),1,"")&":"&SUBSTITUTE(ADDRESS(1,MATCH("DR",'Referring domains'!$A$1:$M$1,0),4),1,"")),"<"&D3, INDIRECT("'Referring domains'!"&SUBSTITUTE(ADDRESS(1,MATCH("DR",'Referring domains'!$A$1:$M$1,0),4),1,"")&":"&SUBSTITUTE(ADDRESS(1,MATCH("DR",'Referring domains'!$A$1:$M$1,0),4),1,"")),">"&C3 )} -> 53 | H3: {=sumifs(INDIRECT("'Referring domains'!"&SUBSTITUTE(ADDRESS(1,MATCH("Links to target",'Referring domains'!$A$1:$M$1,0),4),1,"")&":"&SUBSTITUTE(ADDRESS(1,MATCH("Links to target",'Referring domains'!$A$1:$M$1,0),4),1,"")), INDIRECT("'Referring domains'!"&SUBSTITUTE(ADDRESS(1,MATCH("DR",'Referring domains'!$A$1:$M$1,0),4),1,"")&":"&SUBSTITUTE(ADDRESS(1,MATCH("DR",'Referring domains'!$A$1:$M$1,0),4),1,"")),"<"&D3, INDIRECT("'Referring domains'!"&SUBSTITUTE(ADDRESS(1,MATCH("DR",'Referring domains'!$A$1:$M$1,0),4),1,"")&":"&SUBSTITUTE(ADDRESS(1,MATCH("DR",'Referring domains'!$A$1:$M$1,0),4),1,"")),">"&C3)} -> 24870 | I3: =H3*B3 -> 7461000 | K3: {=COUNTIFS( INDIRECT("'Referring domains'!"&SUBSTITUTE(ADDRESS(1,MATCH("Domain Rating (desc)",'Referring domains'!$A$1:$M$1,0),4),1,"")&":"&SUBSTITUTE(ADDRESS(1,MATCH("Domain Rating (desc)",'Referring domains'!$A$1:$M$1,0),4),1,"")),"<"&D3, INDIRECT("'Referring domains'!"&SUBSTITUTE(ADDRESS(1,MATCH("Domain Rating (desc)",'Referring domains'!$A$1:$M$1,0),4),1,"")&":"&SUBSTITUTE(ADDRESS(1,MATCH("Domain Rating (desc)",'Referring domains'!$A$1:$M$1,0),4),1,"")),">"&C3, INDIRECT("'Referring domains'!"&SUBSTITUTE(ADDRESS(1,MATCH("Organic Traffic",'Referring domains'!$A$1:$M$1,0),4),1,"")&":"&SUBSTITUTE(ADDRESS(1,MATCH("Organic Traffic",'Referring domains'!$A$1:$M$1,0),4),1,"")),">1000" )} -> 0 | L3: {=sumifs(INDIRECT("'Referring domains'!"&SUBSTITUTE(ADDRESS(1,MATCH("Total Backlinks",'Referring domains'!$A$1:$M$1,0),4),1,"")&":"&SUBSTITUTE(ADDRESS(1,MATCH("Total Backlinks",'Referring domains'!$A$1:$M$1,0),4),1,"")), INDIRECT("'Referring domains'!"&SUBSTITUTE(ADDRESS(1,MATCH("Domain Rating (desc)",'Referring domains'!$A$1:$M$1,0),4),1,"")&":"&SUBSTITUTE(ADDRESS(1,MATCH("Domain Rating (desc)",'Referring domains'!$A$1:$M$1,0),4),1,"")),"<"&D3, INDIRECT("'Referring domains'!"&SUBSTITUTE(ADDRESS(1,MATCH("Domain Rating (desc)",'Referring domains'!$A$1:$M$1,0),4),1,"")&":"&SUBSTITUTE(ADDRESS(1,MATCH("Domain Rating (desc)",'Referring domains'!$A$1:$M$1,0),4),1,"")),">"&C3, INDIRECT("'Referring domains'!"&SUBSTITUTE(ADDRESS(1,MATCH("Organic Traffic",'Referring domains'!$A$1:$M$1,0),4),1,"")&":"&SUBSTITUTE(ADDRESS(1,MATCH("Organic Traffic",'Referring domains'!$A$1:$M$1,0),4),1,"")),">1000")} -> #N/A | M3: =L3*B3 -> #N/A
A4: 30-40 | B4: 100 | C4: 29 | D4: 40 | E4: =sumifs('Referring domains'!$D:$D,'Referring domains'!B:B,"<"&D4,'Referring domains'!B:B,">"&C4,'Referring domains'!K:K,">1000") -> 0 | G4: {=COUNTIFS( INDIRECT("'Referring domains'!"&SUBSTITUTE(ADDRESS(1,MATCH("DR",'Referring domains'!$A$1:$M$1,0),4),1,"")&":"&SUBSTITUTE(ADDRESS(1,MATCH("DR",'Referring domains'!$A$1:$M$1,0),4),1,"")),"<"&D4, INDIRECT("'Referring domains'!"&SUBSTITUTE(ADDRESS(1,MATCH("DR",'Referring domains'!$A$1:$M$1,0),4),1,"")&":"&SUBSTITUTE(ADDRESS(1,MATCH("DR",'Referring domains'!$A$1:$M$1,0),4),1,"")),">"&C4 )} -> 143 | H4: {=sumifs(INDIRECT("'Referring domains'!"&SUBSTITUTE(ADDRESS(1,MATCH("Links to target",'Referring domains'!$A$1:$M$1,0),4),1,"")&":"&SUBSTITUTE(ADDRESS(1,MATCH("Links to target",'Referring domains'!$A$1:$M$1,0),4),1,"")), INDIRECT("'Referring domains'!"&SUBSTITUTE(ADDRESS(1,MATCH("DR",'Referring domains'!$A$1:$M$1,0),4),1,"")&":"&SUBSTITUTE(ADDRESS(1,MATCH("DR",'Referring domains'!$A$1:$M$1,0),4),1,"")),"<"&D4, INDIRECT("'Referring domains'!"&SUBSTITUTE(ADDRESS(1,MATCH("DR",'Referring domains'!$A$1:$M$1,0),4),1,"")&":"&SUBSTITUTE(ADDRESS(1,MATCH("DR",'Referring domains'!$A$1:$M$1,0),4),1,"")),">"&C4)} -> 663 | I4: =H4*B4 -> 66300 | K4: {=COUNTIFS( INDIRECT("'Referring domains'!"&SUBSTITUTE(ADDRESS(1,MATCH("Domain Rating (desc)",'Referring domains'!$A$1:$M$1,0),4),1,"")&":"&SUBSTITUTE(ADDRESS(1,MATCH("Domain Rating (desc)",'Referring domains'!$A$1:$M$1,0),4),1,"")),"<"&D4, INDIRECT("'Referring domains'!"&SUBSTITUTE(ADDRESS(1,MATCH("Domain Rating (desc)",'Referring domains'!$A$1:$M$1,0),4),1,"")&":"&SUBSTITUTE(ADDRESS(1,MATCH("Domain Rating (desc)",'Referring domains'!$A$1:$M$1,0),4),1,"")),">"&C4, INDIRECT("'Referring domains'!"&SUBSTITUTE(ADDRESS(1,MATCH("Organic Traffic",'Referring domains'!$A$1:$M$1,0),4),1,"")&":"&SUBSTITUTE(ADDRESS(1,MATCH("Organic Traffic",'Referring domains'!$A$1:$M$1,0),4),1,"")),">1000" )} -> 0 | L4: {=sumifs(INDIRECT("'Referring domains'!"&SUBSTITUTE(ADDRESS(1,MATCH("Total Backlinks",'Referring domains'!$A$1:$M$1,0),4),1,"")&":"&SUBSTITUTE(ADDRESS(1,MATCH("Total Backlinks",'Referring domains'!$A$1:$M$1,0),4),1,"")), INDIRECT("'Referring domains'!"&SUBSTITUTE(ADDRESS(1,MATCH("Domain Rating (desc)",'Referring domains'!$A$1:$M$1,0),4),1,"")&":"&SUBSTITUTE(ADDRESS(1,MATCH("Domain Rating (desc)",'Referring domains'!$A$1:$M$1,0),4),1,"")),"<"&D4, INDIRECT("'Referring domains'!"&SUBSTITUTE(ADDRESS(1,MATCH("Domain Rating (desc)",'Referring domains'!$A$1:$M$1,0),4),1,"")&":"&SUBSTITUTE(ADDRESS(1,MATCH("Domain Rating (desc)",'Referring domains'!$A$1:$M$1,0),4),1,"")),">"&C4, INDIRECT("'Referring domains'!"&SUBSTITUTE(ADDRESS(1,MATCH("Organic Traffic",'Referring domains'!$A$1:$M$1,0),4),1,"")&":"&SUBSTITUTE(ADDRESS(1,MATCH("Organic Traffic",'Referring domains'!$A$1:$M$1,0),4),1,"")),">1000")} -> #N/A | M4: =L4*B4 -> #N/A
A5: 10-30 | B5: 50 | C5: 9 | D5: 30 | E5: =sumifs('Referring domains'!$D:$D,'Referring domains'!B:B,"<"&D5,'Referring domains'!B:B,">"&C5,'Referring domains'!K:K,">1000") -> 0 | G5: {=COUNTIFS( INDIRECT("'Referring domains'!"&SUBSTITUTE(ADDRESS(1,MATCH("DR",'Referring domains'!$A$1:$M$1,0),4),1,"")&":"&SUBSTITUTE(ADDRESS(1,MATCH("DR",'Referring domains'!$A$1:$M$1,0),4),1,"")),"<"&D5, INDIRECT("'Referring domains'!"&SUBSTITUTE(ADDRESS(1,MATCH("DR",'Referring domains'!$A$1:$M$1,0),4),1,"")&":"&SUBSTITUTE(ADDRESS(1,MATCH("DR",'Referring domains'!$A$1:$M$1,0),4),1,"")),">"&C5 )} -> 415 | H5: {=sumifs(INDIRECT("'Referring domains'!"&SUBSTITUTE(ADDRESS(1,MATCH("Links to target",'Referring domains'!$A$1:$M$1,0),4),1,"")&":"&SUBSTITUTE(ADDRESS(1,MATCH("Links to target",'Referring domains'!$A$1:$M$1,0),4),1,"")), INDIRECT("'Referring domains'!"&SUBSTITUTE(ADDRESS(1,MATCH("DR",'Referring domains'!$A$1:$M$1,0),4),1,"")&":"&SUBSTITUTE(ADDRESS(1,MATCH("DR",'Referring domains'!$A$1:$M$1,0),4),1,"")),"<"&D5, INDIRECT("'Referring domains'!"&SUBSTITUTE(ADDRESS(1,MATCH("DR",'Referring domains'!$A$1:$M$1,0),4),1,"")&":"&SUBSTITUTE(ADDRESS(1,MATCH("DR",'Referring domains'!$A$1:$M$1,0),4),1,"")),">"&C5)} -> 1383 | I5: =H5*B5 -> 69150 | K5: {=COUNTIFS( INDIRECT("'Referring domains'!"&SUBSTITUTE(ADDRESS(1,MATCH("Domain Rating (desc)",'Referring domains'!$A$1:$M$1,0),4),1,"")&":"&SUBSTITUTE(ADDRESS(1,MATCH("Domain Rating (desc)",'Referring domains'!$A$1:$M$1,0),4),1,"")),"<"&D5, INDIRECT("'Referring domains'!"&SUBSTITUTE(ADDRESS(1,MATCH("Domain Rating (desc)",'Referring domains'!$A$1:$M$1,0),4),1,"")&":"&SUBSTITUTE(ADDRESS(1,MATCH("Domain Rating (desc)",'Referring domains'!$A$1:$M$1,0),4),1,"")),">"&C5, INDIRECT("'Referring domains'!"&SUBSTITUTE(ADDRESS(1,MATCH("Organic Traffic",'Referring domains'!$A$1:$M$1,0),4),1,"")&":"&SUBSTITUTE(ADDRESS(1,MATCH("Organic Traffic",'Referring domains'!$A$1:$M$1,0),4),1,"")),">1000" )} -> 0 | L5: {=sumifs(INDIRECT("'Referring domains'!"&SUBSTITUTE(ADDRESS(1,MATCH("Total Backlinks",'Referring domains'!$A$1:$M$1,0),4),1,"")&":"&SUBSTITUTE(ADDRESS(1,MATCH("Total Backlinks",'Referring domains'!$A$1:$M$1,0),4),1,"")), INDIRECT("'Referring domains'!"&SUBSTITUTE(ADDRESS(1,MATCH("Domain Rating (desc)",'Referring domains'!$A$1:$M$1,0),4),1,"")&":"&SUBSTITUTE(ADDRESS(1,MATCH("Domain Rating (desc)",'Referring domains'!$A$1:$M$1,0),4),1,"")),"<"&D5, INDIRECT("'Referring domains'!"&SUBSTITUTE(ADDRESS(1,MATCH("Domain Rating (desc)",'Referring domains'!$A$1:$M$1,0),4),1,"")&":"&SUBSTITUTE(ADDRESS(1,MATCH("Domain Rating (desc)",'Referring domains'!$A$1:$M$1,0),4),1,"")),">"&C5, INDIRECT("'Referring domains'!"&SUBSTITUTE(ADDRESS(1,MATCH("Organic Traffic",'Referring domains'!$A$1:$M$1,0),4),1,"")&":"&SUBSTITUTE(ADDRESS(1,MATCH("Organic Traffic",'Referring domains'!$A$1:$M$1,0),4),1,"")),">1000")} -> #N/A | M5: =L5*B5 -> #N/A
A6: 0-10 | B6: 10 | C6: -1 | D6: 10 | E6: =sumifs('Referring domains'!$D:$D,'Referring domains'!B:B,"<"&D6,'Referring domains'!B:B,">"&C6,'Referring domains'!K:K,">1000") -> 0 | G6: {=COUNTIFS( INDIRECT("'Referring domains'!"&SUBSTITUTE(ADDRESS(1,MATCH("DR",'Referring domains'!$A$1:$M$1,0),4),1,"")&":"&SUBSTITUTE(ADDRESS(1,MATCH("DR",'Referring domains'!$A$1:$M$1,0),4),1,"")),"<"&D6, INDIRECT("'Referring domains'!"&SUBSTITUTE(ADDRESS(1,MATCH("DR",'Referring domains'!$A$1:$M$1,0),4),1,"")&":"&SUBSTITUTE(ADDRESS(1,MATCH("DR",'Referring domains'!$A$1:$M$1,0),4),1,"")),">"&C6 )} -> 4870 | H6: {=sumifs(INDIRECT("'Referring domains'!"&SUBSTITUTE(ADDRESS(1,MATCH("Links to target",'Referring domains'!$A$1:$M$1,0),4),1,"")&":"&SUBSTITUTE(ADDRESS(1,MATCH("Links to target",'Referring domains'!$A$1:$M$1,0),4),1,"")), INDIRECT("'Referring domains'!"&SUBSTITUTE(ADDRESS(1,MATCH("DR",'Referring domains'!$A$1:$M$1,0),4),1,"")&":"&SUBSTITUTE(ADDRESS(1,MATCH("DR",'Referring domains'!$A$1:$M$1,0),4),1,"")),"<"&D6, INDIRECT("'Referring domains'!"&SUBSTITUTE(ADDRESS(1,MATCH("DR",'Referring domains'!$A$1:$M$1,0),4),1,"")&":"&SUBSTITUTE(ADDRESS(1,MATCH("DR",'Referring domains'!$A$1:$M$1,0),4),1,"")),">"&C6)} -> 81975 | I6: =H6*B6 -> 819750 | K6: {=COUNTIFS( INDIRECT("'Referring domains'!"&SUBSTITUTE(ADDRESS(1,MATCH("Domain Rating (desc)",'Referring domains'!$A$1:$M$1,0),4),1,"")&":"&SUBSTITUTE(ADDRESS(1,MATCH("Domain Rating (desc)",'Referring domains'!$A$1:$M$1,0),4),1,"")),"<"&D6, INDIRECT("'Referring domains'!"&SUBSTITUTE(ADDRESS(1,MATCH("Domain Rating (desc)",'Referring domains'!$A$1:$M$1,0),4),1,"")&":"&SUBSTITUTE(ADDRESS(1,MATCH("Domain Rating (desc)",'Referring domains'!$A$1:$M$1,0),4),1,"")),">"&C6, INDIRECT("'Referring domains'!"&SUBSTITUTE(ADDRESS(1,MATCH("Organic Traffic",'Referring domains'!$A$1:$M$1,0),4),1,"")&":"&SUBSTITUTE(ADDRESS(1,MATCH("Organic Traffic",'Referring domains'!$A$1:$M$1,0),4),1,"")),">1000" )} -> 0 | L6: {=sumifs(INDIRECT("'Referring domains'!"&SUBSTITUTE(ADDRESS(1,MATCH("Total Backlinks",'Referring domains'!$A$1:$M$1,0),4),1,"")&":"&SUBSTITUTE(ADDRESS(1,MATCH("Total Backlinks",'Referring domains'!$A$1:$M$1,0),4),1,"")), INDIRECT("'Referring domains'!"&SUBSTITUTE(ADDRESS(1,MATCH("Domain Rating (desc)",'Referring domains'!$A$1:$M$1,0),4),1,"")&":"&SUBSTITUTE(ADDRESS(1,MATCH("Domain Rating (desc)",'Referring domains'!$A$1:$M$1,0),4),1,"")),"<"&D6, INDIRECT("'Referring domains'!"&SUBSTITUTE(ADDRESS(1,MATCH("Domain Rating (desc)",'Referring domains'!$A$1:$M$1,0),4),1,"")&":"&SUBSTITUTE(ADDRESS(1,MATCH("Domain Rating (desc)",'Referring domains'!$A$1:$M$1,0),4),1,"")),">"&C6, INDIRECT("'Referring domains'!"&SUBSTITUTE(ADDRESS(1,MATCH("Organic Traffic",'Referring domains'!$A$1:$M$1,0),4),1,"")&":"&SUBSTITUTE(ADDRESS(1,MATCH("Organic Traffic",'Referring domains'!$A$1:$M$1,0),4),1,"")),">1000")} -> #N/A | M6: =L6*B6 -> #N/A
G8: Total ref domains | H8: Total backlinks | I8: Total value | L8: Total backlinks | M8: Total value
G9: =SUM(G2:G6) -> 5497 | H9: =sum(H2:H6) -> 108971 | I9: =SUM(I2:I6) -> 8476200 | L9: =sum(L2:L6) -> #N/A | M9: =SUM(M2:M6) -> #N/A
G12: minimum traffic
G13: -1

Sheet Cost of backlinks (without low 
A1: DR range | B1: value per backlink | C1: min (not inclusive) | D1: max (not inclusive) | E1: total backlinks (wrong) | F1: with low traffic: | G1: referring domains | H1: backlinks | I1: value | J1: without low traffic: | K1: referring domains | L1: backlinks | M1: value | P1: =A2 -> 70-100 | Q1: =A3 -> 40-70 | R1: =A4 -> 30-40 | S1: =A5 -> 10-30 | T1: =A6 -> 0-10
A2: 70-100 | B2: 750 | C2: 69 | D2: 101 | E2: =sumifs('Referring domains'!$D:$D, 'Referring domains'!B:B,"<"&D2, 'Referring domains'!B:B,">"&C2, 'Referring domains'!K:K,">1000") -> 0 | G2: {=COUNTIFS( INDIRECT("'Referring domains'!"&SUBSTITUTE(ADDRESS(1,MATCH("Domain Rating (desc)",'Referring domains'!$A$1:$M$1,0),4),1,"")&":"&SUBSTITUTE(ADDRESS(1,MATCH("Domain Rating (desc)",'Referring domains'!$A$1:$M$1,0),4),1,"")),"<"&D2, INDIRECT("'Referring domains'!"&SUBSTITUTE(ADDRESS(1,MATCH("Domain Rating (desc)",'Referring domains'!$A$1:$M$1,0),4),1,"")&":"&SUBSTITUTE(ADDRESS(1,MATCH("Domain Rating (desc)",'Referring domains'!$A$1:$M$1,0),4),1,"")),">"&C2 )} -> 0 | H2: {=sumifs(INDIRECT("'Referring domains'!"&SUBSTITUTE(ADDRESS(1,MATCH("Total Backlinks",'Referring domains'!$A$1:$M$1,0),4),1,"")&":"&SUBSTITUTE(ADDRESS(1,MATCH("Total Backlinks",'Referring domains'!$A$1:$M$1,0),4),1,"")), INDIRECT("'Referring domains'!"&SUBSTITUTE(ADDRESS(1,MATCH("Domain Rating (desc)",'Referring domains'!$A$1:$M$1,0),4),1,"")&":"&SUBSTITUTE(ADDRESS(1,MATCH("Domain Rating (desc)",'Referring domains'!$A$1:$M$1,0),4),1,"")),"<"&D2, INDIRECT("'Referring domains'!"&SUBSTITUTE(ADDRESS(1,MATCH("Domain Rating (desc)",'Referring domains'!$A$1:$M$1,0),4),1,"")&":"&SUBSTITUTE(ADDRESS(1,MATCH("Domain Rating (desc)",'Referring domains'!$A$1:$M$1,0),4),1,"")),">"&C2)} -> #N/A | I2: =H2*B2 -> #N/A | K2: =COUNTA(P:P) - 1 -> 1 | L2: =IFERROR(__xludf.DUMMYFUNCTION("sum(filter('Referring domains'!G1:G788,isnumber(match('Referring domains'!A1:A788,'Cost of backlinks (without low '!P:P,0)))) "),"#N/A") -> #N/A | M2: =L2*B2 -> #N/A | P2: =IFERROR(__xludf.DUMMYFUNCTION("FILTER('Referring domains'!$A$2:$A788, 'Referring domains'!$B$2:$B788<101, 'Referring domains'!$B$2:$B788>69, 'Referring domains'!$E$2:$E788>$K$13)"),"#N/A") -> #N/A | Q2: =IFERROR(__xludf.DUMMYFUNCTION("FILTER('Referring domains'!$A$2:$A788, 'Referring domains'!$B$2:$B788<70, 'Referring domains'!$B$2:$B788>39, 'Referring domains'!$E$2:$E788>$K$13)"),"#N/A") -> #N/A | R2: =IFERROR(__xludf.DUMMYFUNCTION("FILTER('Referring domains'!$A$2:$A788, 'Referring domains'!$B$2:$B788<40, 'Referring domains'!$B$2:$B788>29, 'Referring domains'!$E$2:$E788>$K$13)"),"#N/A") -> #N/A | S2: =IFERROR(__xludf.DUMMYFUNCTION("FILTER('Referring domains'!$A$2:$A788, 'Referring domains'!$B$2:$B788<30, 'Referring domains'!$B$2:$B788>9, 'Referring domains'!$E$2:$E788>$K$13)"),"#N/A") -> #N/A | T2: =IFERROR(__xludf.DUMMYFUNCTION("FILTER('Referring domains'!$A$2:$A788, 'Referring domains'!$B$2:$B788<10, 'Referring domains'!$B$2:$B788>-1, 'Referring domains'!$E$2:$E788>$K$13)"),"#N/A") -> #N/A
A3: 40-70 | B3: 300 | C3: 39 | D3: 70 | E3: =sumifs('Referring domains'!$D:$D,'Referring domains'!B:B,"<"&D3,'Referring domains'!B:B,">"&C3,'Referring domains'!K:K,">1000") -> 0 | G3: {=COUNTIFS( INDIRECT("'Referring domains'!"&SUBSTITUTE(ADDRESS(1,MATCH("Domain Rating (desc)",'Referring domains'!$A$1:$M$1,0),4),1,"")&":"&SUBSTITUTE(ADDRESS(1,MATCH("Domain Rating (desc)",'Referring domains'!$A$1:$M$1,0),4),1,"")),"<"&D3, INDIRECT("'Referring domains'!"&SUBSTITUTE(ADDRESS(1,MATCH("Domain Rating (desc)",'Referring domains'!$A$1:$M$1,0),4),1,"")&":"&SUBSTITUTE(ADDRESS(1,MATCH("Domain Rating (desc)",'Referring domains'!$A$1:$M$1,0),4),1,"")),">"&C3 )} -> 0 | H3: {=sumifs(INDIRECT("'Referring domains'!"&SUBSTITUTE(ADDRESS(1,MATCH("Total Backlinks",'Referring domains'!$A$1:$M$1,0),4),1,"")&":"&SUBSTITUTE(ADDRESS(1,MATCH("Total Backlinks",'Referring domains'!$A$1:$M$1,0),4),1,"")), INDIRECT("'Referring domains'!"&SUBSTITUTE(ADDRESS(1,MATCH("Domain Rating (desc)",'Referring domains'!$A$1:$M$1,0),4),1,"")&":"&SUBSTITUTE(ADDRESS(1,MATCH("Domain Rating (desc)",'Referring domains'!$A$1:$M$1,0),4),1,"")),"<"&D3, INDIRECT("'Referring domains'!"&SUBSTITUTE(ADDRESS(1,MATCH("Domain Rating (desc)",'Referring domains'!$A$1:$M$1,0),4),1,"")&":"&SUBSTITUTE(ADDRESS(1,MATCH("Domain Rating (desc)",'Referring domains'!$A$1:$M$1,0),4),1,"")),">"&C3)} -> #N/A | I3: =H3*B3 -> #N/A | K3: =COUNTA(Q:Q) - 1 -> 1 | L3: =IFERROR(__xludf.DUMMYFUNCTION("sum(filter('Referring domains'!G:G,isnumber(match('Referring domains'!A:A,'Cost of backlinks (without low '!Q:Q,0)))) "),"#N/A") -> #N/A | M3: =L3*B3 -> #N/A
A4: 30-40 | B4: 100 | C4: 29 | D4: 40 | E4: =sumifs('Referring domains'!$D:$D,'Referring domains'!B:B,"<"&D4,'Referring domains'!B:B,">"&C4,'Referring domains'!K:K,">1000") -> 0 | G4: {=COUNTIFS( INDIRECT("'Referring domains'!"&SUBSTITUTE(ADDRESS(1,MATCH("Domain Rating (desc)",'Referring domains'!$A$1:$M$1,0),4),1,"")&":"&SUBSTITUTE(ADDRESS(1,MATCH("Domain Rating (desc)",'Referring domains'!$A$1:$M$1,0),4),1,"")),"<"&D4, INDIRECT("'Referring domains'!"&SUBSTITUTE(ADDRESS(1,MATCH("Domain Rating (desc)",'Referring domains'!$A$1:$M$1,0),4),1,"")&":"&SUBSTITUTE(ADDRESS(1,MATCH("Domain Rating (desc)",'Referring domains'!$A$1:$M$1,0),4),1,"")),">"&C4 )} -> 0 | H4: {=sumifs(INDIRECT("'Referring domains'!"&SUBSTITUTE(ADDRESS(1,MATCH("Total Backlinks",'Referring domains'!$A$1:$M$1,0),4),1,"")&":"&SUBSTITUTE(ADDRESS(1,MATCH("Total Backlinks",'Referring domains'!$A$1:$M$1,0),4),1,"")), INDIRECT("'Referring domains'!"&SUBSTITUTE(ADDRESS(1,MATCH("Domain Rating (desc)",'Referring domains'!$A$1:$M$1,0),4),1,"")&":"&SUBSTITUTE(ADDRESS(1,MATCH("Domain Rating (desc)",'Referring domains'!$A$1:$M$1,0),4),1,"")),"<"&D4, INDIRECT("'Referring domains'!"&SUBSTITUTE(ADDRESS(1,MATCH("Domain Rating (desc)",'Referring domains'!$A$1:$M$1,0),4),1,"")&":"&SUBSTITUTE(ADDRESS(1,MATCH("Domain Rating (desc)",'Referring domains'!$A$1:$M$1,0),4),1,"")),">"&C4)} -> #N/A | I4: =H4*B4 -> #N/A | K4: =COUNTA(R:R) - 1 -> 1 | L4: =IFERROR(__xludf.DUMMYFUNCTION("sum(filter('Referring domains'!G:G,isnumber(match('Referring domains'!A:A,'Cost of backlinks (without low '!R:R,0)))) "),"#N/A") -> #N/A | M4: =L4*B4 -> #N/A
A5: 10-30 | B5: 50 | C5: 9 | D5: 30 | E5: =sumifs('Referring domains'!$D:$D,'Referring domains'!B:B,"<"&D5,'Referring domains'!B:B,">"&C5,'Referring domains'!K:K,">1000") -> 0 | G5: {=COUNTIFS( INDIRECT("'Referring domains'!"&SUBSTITUTE(ADDRESS(1,MATCH("Domain Rating (desc)",'Referring domains'!$A$1:$M$1,0),4),1,"")&":"&SUBSTITUTE(ADDRESS(1,MATCH("Domain Rating (desc)",'Referring domains'!$A$1:$M$1,0),4),1,"")),"<"&D5, INDIRECT("'Referring domains'!"&SUBSTITUTE(ADDRESS(1,MATCH("Domain Rating (desc)",'Referring domains'!$A$1:$M$1,0),4),1,"")&":"&SUBSTITUTE(ADDRESS(1,MATCH("Domain Rating (desc)",'Referring domains'!$A$1:$M$1,0),4),1,"")),">"&C5 )} -> 0 | H5: {=sumifs(INDIRECT("'Referring domains'!"&SUBSTITUTE(ADDRESS(1,MATCH("Total Backlinks",'Referring domains'!$A$1:$M$1,0),4),1,"")&":"&SUBSTITUTE(ADDRESS(1,MATCH("Total Backlinks",'Referring domains'!$A$1:$M$1,0),4),1,"")), INDIRECT("'Referring domains'!"&SUBSTITUTE(ADDRESS(1,MATCH("Domain Rating (desc)",'Referring domains'!$A$1:$M$1,0),4),1,"")&":"&SUBSTITUTE(ADDRESS(1,MATCH("Domain Rating (desc)",'Referring domains'!$A$1:$M$1,0),4),1,"")),"<"&D5, INDIRECT("'Referring domains'!"&SUBSTITUTE(ADDRESS(1,MATCH("Domain Rating (desc)",'Referring domains'!$A$1:$M$1,0),4),1,"")&":"&SUBSTITUTE(ADDRESS(1,MATCH("Domain Rating (desc)",'Referring domains'!$A$1:$M$1,0),4),1,"")),">"&C5)} -> #N/A | I5: =H5*B5 -> #N/A | K5: =COUNTA(S:S) - 1 -> 1 | L5: =IFERROR(__xludf.DUMMYFUNCTION("sum(filter('Referring domains'!G:G,isnumber(match('Referring domains'!A:A,'Cost of backlinks (without low '!S:S,0)))) "),"#N/A") -> #N/A | M5: =L5*B5 -> #N/A
A6: 0-10 | B6: 10 | C6: -1 | D6: 10 | E6: =sumifs('Referring domains'!$D:$D,'Referring domains'!B:B,"<"&D6,'Referring domains'!B:B,">"&C6,'Referring domains'!K:K,">1000") -> 0 | G6: {=COUNTIFS( INDIRECT("'Referring domains'!"&SUBSTITUTE(ADDRESS(1,MATCH("Domain Rating (desc)",'Referring domains'!$A$1:$M$1,0),4),1,"")&":"&SUBSTITUTE(ADDRESS(1,MATCH("Domain Rating (desc)",'Referring domains'!$A$1:$M$1,0),4),1,"")),"<"&D6, INDIRECT("'Referring domains'!"&SUBSTITUTE(ADDRESS(1,MATCH("Domain Rating (desc)",'Referring domains'!$A$1:$M$1,0),4),1,"")&":"&SUBSTITUTE(ADDRESS(1,MATCH("Domain Rating (desc)",'Referring domains'!$A$1:$M$1,0),4),1,"")),">"&C6 )} -> 0 | H6: {=sumifs(INDIRECT("'Referring domains'!"&SUBSTITUTE(ADDRESS(1,MATCH("Total Backlinks",'Referring domains'!$A$1:$M$1,0),4),1,"")&":"&SUBSTITUTE(ADDRESS(1,MATCH("Total Backlinks",'Referring domains'!$A$1:$M$1,0),4),1,"")), INDIRECT("'Referring domains'!"&SUBSTITUTE(ADDRESS(1,MATCH("Domain Rating (desc)",'Referring domains'!$A$1:$M$1,0),4),1,"")&":"&SUBSTITUTE(ADDRESS(1,MATCH("Domain Rating (desc)",'Referring domains'!$A$1:$M$1,0),4),1,"")),"<"&D6, INDIRECT("'Referring domains'!"&SUBSTITUTE(ADDRESS(1,MATCH("Domain Rating (desc)",'Referring domains'!$A$1:$M$1,0),4),1,"")&":"&SUBSTITUTE(ADDRESS(1,MATCH("Domain Rating (desc)",'Referring domains'!$A$1:$M$1,0),4),1,"")),">"&C6)} -> #N/A | I6: =H6*B6 -> #N/A | K6: =COUNTA(T:T) - 1 -> 1 | L6: =IFERROR(__xludf.DUMMYFUNCTION("sum(filter('Referring domains'!G:G,isnumber(match('Referring domains'!A:A,'Cost of backlinks (without low '!T:T,0)))) "),"#N/A") -> #N/A | M6: =L6*B6 -> #N/A
H8: Total backlinks | I8: Total value | L8: Total backlinks | M8: Total value
H9: =sum(H2:H6) -> #N/A | I9: =SUM(I2:I6) -> #N/A | L9: =sum(L2:L6) -> #N/A | M9: =SUM(M2:M6) -> #N/A
K12: minimum traffic
K13: 1000
