Workbook

Sheet data
A1: URL | B1: Title | C1: Title length | D1: No. of titles | E1: No. of groups having the same title | F1: No. of pages having the same title | G1: Is page title used in SERP | H1: HTTP status code | I1: Is indexable page | J1: Content type | K1: Is rendered page
A2: https://www.pikelandpropertygroup.com/ | B2: Pikeland Property Group - Sell My House Fast - We Buy Houses for Cash | C2: 69 | D2: 1 | E2: 2 | F2: 3 | H2: 200 | I2: TRUE | J2: text/html; charset=utf-8 | K2: TRUE
A3: https://www.pikelandpropertygroup.com/privacy-policy/ | B3: Privacy Policy - Pikeland Property Group | C3: 40 | D3: 1 | E3: 1 | F3: 1 | H3: 200 | I3: TRUE | J3: text/html; charset=utf-8 | K3: TRUE
A4: https://www.pikelandpropertygroup.com/faq/ | B4: FAQ - Pikeland Property Group | C4: 29 | D4: 1 | E4: 1 | F4: 1 | H4: 200 | I4: TRUE | J4: text/html; charset=utf-8 | K4: TRUE
A5: https://www.pikelandpropertygroup.com/how-we-buy-houses/ | B5: How It Works - Pikeland Property Group | C5: 38 | D5: 1 | E5: 1 | F5: 1 | H5: 200 | I5: TRUE | J5: text/html; charset=utf-8 | K5: TRUE
A6: https://www.pikelandpropertygroup.com/contact-us/ | B6: Contact Us - Pikeland Property Group | C6: 36 | D6: 1 | E6: 1 | F6: 1 | H6: 200 | I6: TRUE | J6: text/html; charset=utf-8 | K6: TRUE
A7: https://www.pikelandpropertygroup.com/reviews/ | B7: Reviews - Pikeland Property Group | C7: 33 | D7: 1 | E7: 1 | F7: 1 | H7: 200 | I7: TRUE | J7: text/html; charset=utf-8 | K7: TRUE
A8: https://www.pikelandpropertygroup.com/our-company/ | B8: About Us - Pikeland Property Group | C8: 34 | D8: 1 | E8: 1 | F8: 1 | H8: 200 | I8: TRUE | J8: text/html; charset=utf-8 | K8: TRUE
A9: https://www.pikelandpropertygroup.com/get-your-offer/ | B9: Get Your Offer - Pikeland Property Group | C9: 40 | D9: 1 | E9: 1 | F9: 1 | H9: 200 | I9: TRUE | J9: text/html; charset=utf-8 | K9: TRUE
A10: https://www.pikelandpropertygroup.com/blog/category/sellers/ | B10: sellers Archives - Pikeland Property Group | C10: 42 | D10: 1 | E10: 1 | F10: 1 | H10: 200 | I10: TRUE | J10: text/html; charset=utf-8 | K10: TRUE
A11: https://www.pikelandpropertygroup.com/blog/author/harrisonpikelandpropertygroup-com/ | B11: Harrison Hall, Author at Pikeland Property Group | C11: 48 | D11: 1 | E11: 1 | F11: 1 | H11: 200 | I11: TRUE | J11: text/html; charset=utf-8 | K11: TRUE
A12: https://www.pikelandpropertygroup.com/blog/category/building-credibility/ | B12: building-credibility Archives - Pikeland Property Group | C12: 55 | D12: 1 | E12: 1 | F12: 1 | H12: 200 | I12: TRUE | J12: text/html; charset=utf-8 | K12: TRUE
A13: https://www.pikelandpropertygroup.com/blog/category/buying-mobile-homes/ | B13: buying-mobile-homes Archives - Pikeland Property Group | C13: 54 | D13: 1 | E13: 1 | F13: 1 | H13: 200 | I13: TRUE | J13: text/html; charset=utf-8 | K13: TRUE
... A25: https://www.pikelandpropertygroup.com/blog/2023/08/ | B25: August 2023 - Pikeland Property Group | C25: 37 | D25: 1 | E25: 1 | F25: 1 | H25: 200 | I25: FALSE | J25: text/html; charset=utf-8 | K25: TRUE
A26: https://www.pikelandpropertygroup.com/stop-foreclosure/ | D26: 0 | H26: 404 | I26: FALSE | J26: text/html; charset=utf-8 | K26: FALSE
A27: https://www.pikelandpropertygroup.com/blog/faq-items/what-if-i-dont-need-a-fast-closing/ | B27: What if I don’t need a fast closing? - Pikeland Property Group | C27: 62 | D27: 1 | E27: 1 | F27: 1 | H27: 200 | I27: TRUE | J27: text/html; charset=utf-8 | K27: TRUE
A28: https://www.pikelandpropertygroup.com/blog/selling-a-property-that-needs-repairs-in-pennsylvania/ | B28: 6 Things You Need to Know About Selling a Property That Needs Repairs in Pennsylvania - Pikeland Property Group | C28: 111 | D28: 1 | E28: 1 | F28: 1 | H28: 200 | I28: TRUE | J28: text/html; charset=utf-8 | K28: TRUE
A29: https://www.pikelandpropertygroup.com/blog/selling-your-home-to-a-direct-buyer-pennsylvania/ | B29: 5 Mistakes to Avoid When Selling Your Home to a Direct Buyer in Pennsylvania - Pikeland Property Group | C29: 102 | D29: 1 | E29: 1 | F29: 1 | H29: 200 | I29: TRUE | J29: text/html; charset=utf-8 | K29: TRUE
A30: https://www.pikelandpropertygroup.com/blog/faq-items/what-are-the-benefits-of-selling-my-house-in-pennsylvania-to-a-cash-home-buyer/ | B30: What Are the Benefits of Selling My House in Pennsylvania To A Cash Home Buyer? - Pikeland Property Group | C30: 105 | D30: 1 | E30: 1 | F30: 1 | H30: 200 | I30: TRUE | J30: text/html; charset=utf-8 | K30: TRUE
A31: https://www.pikelandpropertygroup.com/blog/faq-items/how-fast-is-a-fast-closing/ | B31: How fast is a fast closing? - Pikeland Property Group | C31: 53 | D31: 1 | E31: 1 | F31: 1 | H31: 200 | I31: TRUE | J31: text/html; charset=utf-8 | K31: TRUE
A32: https://www.pikelandpropertygroup.com/blog/low-earning-vacation-rental-in-pennsylvania/ | B32: 5 Solutions to Help You With Your Low-Earning Vacation Rental in Pennsylvania - Pikeland Property Group | C32: 103 | D32: 1 | E32: 1 | F32: 1 | H32: 200 | I32: TRUE | J32: text/html; charset=utf-8 | K32: TRUE
A33: https://www.pikelandpropertygroup.com/blog/faq-items/how-are-you-different-from-a-real-estate-agent/ | B33: How are you different from a real estate agent? - Pikeland Property Group | C33: 73 | D33: 1 | E33: 1 | F33: 1 | H33: 200 | I33: TRUE | J33: text/html; charset=utf-8 | K33: TRUE
A34: https://www.pikelandpropertygroup.com/blog/faq-items/learn-about-our-process-and-sell-your-house-today/ | B34: Learn About Our Process and Sell Your House Today! - Pikeland Property Group | C34: 76 | D34: 1 | E34: 1 | F34: 1 | H34: 200 | I34: TRUE | J34: text/html; charset=utf-8 | K34: TRUE
A35: https://www.pikelandpropertygroup.com/blog/selling-your-home-to-a-direct-buyer-in-pennsylvania-3/ | B35: 6 Advantages of Selling Your Home to a Direct Buyer in Pennsylvania That You Might Not Know About - Pikeland Property Group | C35: 123 | D35: 1 | E35: 1 | F35: 1 | H35: 200 | I35: TRUE | J35: text/html; charset=utf-8 | K35: TRUE
A36: https://www.pikelandpropertygroup.com/blog/design-elements-that-can-make-it-difficult-to-sell-your-house-pennsylvania/ | B36: Dated Design Elements That Can make it Difficult to Sell Your House in Pennsylvania - Pikeland Property Group | C36: 109 | D36: 1 | E36: 1 | F36: 1 | H36: 200 | I36: TRUE | J36: text/html; charset=utf-8 | K36: TRUE
A37: https://www.pikelandpropertygroup.com/blog/selling-mobile-homes-pennsylvania/ | B37: Maximizing ROI: How to Make the Most Profit from Buying and Selling Mobile Homes in Pennsylvania - Pikeland Property Group | C37: 122 | D37: 1 | E37: 1 | F37: 1 | H37: 200 | I37: TRUE | J37: text/html; charset=utf-8 | K37: TRUE
A38: https://www.pikelandpropertygroup.com/blog/buying-and-selling-mobile-homes-pennsylvania/ | B38: Maximizing Profits: Tips for Buying and Selling Mobile Homes in Pennsylvania - Pikeland Property Group | C38: 102 | D38: 1 | E38: 1 | F38: 1 | H38: 200 | I38: TRUE | J38: text/html; charset=utf-8 | K38: TRUE
... A90: https://www.pikelandpropertygroup.com/blog/page/3/ | B90: Blog - Pikeland Property Group | C90: 30 | D90: 1 | E90: 1 | F90: 3 | H90: 200 | I90: FALSE | J90: text/html; charset=utf-8 | K90: TRUE
A91: https://www.pikelandpropertygroup.com/blog/faq_category/general/ | D91: 0 | H91: 404 | I91: FALSE | J91: text/html; charset=utf-8 | K91: FALSE
A92: https://www.pikelandpropertygroup.com/blog/fusion_tb_category/header/ | D92: 0 | H92: 301 | I92: FALSE | J92: text/html; charset=utf-8 | K92: FALSE
A93: https://www.pikelandpropertygroup.com/blog/fusion_tb_category/content/ | D93: 0 | H93: 301 | I93: FALSE | J93: text/html; charset=utf-8 | K93: FALSE
A94: https://www.pikelandpropertygroup.com/blog/element_category/elements/ | D94: 0 | H94: 301 | I94: FALSE | J94: text/html; charset=utf-8 | K94: FALSE
A95: https://www.pikelandpropertygroup.com/blog/page/4/ | B95: Blog - Pikeland Property Group | C95: 30 | D95: 1 | H95: 200 | I95: FALSE | J95: text/html; charset=utf-8 | K95: TRUE
A96: https://www.pikelandpropertygroup.com/blog/fusion_tb_category/page_title_bar/ | D96: 0 | H96: 301 | I96: FALSE | J96: text/html; charset=utf-8 | K96: FALSE
A97: https://www.pikelandpropertygroup.com/wp-content/uploads/2023/07/How-To-Stop-Foreclosure-Guide.pdf | D97: 0 | H97: 200 | I97: FALSE | J97: application/pdf | K97: FALSE
A98: https://www.pikelandpropertygroup.com/blog/element_category/sections/ | D98: 0 | H98: 301 | I98: FALSE | J98: text/html; charset=utf-8 | K98: FALSE
A99: https://www.pikelandpropertygroup.com/blog/faq_category/how-we-buy-houses/ | D99: 0 | H99: 301 | I99: FALSE | J99: text/html; charset=utf-8 | K99: FALSE
A100: https://www.pikelandpropertygroup.com/blog/faq_category/home/ | D100: 0 | H100: 404 | I100: FALSE | J100: text/html; charset=utf-8 | K100: FALSE
A101: https://www.pikelandpropertygroup.com/blog/element_category/post_cards/ | D101: 0 | H101: 301 | I101: FALSE | J101: text/html; charset=utf-8 | K101: FALSE
A102: http://www.pikelandpropertygroup.com/ | D102: 0 | H102: 301 | I102: FALSE | J102: text/html | K102: FALSE
A103: https://www.pikelandpropertygroup.com/blog/page/2/ | B103: Blog - Pikeland Property Group | C103: 30 | D103: 1 | E103: 1 | F103: 3 | H103: 200 | I103: FALSE | J103: text/html; charset=utf-8 | K103: TRUE
A104: https://www.pikelandpropertygroup.com/blog/fusion_tb_category/footer/ | D104: 0 | H104: 301 | I104: FALSE | J104: text/html; charset=utf-8 | K104: FALSE
A105: https://www.pikelandpropertygroup.com/page/2/ | B105: Pikeland Property Group - Sell My House Fast - We Buy Houses for Cash | C105: 69 | D105: 1 | E105: 2 | F105: 3 | H105: 200 | I105: FALSE | J105: text/html; charset=utf-8 | K105: TRUE
A106: https://www.pikelandpropertygroup.com/wp-content/uploads/2023/07/Selling-To-A-Real-Estate-Investor.pdf | D106: 0 | H106: 200 | I106: FALSE | J106: application/pdf | K106: FALSE
A107: https://www.pikelandpropertygroup.com/blog/element_category/columns/ | D107: 0 | H107: 301 | I107: FALSE | J107: text/html; charset=utf-8 | K107: FALSE

Sheet short-
A1: URL | B1: Title | C1: Title length | D1: No. of titles | E1: No. of groups having the same title | F1: No. of pages having the same title | G1: Is page title used in SERP | H1: HTTP status code | I1: Is indexable page | J1: Content type | K1: Is rendered page
A2: https://www.pikelandpropertygroup.com/ | B2: Pikeland Property Group - Sell My House Fast - We Buy Houses for Cash | C2: 69 | D2: 1 | E2: 2 | F2: 3 | H2: 200 | I2: TRUE | J2: text/html; charset=utf-8 | K2: TRUE
A3: https://www.pikelandpropertygroup.com/privacy-policy/ | B3: Privacy Policy - Pikeland Property Group | C3: 40 | D3: 1 | E3: 1 | F3: 1 | H3: 200 | I3: TRUE | J3: text/html; charset=utf-8 | K3: TRUE
A4: https://www.pikelandpropertygroup.com/faq/ | B4: FAQ - Pikeland Property Group | C4: 29 | D4: 1 | E4: 1 | F4: 1 | H4: 200 | I4: TRUE | J4: text/html; charset=utf-8 | K4: TRUE
A5: https://www.pikelandpropertygroup.com/how-we-buy-houses/ | B5: How It Works - Pikeland Property Group | C5: 38 | D5: 1 | E5: 1 | F5: 1 | H5: 200 | I5: TRUE | J5: text/html; charset=utf-8 | K5: TRUE
A6: https://www.pikelandpropertygroup.com/contact-us/ | B6: Contact Us - Pikeland Property Group | C6: 36 | D6: 1 | E6: 1 | F6: 1 | H6: 200 | I6: TRUE | J6: text/html; charset=utf-8 | K6: TRUE
A7: https://www.pikelandpropertygroup.com/reviews/ | B7: Reviews - Pikeland Property Group | C7: 33 | D7: 1 | E7: 1 | F7: 1 | H7: 200 | I7: TRUE | J7: text/html; charset=utf-8 | K7: TRUE
A8: https://www.pikelandpropertygroup.com/our-company/ | B8: About Us - Pikeland Property Group | C8: 34 | D8: 1 | E8: 1 | F8: 1 | H8: 200 | I8: TRUE | J8: text/html; charset=utf-8 | K8: TRUE
A9: https://www.pikelandpropertygroup.com/get-your-offer/ | B9: Get Your Offer - Pikeland Property Group | C9: 40 | D9: 1 | E9: 1 | F9: 1 | H9: 200 | I9: TRUE | J9: text/html; charset=utf-8 | K9: TRUE
A10: https://www.pikelandpropertygroup.com/blog/category/sellers/ | B10: sellers Archives - Pikeland Property Group | C10: 42 | D10: 1 | E10: 1 | F10: 1 | H10: 200 | I10: TRUE | J10: text/html; charset=utf-8 | K10: TRUE
A11: https://www.pikelandpropertygroup.com/blog/author/harrisonpikelandpropertygroup-com/ | B11: Harrison Hall, Author at Pikeland Property Group | C11: 48 | D11: 1 | E11: 1 | F11: 1 | H11: 200 | I11: TRUE | J11: text/html; charset=utf-8 | K11: TRUE
A12: https://www.pikelandpropertygroup.com/blog/category/building-credibility/ | B12: building-credibility Archives - Pikeland Property Group | C12: 55 | D12: 1 | E12: 1 | F12: 1 | H12: 200 | I12: TRUE | J12: text/html; charset=utf-8 | K12: TRUE
A13: https://www.pikelandpropertygroup.com/blog/category/buying-mobile-homes/ | B13: buying-mobile-homes Archives - Pikeland Property Group | C13: 54 | D13: 1 | E13: 1 | F13: 1 | H13: 200 | I13: TRUE | J13: text/html; charset=utf-8 | K13: TRUE
... A25: https://www.pikelandpropertygroup.com/blog/2023/08/ | B25: August 2023 - Pikeland Property Group | C25: 37 | D25: 1 | E25: 1 | F25: 1 | H25: 200 | I25: FALSE | J25: text/html; charset=utf-8 | K25: TRUE
A26: https://www.pikelandpropertygroup.com/stop-foreclosure/ | D26: 0 | H26: 404 | I26: FALSE | J26: text/html; charset=utf-8 | K26: FALSE
A27: https://www.pikelandpropertygroup.com/blog/faq-items/what-if-i-dont-need-a-fast-closing/ | B27: What if I don’t need a fast closing? - Pikeland Property Group | C27: 62 | D27: 1 | E27: 1 | F27: 1 | H27: 200 | I27: TRUE | J27: text/html; charset=utf-8 | K27: TRUE
A28: https://www.pikelandpropertygroup.com/blog/selling-a-property-that-needs-repairs-in-pennsylvania/ | B28: 6 Things You Need to Know About Selling a Property That Needs Repairs in Pennsylvania - Pikeland Property Group | C28: 111 | D28: 1 | E28: 1 | F28: 1 | H28: 200 | I28: TRUE | J28: text/html; charset=utf-8 | K28: TRUE
A29: https://www.pikelandpropertygroup.com/blog/selling-your-home-to-a-direct-buyer-pennsylvania/ | B29: 5 Mistakes to Avoid When Selling Your Home to a Direct Buyer in Pennsylvania - Pikeland Property Group | C29: 102 | D29: 1 | E29: 1 | F29: 1 | H29: 200 | I29: TRUE | J29: text/html; charset=utf-8 | K29: TRUE
A30: https://www.pikelandpropertygroup.com/blog/faq-items/what-are-the-benefits-of-selling-my-house-in-pennsylvania-to-a-cash-home-buyer/ | B30: What Are the Benefits of Selling My House in Pennsylvania To A Cash Home Buyer? - Pikeland Property Group | C30: 105 | D30: 1 | E30: 1 | F30: 1 | H30: 200 | I30: TRUE | J30: text/html; charset=utf-8 | K30: TRUE
A31: https://www.pikelandpropertygroup.com/blog/faq-items/how-fast-is-a-fast-closing/ | B31: How fast is a fast closing? - Pikeland Property Group | C31: 53 | D31: 1 | E31: 1 | F31: 1 | H31: 200 | I31: TRUE | J31: text/html; charset=utf-8 | K31: TRUE
A32: https://www.pikelandpropertygroup.com/blog/low-earning-vacation-rental-in-pennsylvania/ | B32: 5 Solutions to Help You With Your Low-Earning Vacation Rental in Pennsylvania - Pikeland Property Group | C32: 103 | D32: 1 | E32: 1 | F32: 1 | H32: 200 | I32: TRUE | J32: text/html; charset=utf-8 | K32: TRUE
A33: https://www.pikelandpropertygroup.com/blog/faq-items/how-are-you-different-from-a-real-estate-agent/ | B33: How are you different from a real estate agent? - Pikeland Property Group | C33: 73 | D33: 1 | E33: 1 | F33: 1 | H33: 200 | I33: TRUE | J33: text/html; charset=utf-8 | K33: TRUE
A34: https://www.pikelandpropertygroup.com/blog/faq-items/learn-about-our-process-and-sell-your-house-today/ | B34: Learn About Our Process and Sell Your House Today! - Pikeland Property Group | C34: 76 | D34: 1 | E34: 1 | F34: 1 | H34: 200 | I34: TRUE | J34: text/html; charset=utf-8 | K34: TRUE
A35: https://www.pikelandpropertygroup.com/blog/selling-your-home-to-a-direct-buyer-in-pennsylvania-3/ | B35: 6 Advantages of Selling Your Home to a Direct Buyer in Pennsylvania That You Might Not Know About - Pikeland Property Group | C35: 123 | D35: 1 | E35: 1 | F35: 1 | H35: 200 | I35: TRUE | J35: text/html; charset=utf-8 | K35: TRUE
A36: https://www.pikelandpropertygroup.com/blog/design-elements-that-can-make-it-difficult-to-sell-your-house-pennsylvania/ | B36: Dated Design Elements That Can make it Difficult to Sell Your House in Pennsylvania - Pikeland Property Group | C36: 109 | D36: 1 | E36: 1 | F36: 1 | H36: 200 | I36: TRUE | J36: text/html; charset=utf-8 | K36: TRUE
A37: https://www.pikelandpropertygroup.com/blog/selling-mobile-homes-pennsylvania/ | B37: Maximizing ROI: How to Make the Most Profit from Buying and Selling Mobile Homes in Pennsylvania - Pikeland Property Group | C37: 122 | D37: 1 | E37: 1 | F37: 1 | H37: 200 | I37: TRUE | J37: text/html; charset=utf-8 | K37: TRUE
A38: https://www.pikelandpropertygroup.com/blog/buying-and-selling-mobile-homes-pennsylvania/ | B38: Maximizing Profits: Tips for Buying and Selling Mobile Homes in Pennsylvania - Pikeland Property Group | C38: 102 | D38: 1 | E38: 1 | F38: 1 | H38: 200 | I38: TRUE | J38: text/html; charset=utf-8 | K38: TRUE
... A90: https://www.pikelandpropertygroup.com/blog/page/3/ | B90: Blog - Pikeland Property Group | C90: 30 | D90: 1 | E90: 1 | F90: 3 | H90: 200 | I90: FALSE | J90: text/html; charset=utf-8 | K90: TRUE
A91: https://www.pikelandpropertygroup.com/blog/faq_category/general/ | D91: 0 | H91: 404 | I91: FALSE | J91: text/html; charset=utf-8 | K91: FALSE
A92: https://www.pikelandpropertygroup.com/blog/fusion_tb_category/header/ | D92: 0 | H92: 301 | I92: FALSE | J92: text/html; charset=utf-8 | K92: FALSE
A93: https://www.pikelandpropertygroup.com/blog/fusion_tb_category/content/ | D93: 0 | H93: 301 | I93: FALSE | J93: text/html; charset=utf-8 | K93: FALSE
A94: https://www.pikelandpropertygroup.com/blog/element_category/elements/ | D94: 0 | H94: 301 | I94: FALSE | J94: text/html; charset=utf-8 | K94: FALSE
A95: https://www.pikelandpropertygroup.com/blog/page/4/ | B95: Blog - Pikeland Property Group | C95: 30 | D95: 1 | H95: 200 | I95: FALSE | J95: text/html; charset=utf-8 | K95: TRUE
A96: https://www.pikelandpropertygroup.com/blog/fusion_tb_category/page_title_bar/ | D96: 0 | H96: 301 | I96: FALSE | J96: text/html; charset=utf-8 | K96: FALSE
A97: https://www.pikelandpropertygroup.com/wp-content/uploads/2023/07/How-To-Stop-Foreclosure-Guide.pdf | D97: 0 | H97: 200 | I97: FALSE | J97: application/pdf | K97: FALSE
A98: https://www.pikelandpropertygroup.com/blog/element_category/sections/ | D98: 0 | H98: 301 | I98: FALSE | J98: text/html; charset=utf-8 | K98: FALSE
A99: https://www.pikelandpropertygroup.com/blog/faq_category/how-we-buy-houses/ | D99: 0 | H99: 301 | I99: FALSE | J99: text/html; charset=utf-8 | K99: FALSE
A100: https://www.pikelandpropertygroup.com/blog/faq_category/home/ | D100: 0 | H100: 404 | I100: FALSE | J100: text/html; charset=utf-8 | K100: FALSE
A101: https://www.pikelandpropertygroup.com/blog/element_category/post_cards/ | D101: 0 | H101: 301 | I101: FALSE | J101: text/html; charset=utf-8 | K101: FALSE
A102: http://www.pikelandpropertygroup.com/ | D102: 0 | H102: 301 | I102: FALSE | J102: text/html | K102: FALSE
A103: https://www.pikelandpropertygroup.com/blog/page/2/ | B103: Blog - Pikeland Property Group | C103: 30 | D103: 1 | E103: 1 | F103: 3 | H103: 200 | I103: FALSE | J103: text/html; charset=utf-8 | K103: TRUE
A104: https://www.pikelandpropertygroup.com/blog/fusion_tb_category/footer/ | D104: 0 | H104: 301 | I104: FALSE | J104: text/html; charset=utf-8 | K104: FALSE
A105: https://www.pikelandpropertygroup.com/page/2/ | B105: Pikeland Property Group - Sell My House Fast - We Buy Houses for Cash | C105: 69 | D105: 1 | E105: 2 | F105: 3 | H105: 200 | I105: FALSE | J105: text/html; charset=utf-8 | K105: TRUE
A106: https://www.pikelandpropertygroup.com/wp-content/uploads/2023/07/Selling-To-A-Real-Estate-Investor.pdf | D106: 0 | H106: 200 | I106: FALSE | J106: application/pdf | K106: FALSE
A107: https://www.pikelandpropertygroup.com/blog/element_category/columns/ | D107: 0 | H107: 301 | I107: FALSE | J107: text/html; charset=utf-8 | K107: FALSE

Sheet long-
A1: URL | B1: Title | C1: Title length | D1: No. of titles | E1: No. of groups having the same title | F1: No. of pages having the same title | G1: Is page title used in SERP | H1: HTTP status code | I1: Is indexable page | J1: Content type | K1: Is rendered page
A2: https://www.pikelandpropertygroup.com/ | B2: Pikeland Property Group - Sell My House Fast - We Buy Houses for Cash | C2: 69 | D2: 1 | E2: 2 | F2: 3 | H2: 200 | I2: TRUE | J2: text/html; charset=utf-8 | K2: TRUE
A3: https://www.pikelandpropertygroup.com/privacy-policy/ | B3: Privacy Policy - Pikeland Property Group | C3: 40 | D3: 1 | E3: 1 | F3: 1 | H3: 200 | I3: TRUE | J3: text/html; charset=utf-8 | K3: TRUE
A4: https://www.pikelandpropertygroup.com/faq/ | B4: FAQ - Pikeland Property Group | C4: 29 | D4: 1 | E4: 1 | F4: 1 | H4: 200 | I4: TRUE | J4: text/html; charset=utf-8 | K4: TRUE
A5: https://www.pikelandpropertygroup.com/how-we-buy-houses/ | B5: How It Works - Pikeland Property Group | C5: 38 | D5: 1 | E5: 1 | F5: 1 | H5: 200 | I5: TRUE | J5: text/html; charset=utf-8 | K5: TRUE
A6: https://www.pikelandpropertygroup.com/contact-us/ | B6: Contact Us - Pikeland Property Group | C6: 36 | D6: 1 | E6: 1 | F6: 1 | H6: 200 | I6: TRUE | J6: text/html; charset=utf-8 | K6: TRUE
A7: https://www.pikelandpropertygroup.com/reviews/ | B7: Reviews - Pikeland Property Group | C7: 33 | D7: 1 | E7: 1 | F7: 1 | H7: 200 | I7: TRUE | J7: text/html; charset=utf-8 | K7: TRUE
A8: https://www.pikelandpropertygroup.com/our-company/ | B8: About Us - Pikeland Property Group | C8: 34 | D8: 1 | E8: 1 | F8: 1 | H8: 200 | I8: TRUE | J8: text/html; charset=utf-8 | K8: TRUE
A9: https://www.pikelandpropertygroup.com/get-your-offer/ | B9: Get Your Offer - Pikeland Property Group | C9: 40 | D9: 1 | E9: 1 | F9: 1 | H9: 200 | I9: TRUE | J9: text/html; charset=utf-8 | K9: TRUE
A10: https://www.pikelandpropertygroup.com/blog/category/sellers/ | B10: sellers Archives - Pikeland Property Group | C10: 42 | D10: 1 | E10: 1 | F10: 1 | H10: 200 | I10: TRUE | J10: text/html; charset=utf-8 | K10: TRUE
A11: https://www.pikelandpropertygroup.com/blog/author/harrisonpikelandpropertygroup-com/ | B11: Harrison Hall, Author at Pikeland Property Group | C11: 48 | D11: 1 | E11: 1 | F11: 1 | H11: 200 | I11: TRUE | J11: text/html; charset=utf-8 | K11: TRUE
A12: https://www.pikelandpropertygroup.com/blog/category/building-credibility/ | B12: building-credibility Archives - Pikeland Property Group | C12: 55 | D12: 1 | E12: 1 | F12: 1 | H12: 200 | I12: TRUE | J12: text/html; charset=utf-8 | K12: TRUE
A13: https://www.pikelandpropertygroup.com/blog/category/buying-mobile-homes/ | B13: buying-mobile-homes Archives - Pikeland Property Group | C13: 54 | D13: 1 | E13: 1 | F13: 1 | H13: 200 | I13: TRUE | J13: text/html; charset=utf-8 | K13: TRUE
... A25: https://www.pikelandpropertygroup.com/blog/2023/08/ | B25: August 2023 - Pikeland Property Group | C25: 37 | D25: 1 | E25: 1 | F25: 1 | H25: 200 | I25: FALSE | J25: text/html; charset=utf-8 | K25: TRUE
A26: https://www.pikelandpropertygroup.com/stop-foreclosure/ | D26: 0 | H26: 404 | I26: FALSE | J26: text/html; charset=utf-8 | K26: FALSE
A27: https://www.pikelandpropertygroup.com/blog/faq-items/what-if-i-dont-need-a-fast-closing/ | B27: What if I don’t need a fast closing? - Pikeland Property Group | C27: 62 | D27: 1 | E27: 1 | F27: 1 | H27: 200 | I27: TRUE | J27: text/html; charset=utf-8 | K27: TRUE
A28: https://www.pikelandpropertygroup.com/blog/selling-a-property-that-needs-repairs-in-pennsylvania/ | B28: 6 Things You Need to Know About Selling a Property That Needs Repairs in Pennsylvania - Pikeland Property Group | C28: 111 | D28: 1 | E28: 1 | F28: 1 | H28: 200 | I28: TRUE | J28: text/html; charset=utf-8 | K28: TRUE
A29: https://www.pikelandpropertygroup.com/blog/selling-your-home-to-a-direct-buyer-pennsylvania/ | B29: 5 Mistakes to Avoid When Selling Your Home to a Direct Buyer in Pennsylvania - Pikeland Property Group | C29: 102 | D29: 1 | E29: 1 | F29: 1 | H29: 200 | I29: TRUE | J29: text/html; charset=utf-8 | K29: TRUE
A30: https://www.pikelandpropertygroup.com/blog/faq-items/what-are-the-benefits-of-selling-my-house-in-pennsylvania-to-a-cash-home-buyer/ | B30: What Are the Benefits of Selling My House in Pennsylvania To A Cash Home Buyer? - Pikeland Property Group | C30: 105 | D30: 1 | E30: 1 | F30: 1 | H30: 200 | I30: TRUE | J30: text/html; charset=utf-8 | K30: TRUE
A31: https://www.pikelandpropertygroup.com/blog/faq-items/how-fast-is-a-fast-closing/ | B31: How fast is a fast closing? - Pikeland Property Group | C31: 53 | D31: 1 | E31: 1 | F31: 1 | H31: 200 | I31: TRUE | J31: text/html; charset=utf-8 | K31: TRUE
A32: https://www.pikelandpropertygroup.com/blog/low-earning-vacation-rental-in-pennsylvania/ | B32: 5 Solutions to Help You With Your Low-Earning Vacation Rental in Pennsylvania - Pikeland Property Group | C32: 103 | D32: 1 | E32: 1 | F32: 1 | H32: 200 | I32: TRUE | J32: text/html; charset=utf-8 | K32: TRUE
A33: https://www.pikelandpropertygroup.com/blog/faq-items/how-are-you-different-from-a-real-estate-agent/ | B33: How are you different from a real estate agent? - Pikeland Property Group | C33: 73 | D33: 1 | E33: 1 | F33: 1 | H33: 200 | I33: TRUE | J33: text/html; charset=utf-8 | K33: TRUE
A34: https://www.pikelandpropertygroup.com/blog/faq-items/learn-about-our-process-and-sell-your-house-today/ | B34: Learn About Our Process and Sell Your House Today! - Pikeland Property Group | C34: 76 | D34: 1 | E34: 1 | F34: 1 | H34: 200 | I34: TRUE | J34: text/html; charset=utf-8 | K34: TRUE
A35: https://www.pikelandpropertygroup.com/blog/selling-your-home-to-a-direct-buyer-in-pennsylvania-3/ | B35: 6 Advantages of Selling Your Home to a Direct Buyer in Pennsylvania That You Might Not Know About - Pikeland Property Group | C35: 123 | D35: 1 | E35: 1 | F35: 1 | H35: 200 | I35: TRUE | J35: text/html; charset=utf-8 | K35: TRUE
A36: https://www.pikelandpropertygroup.com/blog/design-elements-that-can-make-it-difficult-to-sell-your-house-pennsylvania/ | B36: Dated Design Elements That Can make it Difficult to Sell Your House in Pennsylvania - Pikeland Property Group | C36: 109 | D36: 1 | E36: 1 | F36: 1 | H36: 200 | I36: TRUE | J36: text/html; charset=utf-8 | K36: TRUE
A37: https://www.pikelandpropertygroup.com/blog/selling-mobile-homes-pennsylvania/ | B37: Maximizing ROI: How to Make the Most Profit from Buying and Selling Mobile Homes in Pennsylvania - Pikeland Property Group | C37: 122 | D37: 1 | E37: 1 | F37: 1 | H37: 200 | I37: TRUE | J37: text/html; charset=utf-8 | K37: TRUE
A38: https://www.pikelandpropertygroup.com/blog/buying-and-selling-mobile-homes-pennsylvania/ | B38: Maximizing Profits: Tips for Buying and Selling Mobile Homes in Pennsylvania - Pikeland Property Group | C38: 102 | D38: 1 | E38: 1 | F38: 1 | H38: 200 | I38: TRUE | J38: text/html; charset=utf-8 | K38: TRUE
... A90: https://www.pikelandpropertygroup.com/blog/page/3/ | B90: Blog - Pikeland Property Group | C90: 30 | D90: 1 | E90: 1 | F90: 3 | H90: 200 | I90: FALSE | J90: text/html; charset=utf-8 | K90: TRUE
A91: https://www.pikelandpropertygroup.com/blog/faq_category/general/ | D91: 0 | H91: 404 | I91: FALSE | J91: text/html; charset=utf-8 | K91: FALSE
A92: https://www.pikelandpropertygroup.com/blog/fusion_tb_category/header/ | D92: 0 | H92: 301 | I92: FALSE | J92: text/html; charset=utf-8 | K92: FALSE
A93: https://www.pikelandpropertygroup.com/blog/fusion_tb_category/content/ | D93: 0 | H93: 301 | I93: FALSE | J93: text/html; charset=utf-8 | K93: FALSE
A94: https://www.pikelandpropertygroup.com/blog/element_category/elements/ | D94: 0 | H94: 301 | I94: FALSE | J94: text/html; charset=utf-8 | K94: FALSE
A95: https://www.pikelandpropertygroup.com/blog/page/4/ | B95: Blog - Pikeland Property Group | C95: 30 | D95: 1 | H95: 200 | I95: FALSE | J95: text/html; charset=utf-8 | K95: TRUE
A96: https://www.pikelandpropertygroup.com/blog/fusion_tb_category/page_title_bar/ | D96: 0 | H96: 301 | I96: FALSE | J96: text/html; charset=utf-8 | K96: FALSE
A97: https://www.pikelandpropertygroup.com/wp-content/uploads/2023/07/How-To-Stop-Foreclosure-Guide.pdf | D97: 0 | H97: 200 | I97: FALSE | J97: application/pdf | K97: FALSE
A98: https://www.pikelandpropertygroup.com/blog/element_category/sections/ | D98: 0 | H98: 301 | I98: FALSE | J98: text/html; charset=utf-8 | K98: FALSE
A99: https://www.pikelandpropertygroup.com/blog/faq_category/how-we-buy-houses/ | D99: 0 | H99: 301 | I99: FALSE | J99: text/html; charset=utf-8 | K99: FALSE
A100: https://www.pikelandpropertygroup.com/blog/faq_category/home/ | D100: 0 | H100: 404 | I100: FALSE | J100: text/html; charset=utf-8 | K100: FALSE
A101: https://www.pikelandpropertygroup.com/blog/element_category/post_cards/ | D101: 0 | H101: 301 | I101: FALSE | J101: text/html; charset=utf-8 | K101: FALSE
A102: http://www.pikelandpropertygroup.com/ | D102: 0 | H102: 301 | I102: FALSE | J102: text/html | K102: FALSE
A103: https://www.pikelandpropertygroup.com/blog/page/2/ | B103: Blog - Pikeland Property Group | C103: 30 | D103: 1 | E103: 1 | F103: 3 | H103: 200 | I103: FALSE | J103: text/html; charset=utf-8 | K103: TRUE
A104: https://www.pikelandpropertygroup.com/blog/fusion_tb_category/footer/ | D104: 0 | H104: 301 | I104: FALSE | J104: text/html; charset=utf-8 | K104: FALSE
A105: https://www.pikelandpropertygroup.com/page/2/ | B105: Pikeland Property Group - Sell My House Fast - We Buy Houses for Cash | C105: 69 | D105: 1 | E105: 2 | F105: 3 | H105: 200 | I105: FALSE | J105: text/html; charset=utf-8 | K105: TRUE
A106: https://www.pikelandpropertygroup.com/wp-content/uploads/2023/07/Selling-To-A-Real-Estate-Investor.pdf | D106: 0 | H106: 200 | I106: FALSE | J106: application/pdf | K106: FALSE
A107: https://www.pikelandpropertygroup.com/blog/element_category/columns/ | D107: 0 | H107: 301 | I107: FALSE | J107: text/html; charset=utf-8 | K107: FALSE

Sheet duplicates-
A1: URL | B1: Title | C1: Title length | D1: No. of titles | E1: No. of groups having the same title | F1: No. of pages having the same title | G1: Is page title used in SERP | H1: HTTP status code | I1: Is indexable page | J1: Content type | K1: Is rendered page
A2: https://www.pikelandpropertygroup.com/ | B2: Pikeland Property Group - Sell My House Fast - We Buy Houses for Cash | C2: 69 | D2: 1 | E2: 2 | F2: 3 | H2: 200 | I2: TRUE | J2: text/html; charset=utf-8 | K2: TRUE
A3: https://www.pikelandpropertygroup.com/privacy-policy/ | B3: Privacy Policy - Pikeland Property Group | C3: 40 | D3: 1 | E3: 1 | F3: 1 | H3: 200 | I3: TRUE | J3: text/html; charset=utf-8 | K3: TRUE
A4: https://www.pikelandpropertygroup.com/faq/ | B4: FAQ - Pikeland Property Group | C4: 29 | D4: 1 | E4: 1 | F4: 1 | H4: 200 | I4: TRUE | J4: text/html; charset=utf-8 | K4: TRUE
A5: https://www.pikelandpropertygroup.com/how-we-buy-houses/ | B5: How It Works - Pikeland Property Group | C5: 38 | D5: 1 | E5: 1 | F5: 1 | H5: 200 | I5: TRUE | J5: text/html; charset=utf-8 | K5: TRUE
A6: https://www.pikelandpropertygroup.com/contact-us/ | B6: Contact Us - Pikeland Property Group | C6: 36 | D6: 1 | E6: 1 | F6: 1 | H6: 200 | I6: TRUE | J6: text/html; charset=utf-8 | K6: TRUE
A7: https://www.pikelandpropertygroup.com/reviews/ | B7: Reviews - Pikeland Property Group | C7: 33 | D7: 1 | E7: 1 | F7: 1 | H7: 200 | I7: TRUE | J7: text/html; charset=utf-8 | K7: TRUE
A8: https://www.pikelandpropertygroup.com/our-company/ | B8: About Us - Pikeland Property Group | C8: 34 | D8: 1 | E8: 1 | F8: 1 | H8: 200 | I8: TRUE | J8: text/html; charset=utf-8 | K8: TRUE
A9: https://www.pikelandpropertygroup.com/get-your-offer/ | B9: Get Your Offer - Pikeland Property Group | C9: 40 | D9: 1 | E9: 1 | F9: 1 | H9: 200 | I9: TRUE | J9: text/html; charset=utf-8 | K9: TRUE
A10: https://www.pikelandpropertygroup.com/blog/category/sellers/ | B10: sellers Archives - Pikeland Property Group | C10: 42 | D10: 1 | E10: 1 | F10: 1 | H10: 200 | I10: TRUE | J10: text/html; charset=utf-8 | K10: TRUE
A11: https://www.pikelandpropertygroup.com/blog/author/harrisonpikelandpropertygroup-com/ | B11: Harrison Hall, Author at Pikeland Property Group | C11: 48 | D11: 1 | E11: 1 | F11: 1 | H11: 200 | I11: TRUE | J11: text/html; charset=utf-8 | K11: TRUE
A12: https://www.pikelandpropertygroup.com/blog/category/building-credibility/ | B12: building-credibility Archives - Pikeland Property Group | C12: 55 | D12: 1 | E12: 1 | F12: 1 | H12: 200 | I12: TRUE | J12: text/html; charset=utf-8 | K12: TRUE
A13: https://www.pikelandpropertygroup.com/blog/category/buying-mobile-homes/ | B13: buying-mobile-homes Archives - Pikeland Property Group | C13: 54 | D13: 1 | E13: 1 | F13: 1 | H13: 200 | I13: TRUE | J13: text/html; charset=utf-8 | K13: TRUE
... A25: https://www.pikelandpropertygroup.com/blog/2023/08/ | B25: August 2023 - Pikeland Property Group | C25: 37 | D25: 1 | E25: 1 | F25: 1 | H25: 200 | I25: FALSE | J25: text/html; charset=utf-8 | K25: TRUE
A26: https://www.pikelandpropertygroup.com/stop-foreclosure/ | D26: 0 | H26: 404 | I26: FALSE | J26: text/html; charset=utf-8 | K26: FALSE
A27: https://www.pikelandpropertygroup.com/blog/faq-items/what-if-i-dont-need-a-fast-closing/ | B27: What if I don’t need a fast closing? - Pikeland Property Group | C27: 62 | D27: 1 | E27: 1 | F27: 1 | H27: 200 | I27: TRUE | J27: text/html; charset=utf-8 | K27: TRUE
A28: https://www.pikelandpropertygroup.com/blog/selling-a-property-that-needs-repairs-in-pennsylvania/ | B28: 6 Things You Need to Know About Selling a Property That Needs Repairs in Pennsylvania - Pikeland Property Group | C28: 111 | D28: 1 | E28: 1 | F28: 1 | H28: 200 | I28: TRUE | J28: text/html; charset=utf-8 | K28: TRUE
A29: https://www.pikelandpropertygroup.com/blog/selling-your-home-to-a-direct-buyer-pennsylvania/ | B29: 5 Mistakes to Avoid When Selling Your Home to a Direct Buyer in Pennsylvania - Pikeland Property Group | C29: 102 | D29: 1 | E29: 1 | F29: 1 | H29: 200 | I29: TRUE | J29: text/html; charset=utf-8 | K29: TRUE
A30: https://www.pikelandpropertygroup.com/blog/faq-items/what-are-the-benefits-of-selling-my-house-in-pennsylvania-to-a-cash-home-buyer/ | B30: What Are the Benefits of Selling My House in Pennsylvania To A Cash Home Buyer? - Pikeland Property Group | C30: 105 | D30: 1 | E30: 1 | F30: 1 | H30: 200 | I30: TRUE | J30: text/html; charset=utf-8 | K30: TRUE
A31: https://www.pikelandpropertygroup.com/blog/faq-items/how-fast-is-a-fast-closing/ | B31: How fast is a fast closing? - Pikeland Property Group | C31: 53 | D31: 1 | E31: 1 | F31: 1 | H31: 200 | I31: TRUE | J31: text/html; charset=utf-8 | K31: TRUE
A32: https://www.pikelandpropertygroup.com/blog/low-earning-vacation-rental-in-pennsylvania/ | B32: 5 Solutions to Help You With Your Low-Earning Vacation Rental in Pennsylvania - Pikeland Property Group | C32: 103 | D32: 1 | E32: 1 | F32: 1 | H32: 200 | I32: TRUE | J32: text/html; charset=utf-8 | K32: TRUE
A33: https://www.pikelandpropertygroup.com/blog/faq-items/how-are-you-different-from-a-real-estate-agent/ | B33: How are you different from a real estate agent? - Pikeland Property Group | C33: 73 | D33: 1 | E33: 1 | F33: 1 | H33: 200 | I33: TRUE | J33: text/html; charset=utf-8 | K33: TRUE
A34: https://www.pikelandpropertygroup.com/blog/faq-items/learn-about-our-process-and-sell-your-house-today/ | B34: Learn About Our Process and Sell Your House Today! - Pikeland Property Group | C34: 76 | D34: 1 | E34: 1 | F34: 1 | H34: 200 | I34: TRUE | J34: text/html; charset=utf-8 | K34: TRUE
A35: https://www.pikelandpropertygroup.com/blog/selling-your-home-to-a-direct-buyer-in-pennsylvania-3/ | B35: 6 Advantages of Selling Your Home to a Direct Buyer in Pennsylvania That You Might Not Know About - Pikeland Property Group | C35: 123 | D35: 1 | E35: 1 | F35: 1 | H35: 200 | I35: TRUE | J35: text/html; charset=utf-8 | K35: TRUE
A36: https://www.pikelandpropertygroup.com/blog/design-elements-that-can-make-it-difficult-to-sell-your-house-pennsylvania/ | B36: Dated Design Elements That Can make it Difficult to Sell Your House in Pennsylvania - Pikeland Property Group | C36: 109 | D36: 1 | E36: 1 | F36: 1 | H36: 200 | I36: TRUE | J36: text/html; charset=utf-8 | K36: TRUE
A37: https://www.pikelandpropertygroup.com/blog/selling-mobile-homes-pennsylvania/ | B37: Maximizing ROI: How to Make the Most Profit from Buying and Selling Mobile Homes in Pennsylvania - Pikeland Property Group | C37: 122 | D37: 1 | E37: 1 | F37: 1 | H37: 200 | I37: TRUE | J37: text/html; charset=utf-8 | K37: TRUE
A38: https://www.pikelandpropertygroup.com/blog/buying-and-selling-mobile-homes-pennsylvania/ | B38: Maximizing Profits: Tips for Buying and Selling Mobile Homes in Pennsylvania - Pikeland Property Group | C38: 102 | D38: 1 | E38: 1 | F38: 1 | H38: 200 | I38: TRUE | J38: text/html; charset=utf-8 | K38: TRUE
... A90: https://www.pikelandpropertygroup.com/blog/page/3/ | B90: Blog - Pikeland Property Group | C90: 30 | D90: 1 | E90: 1 | F90: 3 | H90: 200 | I90: FALSE | J90: text/html; charset=utf-8 | K90: TRUE
A91: https://www.pikelandpropertygroup.com/blog/faq_category/general/ | D91: 0 | H91: 404 | I91: FALSE | J91: text/html; charset=utf-8 | K91: FALSE
A92: https://www.pikelandpropertygroup.com/blog/fusion_tb_category/header/ | D92: 0 | H92: 301 | I92: FALSE | J92: text/html; charset=utf-8 | K92: FALSE
A93: https://www.pikelandpropertygroup.com/blog/fusion_tb_category/content/ | D93: 0 | H93: 301 | I93: FALSE | J93: text/html; charset=utf-8 | K93: FALSE
A94: https://www.pikelandpropertygroup.com/blog/element_category/elements/ | D94: 0 | H94: 301 | I94: FALSE | J94: text/html; charset=utf-8 | K94: FALSE
A95: https://www.pikelandpropertygroup.com/blog/page/4/ | B95: Blog - Pikeland Property Group | C95: 30 | D95: 1 | H95: 200 | I95: FALSE | J95: text/html; charset=utf-8 | K95: TRUE
A96: https://www.pikelandpropertygroup.com/blog/fusion_tb_category/page_title_bar/ | D96: 0 | H96: 301 | I96: FALSE | J96: text/html; charset=utf-8 | K96: FALSE
A97: https://www.pikelandpropertygroup.com/wp-content/uploads/2023/07/How-To-Stop-Foreclosure-Guide.pdf | D97: 0 | H97: 200 | I97: FALSE | J97: application/pdf | K97: FALSE
A98: https://www.pikelandpropertygroup.com/blog/element_category/sections/ | D98: 0 | H98: 301 | I98: FALSE | J98: text/html; charset=utf-8 | K98: FALSE
A99: https://www.pikelandpropertygroup.com/blog/faq_category/how-we-buy-houses/ | D99: 0 | H99: 301 | I99: FALSE | J99: text/html; charset=utf-8 | K99: FALSE
A100: https://www.pikelandpropertygroup.com/blog/faq_category/home/ | D100: 0 | H100: 404 | I100: FALSE | J100: text/html; charset=utf-8 | K100: FALSE
A101: https://www.pikelandpropertygroup.com/blog/element_category/post_cards/ | D101: 0 | H101: 301 | I101: FALSE | J101: text/html; charset=utf-8 | K101: FALSE
A102: http://www.pikelandpropertygroup.com/ | D102: 0 | H102: 301 | I102: FALSE | J102: text/html | K102: FALSE
A103: https://www.pikelandpropertygroup.com/blog/page/2/ | B103: Blog - Pikeland Property Group | C103: 30 | D103: 1 | E103: 1 | F103: 3 | H103: 200 | I103: FALSE | J103: text/html; charset=utf-8 | K103: TRUE
A104: https://www.pikelandpropertygroup.com/blog/fusion_tb_category/footer/ | D104: 0 | H104: 301 | I104: FALSE | J104: text/html; charset=utf-8 | K104: FALSE
A105: https://www.pikelandpropertygroup.com/page/2/ | B105: Pikeland Property Group - Sell My House Fast - We Buy Houses for Cash | C105: 69 | D105: 1 | E105: 2 | F105: 3 | H105: 200 | I105: FALSE | J105: text/html; charset=utf-8 | K105: TRUE
A106: https://www.pikelandpropertygroup.com/wp-content/uploads/2023/07/Selling-To-A-Real-Estate-Investor.pdf | D106: 0 | H106: 200 | I106: FALSE | J106: application/pdf | K106: FALSE
A107: https://www.pikelandpropertygroup.com/blog/element_category/columns/ | D107: 0 | H107: 301 | I107: FALSE | J107: text/html; charset=utf-8 | K107: FALSE

Sheet suffixes
A1: URL | B1: Title | C1: Title length | D1: No. of titles | E1: No. of groups having the same title | F1: No. of pages having the same title | G1: Is page title used in SERP | H1: HTTP status code | I1: Is indexable page | J1: Content type | K1: Is rendered page | L1: Suffixes
A2: https://www.pikelandpropertygroup.com/ | B2: Pikeland Property Group - Sell My House Fast - We Buy Houses for Cash | C2: 69 | D2: 1 | E2: 2 | F2: 3 | H2: 200 | I2: TRUE | J2: text/html; charset=utf-8 | K2: TRUE | L2: =IFERROR(__xludf.DUMMYFUNCTION("IFNA(REGEXEXTRACT(B2,""[\-|–][^–|\-]+$""))"),"- We Buy Houses for Cash") -> - We Buy Houses for Cash
A3: https://www.pikelandpropertygroup.com/privacy-policy/ | B3: Privacy Policy - Pikeland Property Group | C3: 40 | D3: 1 | E3: 1 | F3: 1 | H3: 200 | I3: TRUE | J3: text/html; charset=utf-8 | K3: TRUE | L3: =IFERROR(__xludf.DUMMYFUNCTION("IFNA(REGEXEXTRACT(B3,""[\-|–][^–|\-]+$""))"),"- Pikeland Property Group") -> - Pikeland Property Group
A4: https://www.pikelandpropertygroup.com/faq/ | B4: FAQ - Pikeland Property Group | C4: 29 | D4: 1 | E4: 1 | F4: 1 | H4: 200 | I4: TRUE | J4: text/html; charset=utf-8 | K4: TRUE | L4: =IFERROR(__xludf.DUMMYFUNCTION("IFNA(REGEXEXTRACT(B4,""[\-|–][^–|\-]+$""))"),"- Pikeland Property Group") -> - Pikeland Property Group
A5: https://www.pikelandpropertygroup.com/how-we-buy-houses/ | B5: How It Works - Pikeland Property Group | C5: 38 | D5: 1 | E5: 1 | F5: 1 | H5: 200 | I5: TRUE | J5: text/html; charset=utf-8 | K5: TRUE | L5: =IFERROR(__xludf.DUMMYFUNCTION("IFNA(REGEXEXTRACT(B5,""[\-|–][^–|\-]+$""))"),"- Pikeland Property Group") -> - Pikeland Property Group
A6: https://www.pikelandpropertygroup.com/contact-us/ | B6: Contact Us - Pikeland Property Group | C6: 36 | D6: 1 | E6: 1 | F6: 1 | H6: 200 | I6: TRUE | J6: text/html; charset=utf-8 | K6: TRUE | L6: =IFERROR(__xludf.DUMMYFUNCTION("IFNA(REGEXEXTRACT(B6,""[\-|–][^–|\-]+$""))"),"- Pikeland Property Group") -> - Pikeland Property Group
A7: https://www.pikelandpropertygroup.com/reviews/ | B7: Reviews - Pikeland Property Group | C7: 33 | D7: 1 | E7: 1 | F7: 1 | H7: 200 | I7: TRUE | J7: text/html; charset=utf-8 | K7: TRUE | L7: =IFERROR(__xludf.DUMMYFUNCTION("IFNA(REGEXEXTRACT(B7,""[\-|–][^–|\-]+$""))"),"- Pikeland Property Group") -> - Pikeland Property Group
A8: https://www.pikelandpropertygroup.com/our-company/ | B8: About Us - Pikeland Property Group | C8: 34 | D8: 1 | E8: 1 | F8: 1 | H8: 200 | I8: TRUE | J8: text/html; charset=utf-8 | K8: TRUE | L8: =IFERROR(__xludf.DUMMYFUNCTION("IFNA(REGEXEXTRACT(B8,""[\-|–][^–|\-]+$""))"),"- Pikeland Property Group") -> - Pikeland Property Group
A9: https://www.pikelandpropertygroup.com/get-your-offer/ | B9: Get Your Offer - Pikeland Property Group | C9: 40 | D9: 1 | E9: 1 | F9: 1 | H9: 200 | I9: TRUE | J9: text/html; charset=utf-8 | K9: TRUE | L9: =IFERROR(__xludf.DUMMYFUNCTION("IFNA(REGEXEXTRACT(B9,""[\-|–][^–|\-]+$""))"),"- Pikeland Property Group") -> - Pikeland Property Group
A10: https://www.pikelandpropertygroup.com/blog/category/sellers/ | B10: sellers Archives - Pikeland Property Group | C10: 42 | D10: 1 | E10: 1 | F10: 1 | H10: 200 | I10: TRUE | J10: text/html; charset=utf-8 | K10: TRUE | L10: =IFERROR(__xludf.DUMMYFUNCTION("IFNA(REGEXEXTRACT(B10,""[\-|–][^–|\-]+$""))"),"- Pikeland Property Group") -> - Pikeland Property Group
A11: https://www.pikelandpropertygroup.com/blog/author/harrisonpikelandpropertygroup-com/ | B11: Harrison Hall, Author at Pikeland Property Group | C11: 48 | D11: 1 | E11: 1 | F11: 1 | H11: 200 | I11: TRUE | J11: text/html; charset=utf-8 | K11: TRUE | L11: =IFERROR(__xludf.DUMMYFUNCTION("IFNA(REGEXEXTRACT(B11,""[\-|–][^–|\-]+$""))"),"")
A12: https://www.pikelandpropertygroup.com/blog/category/building-credibility/ | B12: building-credibility Archives - Pikeland Property Group | C12: 55 | D12: 1 | E12: 1 | F12: 1 | H12: 200 | I12: TRUE | J12: text/html; charset=utf-8 | K12: TRUE | L12: =IFERROR(__xludf.DUMMYFUNCTION("IFNA(REGEXEXTRACT(B12,""[\-|–][^–|\-]+$""))"),"- Pikeland Property Group") -> - Pikeland Property Group
A13: https://www.pikelandpropertygroup.com/blog/category/buying-mobile-homes/ | B13: buying-mobile-homes Archives - Pikeland Property Group | C13: 54 | D13: 1 | E13: 1 | F13: 1 | H13: 200 | I13: TRUE | J13: text/html; charset=utf-8 | K13: TRUE | L13: =IFERROR(__xludf.DUMMYFUNCTION("IFNA(REGEXEXTRACT(B13,""[\-|–][^–|\-]+$""))"),"- Pikeland Property Group") -> - Pikeland Property Group
A14: https://www.pikelandpropertygroup.com/blog/category/uncategorized/ | B14: Uncategorized Archives - Pikeland Property Group | C14: 48 | D14: 1 | E14: 1 | F14: 1 | H14: 200 | I14: TRUE | J14: text/html; charset=utf-8 | K14: TRUE | L14: =IFERROR(__xludf.DUMMYFUNCTION("IFNA(REGEXEXTRACT(B14,""[\-|–][^–|\-]+$""))"),"- Pikeland Property Group") -> - Pikeland Property Group
A15: https://www.pikelandpropertygroup.com/blog/category/selling-mobile-homes/ | B15: selling-mobile-homes Archives - Pikeland Property Group | C15: 55 | D15: 1 | E15: 1 | F15: 1 | H15: 200 | I15: TRUE | J15: text/html; charset=utf-8 | K15: TRUE | L15: =IFERROR(__xludf.DUMMYFUNCTION("IFNA(REGEXEXTRACT(B15,""[\-|–][^–|\-]+$""))"),"- Pikeland Property Group") -> - Pikeland Property Group
A16: https://www.pikelandpropertygroup.com/get-a-cash-offer-today/ | B16: Sell My House Fast Philadelphia - We Buy Houses for Cash - Pikeland Property Group | C16: 82 | D16: 1 | E16: 2 | F16: 2 | H16: 200 | I16: TRUE | J16: text/html; charset=utf-8 | K16: TRUE | L16: =IFERROR(__xludf.DUMMYFUNCTION("IFNA(REGEXEXTRACT(B16,""[\-|–][^–|\-]+$""))"),"- Pikeland Property Group") -> - Pikeland Property Group
A17: https://www.pikelandpropertygroup.com/blog/author/tommy/ | B17: Tommy, Author at Pikeland Property Group | C17: 40 | D17: 1 | E17: 1 | F17: 1 | H17: 200 | I17: FALSE | J17: text/html; charset=utf-8 | K17: TRUE | L17: =IFERROR(__xludf.DUMMYFUNCTION("IFNA(REGEXEXTRACT(B17,""[\-|–][^–|\-]+$""))"),"")
A18: https://www.pikelandpropertygroup.com/blog/2024/05/ | B18: May 2024 - Pikeland Property Group | C18: 34 | D18: 1 | E18: 1 | F18: 1 | H18: 200 | I18: FALSE | J18: text/html; charset=utf-8 | K18: TRUE | L18: =IFERROR(__xludf.DUMMYFUNCTION("IFNA(REGEXEXTRACT(B18,""[\-|–][^–|\-]+$""))"),"- Pikeland Property Group") -> - Pikeland Property Group
A19: https://www.pikelandpropertygroup.com/blog/2023/10/ | B19: October 2023 - Pikeland Property Group | C19: 38 | D19: 1 | E19: 1 | F19: 1 | H19: 200 | I19: FALSE | J19: text/html; charset=utf-8 | K19: TRUE | L19: =IFERROR(__xludf.DUMMYFUNCTION("IFNA(REGEXEXTRACT(B19,""[\-|–][^–|\-]+$""))"),"- Pikeland Property Group") -> - Pikeland Property Group
A20: https://www.pikelandpropertygroup.com/blog/2024/04/ | B20: April 2024 - Pikeland Property Group | C20: 36 | D20: 1 | E20: 1 | F20: 1 | H20: 200 | I20: FALSE | J20: text/html; charset=utf-8 | K20: TRUE | L20: =IFERROR(__xludf.DUMMYFUNCTION("IFNA(REGEXEXTRACT(B20,""[\-|–][^–|\-]+$""))"),"- Pikeland Property Group") -> - Pikeland Property Group
A21: https://www.pikelandpropertygroup.com/blog/2024/01/ | B21: January 2024 - Pikeland Property Group | C21: 38 | D21: 1 | E21: 1 | F21: 1 | H21: 200 | I21: FALSE | J21: text/html; charset=utf-8 | K21: TRUE | L21: =IFERROR(__xludf.DUMMYFUNCTION("IFNA(REGEXEXTRACT(B21,""[\-|–][^–|\-]+$""))"),"- Pikeland Property Group") -> - Pikeland Property Group
A22: https://www.pikelandpropertygroup.com/blog/2024/03/ | B22: March 2024 - Pikeland Property Group | C22: 36 | D22: 1 | E22: 1 | F22: 1 | H22: 200 | I22: FALSE | J22: text/html; charset=utf-8 | K22: TRUE | L22: =IFERROR(__xludf.DUMMYFUNCTION("IFNA(REGEXEXTRACT(B22,""[\-|–][^–|\-]+$""))"),"- Pikeland Property Group") -> - Pikeland Property Group
A23: https://www.pikelandpropertygroup.com/blog/2023/09/ | B23: September 2023 - Pikeland Property Group | C23: 40 | D23: 1 | E23: 1 | F23: 1 | H23: 200 | I23: FALSE | J23: text/html; charset=utf-8 | K23: TRUE | L23: =IFERROR(__xludf.DUMMYFUNCTION("IFNA(REGEXEXTRACT(B23,""[\-|–][^–|\-]+$""))"),"- Pikeland Property Group") -> - Pikeland Property Group
A24: https://www.pikelandpropertygroup.com/blog/2024/02/ | B24: February 2024 - Pikeland Property Group | C24: 39 | D24: 1 | E24: 1 | F24: 1 | H24: 200 | I24: FALSE | J24: text/html; charset=utf-8 | K24: TRUE | L24: =IFERROR(__xludf.DUMMYFUNCTION("IFNA(REGEXEXTRACT(B24,""[\-|–][^–|\-]+$""))"),"- Pikeland Property Group") -> - Pikeland Property Group
A25: https://www.pikelandpropertygroup.com/blog/2023/08/ | B25: August 2023 - Pikeland Property Group | C25: 37 | D25: 1 | E25: 1 | F25: 1 | H25: 200 | I25: FALSE | J25: text/html; charset=utf-8 | K25: TRUE | L25: =IFERROR(__xludf.DUMMYFUNCTION("IFNA(REGEXEXTRACT(B25,""[\-|–][^–|\-]+$""))"),"- Pikeland Property Group") -> - Pikeland Property Group
A26: https://www.pikelandpropertygroup.com/stop-foreclosure/ | D26: 0 | H26: 404 | I26: FALSE | J26: text/html; charset=utf-8 | K26: FALSE | L26: =IFERROR(__xludf.DUMMYFUNCTION("IFNA(REGEXEXTRACT(B26,""[\-|–][^–|\-]+$""))"),"")
A27: https://www.pikelandpropertygroup.com/blog/faq-items/what-if-i-dont-need-a-fast-closing/ | B27: What if I don’t need a fast closing? - Pikeland Property Group | C27: 62 | D27: 1 | E27: 1 | F27: 1 | H27: 200 | I27: TRUE | J27: text/html; charset=utf-8 | K27: TRUE | L27: =IFERROR(__xludf.DUMMYFUNCTION("IFNA(REGEXEXTRACT(B27,""[\-|–][^–|\-]+$""))"),"- Pikeland Property Group") -> - Pikeland Property Group
A28: https://www.pikelandpropertygroup.com/blog/selling-a-property-that-needs-repairs-in-pennsylvania/ | B28: 6 Things You Need to Know About Selling a Property That Needs Repairs in Pennsylvania - Pikeland Property Group | C28: 111 | D28: 1 | E28: 1 | F28: 1 | H28: 200 | I28: TRUE | J28: text/html; charset=utf-8 | K28: TRUE | L28: =IFERROR(__xludf.DUMMYFUNCTION("IFNA(REGEXEXTRACT(B28,""[\-|–][^–|\-]+$""))"),"- Pikeland Property Group") -> - Pikeland Property Group
A29: https://www.pikelandpropertygroup.com/blog/selling-your-home-to-a-direct-buyer-pennsylvania/ | B29: 5 Mistakes to Avoid When Selling Your Home to a Direct Buyer in Pennsylvania - Pikeland Property Group | C29: 102 | D29: 1 | E29: 1 | F29: 1 | H29: 200 | I29: TRUE | J29: text/html; charset=utf-8 | K29: TRUE | L29: =IFERROR(__xludf.DUMMYFUNCTION("IFNA(REGEXEXTRACT(B29,""[\-|–][^–|\-]+$""))"),"- Pikeland Property Group") -> - Pikeland Property Group
A30: https://www.pikelandpropertygroup.com/blog/faq-items/what-are-the-benefits-of-selling-my-house-in-pennsylvania-to-a-cash-home-buyer/ | B30: What Are the Benefits of Selling My House in Pennsylvania To A Cash Home Buyer? - Pikeland Property Group | C30: 105 | D30: 1 | E30: 1 | F30: 1 | H30: 200 | I30: TRUE | J30: text/html; charset=utf-8 | K30: TRUE | L30: =IFERROR(__xludf.DUMMYFUNCTION("IFNA(REGEXEXTRACT(B30,""[\-|–][^–|\-]+$""))"),"- Pikeland Property Group") -> - Pikeland Property Group
A31: https://www.pikelandpropertygroup.com/blog/faq-items/how-fast-is-a-fast-closing/ | B31: How fast is a fast closing? - Pikeland Property Group | C31: 53 | D31: 1 | E31: 1 | F31: 1 | H31: 200 | I31: TRUE | J31: text/html; charset=utf-8 | K31: TRUE | L31: =IFERROR(__xludf.DUMMYFUNCTION("IFNA(REGEXEXTRACT(B31,""[\-|–][^–|\-]+$""))"),"- Pikeland Property Group") -> - Pikeland Property Group
A32: https://www.pikelandpropertygroup.com/blog/low-earning-vacation-rental-in-pennsylvania/ | B32: 5 Solutions to Help You With Your Low-Earning Vacation Rental in Pennsylvania - Pikeland Property Group | C32: 103 | D32: 1 | E32: 1 | F32: 1 | H32: 200 | I32: TRUE | J32: text/html; charset=utf-8 | K32: TRUE | L32: =IFERROR(__xludf.DUMMYFUNCTION("IFNA(REGEXEXTRACT(B32,""[\-|–][^–|\-]+$""))"),"- Pikeland Property Group") -> - Pikeland Property Group
A33: https://www.pikelandpropertygroup.com/blog/faq-items/how-are-you-different-from-a-real-estate-agent/ | B33: How are you different from a real estate agent? - Pikeland Property Group | C33: 73 | D33: 1 | E33: 1 | F33: 1 | H33: 200 | I33: TRUE | J33: text/html; charset=utf-8 | K33: TRUE | L33: =IFERROR(__xludf.DUMMYFUNCTION("IFNA(REGEXEXTRACT(B33,""[\-|–][^–|\-]+$""))"),"- Pikeland Property Group") -> - Pikeland Property Group
A34: https://www.pikelandpropertygroup.com/blog/faq-items/learn-about-our-process-and-sell-your-house-today/ | B34: Learn About Our Process and Sell Your House Today! - Pikeland Property Group | C34: 76 | D34: 1 | E34: 1 | F34: 1 | H34: 200 | I34: TRUE | J34: text/html; charset=utf-8 | K34: TRUE | L34: =IFERROR(__xludf.DUMMYFUNCTION("IFNA(REGEXEXTRACT(B34,""[\-|–][^–|\-]+$""))"),"- Pikeland Property Group") -> - Pikeland Property Group
A35: https://www.pikelandpropertygroup.com/blog/selling-your-home-to-a-direct-buyer-in-pennsylvania-3/ | B35: 6 Advantages of Selling Your Home to a Direct Buyer in Pennsylvania That You Might Not Know About - Pikeland Property Group | C35: 123 | D35: 1 | E35: 1 | F35: 1 | H35: 200 | I35: TRUE | J35: text/html; charset=utf-8 | K35: TRUE | L35: =IFERROR(__xludf.DUMMYFUNCTION("IFNA(REGEXEXTRACT(B35,""[\-|–][^–|\-]+$""))"),"- Pikeland Property Group") -> - Pikeland Property Group
A36: https://www.pikelandpropertygroup.com/blog/design-elements-that-can-make-it-difficult-to-sell-your-house-pennsylvania/ | B36: Dated Design Elements That Can make it Difficult to Sell Your House in Pennsylvania - Pikeland Property Group | C36: 109 | D36: 1 | E36: 1 | F36: 1 | H36: 200 | I36: TRUE | J36: text/html; charset=utf-8 | K36: TRUE | L36: =IFERROR(__xludf.DUMMYFUNCTION("IFNA(REGEXEXTRACT(B36,""[\-|–][^–|\-]+$""))"),"- Pikeland Property Group") -> - Pikeland Property Group
A37: https://www.pikelandpropertygroup.com/blog/selling-mobile-homes-pennsylvania/ | B37: Maximizing ROI: How to Make the Most Profit from Buying and Selling Mobile Homes in Pennsylvania - Pikeland Property Group | C37: 122 | D37: 1 | E37: 1 | F37: 1 | H37: 200 | I37: TRUE | J37: text/html; charset=utf-8 | K37: TRUE | L37: =IFERROR(__xludf.DUMMYFUNCTION("IFNA(REGEXEXTRACT(B37,""[\-|–][^–|\-]+$""))"),"- Pikeland Property Group") -> - Pikeland Property Group
A38: https://www.pikelandpropertygroup.com/blog/buying-and-selling-mobile-homes-pennsylvania/ | B38: Maximizing Profits: Tips for Buying and Selling Mobile Homes in Pennsylvania - Pikeland Property Group | C38: 102 | D38: 1 | E38: 1 | F38: 1 | H38: 200 | I38: TRUE | J38: text/html; charset=utf-8 | K38: TRUE | L38: =IFERROR(__xludf.DUMMYFUNCTION("IFNA(REGEXEXTRACT(B38,""[\-|–][^–|\-]+$""))"),"- Pikeland Property Group") -> - Pikeland Property Group
A39: https://www.pikelandpropertygroup.com/blog/buying-and-selling-ranches-and-horse-properties-in-pennsylvania/ | B39: 5 Important Things You Need to Know About Buying and Selling Ranches and Horse Properties in Pennsylvania - Pikeland Property Group | C39: 131 | D39: 1 | E39: 1 | F39: 1 | H39: 200 | I39: TRUE | J39: text/html; charset=utf-8 | K39: TRUE | L39: =IFERROR(__xludf.DUMMYFUNCTION("IFNA(REGEXEXTRACT(B39,""[\-|–][^–|\-]+$""))"),"- Pikeland Property Group") -> - Pikeland Property Group
A40: https://www.pikelandpropertygroup.com/blog/sell-their-house-directly-in-pennsylvania/ | B40: 5 of the Top Reasons Homeowners Opt to Sell Their House Directly in Pennsylvania - Pikeland Property Group | C40: 106 | D40: 1 | E40: 1 | F40: 1 | H40: 200 | I40: TRUE | J40: text/html; charset=utf-8 | K40: TRUE | L40: =IFERROR(__xludf.DUMMYFUNCTION("IFNA(REGEXEXTRACT(B40,""[\-|–][^–|\-]+$""))"),"- Pikeland Property Group") -> - Pikeland Property Group
A41: https://www.pikelandpropertygroup.com/blog/faq-items/is-there-any-obligation-when-i-submit-my-information/ | B41: Is there any obligation when I submit my information? - Pikeland Property Group | C41: 79 | D41: 1 | E41: 1 | F41: 1 | H41: 200 | I41: TRUE | J41: text/html; charset=utf-8 | K41: TRUE | L41: =IFERROR(__xludf.DUMMYFUNCTION("IFNA(REGEXEXTRACT(B41,""[\-|–][^–|\-]+$""))"),"- Pikeland Property Group") -> - Pikeland Property Group
A42: https://www.pikelandpropertygroup.com/blog/costs-you-may-face-when-selling-your-house-pennsylvania/ | B42: Commissions, Repairs, Marketing, and Other Potential Costs You May Face When Selling Your House in Pennsylvania - Pikeland Property Group | C42: 137 | D42: 1 | E42: 1 | F42: 1 | H42: 200 | I42: TRUE | J42: text/html; charset=utf-8 | K42: TRUE | L42: =IFERROR(__xludf.DUMMYFUNCTION("IFNA(REGEXEXTRACT(B42,""[\-|–][^–|\-]+$""))"),"- Pikeland Property Group") -> - Pikeland Property Group
A43: https://www.pikelandpropertygroup.com/blog/investors-are-swooping-up-properties-in-pennsylvania/ | B43: 7 Reasons Investors Are Swooping Up Properties in Pennsylvania - Pikeland Property Group | C43: 88 | D43: 1 | E43: 1 | F43: 1 | H43: 200 | I43: TRUE | J43: text/html; charset=utf-8 | K43: TRUE | L43: =IFERROR(__xludf.DUMMYFUNCTION("IFNA(REGEXEXTRACT(B43,""[\-|–][^–|\-]+$""))"),"- Pikeland Property Group") -> - Pikeland Property Group
A44: https://www.pikelandpropertygroup.com/blog/faq-items/how-do-you-determine-the-price-to-offer-on-my-house/ | B44: How do you determine the price to offer on my house? - Pikeland Property Group | C44: 78 | D44: 1 | E44: 1 | F44: 1 | H44: 200 | I44: TRUE | J44: text/html; charset=utf-8 | K44: TRUE | L44: =IFERROR(__xludf.DUMMYFUNCTION("IFNA(REGEXEXTRACT(B44,""[\-|–][^–|\-]+$""))"),"- Pikeland Property Group") -> - Pikeland Property Group
A45: https://www.pikelandpropertygroup.com/blog/selling-a-house-during-a-divorce-in-pennsylvania/ | B45: 6 Tips for Selling a House During a Divorce in Pennsylvania - Pikeland Property Group | C45: 85 | D45: 1 | E45: 1 | F45: 1 | H45: 200 | I45: TRUE | J45: text/html; charset=utf-8 | K45: TRUE | L45: =IFERROR(__xludf.DUMMYFUNCTION("IFNA(REGEXEXTRACT(B45,""[\-|–][^–|\-]+$""))"),"- Pikeland Property Group") -> - Pikeland Property Group
A46: https://www.pikelandpropertygroup.com/blog/ | B46: Blog - Pikeland Property Group | C46: 30 | D46: 1 | E46: 1 | F46: 3 | H46: 200 | I46: TRUE | J46: text/html; charset=utf-8 | K46: TRUE | L46: =IFERROR(__xludf.DUMMYFUNCTION("IFNA(REGEXEXTRACT(B46,""[\-|–][^–|\-]+$""))"),"- Pikeland Property Group") -> - Pikeland Property Group
A47: https://www.pikelandpropertygroup.com/blog/faq-items/will-you-list-my-house-on-the-mls-or-will-you-be-the-actual-buyer/ | B47: Will you list my house on the MLS, or will you be the actual buyer? - Pikeland Property Group | C47: 93 | D47: 1 | E47: 1 | F47: 1 | H47: 200 | I47: TRUE | J47: text/html; charset=utf-8 | K47: TRUE | L47: =IFERROR(__xludf.DUMMYFUNCTION("IFNA(REGEXEXTRACT(B47,""[\-|–][^–|\-]+$""))"),"- Pikeland Property Group") -> - Pikeland Property Group
A48: https://www.pikelandpropertygroup.com/blog/sell-an-unwanted-house-in-pennsylvania/ | B48: 7 Ways Pikeland Property Group Makes it Simple to Sell An Unwanted House in Pennsylvania - Pikeland Property Group | C48: 114 | D48: 1 | E48: 1 | F48: 1 | H48: 200 | I48: TRUE | J48: text/html; charset=utf-8 | K48: TRUE | L48: =IFERROR(__xludf.DUMMYFUNCTION("IFNA(REGEXEXTRACT(B48,""[\-|–][^–|\-]+$""))"),"- Pikeland Property Group") -> - Pikeland Property Group
A49: https://www.pikelandpropertygroup.com/blog/pennsylvania-real-estate-investors-can-incorporate-multi-family-properties-into-their-portfolios/ | B49: How Pennsylvania Real Estate Investors Can Incorporate Multi-Family Properties Into Their Portfolios - Pikeland Property Group | C49: 126 | D49: 1 | E49: 1 | F49: 1 | H49: 200 | I49: TRUE | J49: text/html; charset=utf-8 | K49: TRUE | L49: =IFERROR(__xludf.DUMMYFUNCTION("IFNA(REGEXEXTRACT(B49,""[\-|–][^–|\-]+$""))"),"- Pikeland Property Group") -> - Pikeland Property Group
A50: https://www.pikelandpropertygroup.com/blog/sell-a-vacant-or-abandoned-home-in-pennsylvania/ | B50: 8 Tips to Help You Sell a Vacant or Abandoned Home in Pennsylvania - Pikeland Property Group | C50: 92 | D50: 1 | E50: 1 | F50: 1 | H50: 200 | I50: TRUE | J50: text/html; charset=utf-8 | K50: TRUE | L50: =IFERROR(__xludf.DUMMYFUNCTION("IFNA(REGEXEXTRACT(B50,""[\-|–][^–|\-]+$""))"),"- Pikeland Property Group") -> - Pikeland Property Group
A51: https://www.pikelandpropertygroup.com/blog/faq-items/is-selling-a-house-to-a-we-buy-houses-company-in-pennsylvania-a-good-idea/ | B51: Is Selling a House to A “We Buy Houses” Company in Pennsylvania a Good Idea? - Pikeland Property Group | C51: 102 | D51: 1 | E51: 1 | F51: 1 | H51: 200 | I51: TRUE | J51: text/html; charset=utf-8 | K51: TRUE | L51: =IFERROR(__xludf.DUMMYFUNCTION("IFNA(REGEXEXTRACT(B51,""[\-|–][^–|\-]+$""))"),"- Pikeland Property Group") -> - Pikeland Property Group
A52: https://www.pikelandpropertygroup.com/blog/faq-items/is-this-even-legit/ | B52: Is this even legit? - Pikeland Property Group | C52: 45 | D52: 1 | E52: 1 | F52: 1 | H52: 200 | I52: TRUE | J52: text/html; charset=utf-8 | K52: TRUE | L52: =IFERROR(__xludf.DUMMYFUNCTION("IFNA(REGEXEXTRACT(B52,""[\-|–][^–|\-]+$""))"),"- Pikeland Property Group") -> - Pikeland Property Group
A53: https://www.pikelandpropertygroup.com/blog/selling-their-homes-in-pennsylvania-3/ | B53: 6 Misconceptions Homeowners Have About Selling Their Homes in Pennsylvania - Pikeland Property Group | C53: 100 | D53: 1 | E53: 1 | F53: 1 | H53: 200 | I53: TRUE | J53: text/html; charset=utf-8 | K53: TRUE | L53: =IFERROR(__xludf.DUMMYFUNCTION("IFNA(REGEXEXTRACT(B53,""[\-|–][^–|\-]+$""))"),"- Pikeland Property Group") -> - Pikeland Property Group
A54: https://www.pikelandpropertygroup.com/blog/faq-items/what-does-as-is-mean/ | B54: What does “as-is” mean? - Pikeland Property Group | C54: 49 | D54: 1 | E54: 1 | F54: 1 | H54: 200 | I54: TRUE | J54: text/html; charset=utf-8 | K54: TRUE | L54: =IFERROR(__xludf.DUMMYFUNCTION("IFNA(REGEXEXTRACT(B54,""[\-|–][^–|\-]+$""))"),"- Pikeland Property Group") -> - Pikeland Property Group
A55: https://www.pikelandpropertygroup.com/blog/investing-in-mobile-homes-pennsylvania/ | B55: Expert Insights: Strategies for Investing in Mobile Homes in Pennsylvania - Pikeland Property Group | C55: 99 | D55: 1 | E55: 1 | F55: 1 | H55: 200 | I55: TRUE | J55: text/html; charset=utf-8 | K55: TRUE | L55: =IFERROR(__xludf.DUMMYFUNCTION("IFNA(REGEXEXTRACT(B55,""[\-|–][^–|\-]+$""))"),"- Pikeland Property Group") -> - Pikeland Property Group
A56: https://www.pikelandpropertygroup.com/blog/faq-items/will-i-get-a-lowball-offer/ | B56: Will I get a lowball offer? - Pikeland Property Group | C56: 53 | D56: 1 | E56: 1 | F56: 1 | H56: 200 | I56: TRUE | J56: text/html; charset=utf-8 | K56: TRUE | L56: =IFERROR(__xludf.DUMMYFUNCTION("IFNA(REGEXEXTRACT(B56,""[\-|–][^–|\-]+$""))"),"- Pikeland Property Group") -> - Pikeland Property Group
A57: https://www.pikelandpropertygroup.com/blog/direct-buyer-pennsylvania/ | B57: 5 Ways That Selling Your Home to a Direct Buyer Can Save You from Unnecessary Hassle in Pennsylvania - Pikeland Property Group | C57: 126 | D57: 1 | E57: 1 | F57: 1 | H57: 200 | I57: TRUE | J57: text/html; charset=utf-8 | K57: TRUE | L57: =IFERROR(__xludf.DUMMYFUNCTION("IFNA(REGEXEXTRACT(B57,""[\-|–][^–|\-]+$""))"),"- Pikeland Property Group") -> - Pikeland Property Group
A58: https://www.pikelandpropertygroup.com/blog/predictions-for-the-mobile-home-market-pennsylvania/ | B58: Staying Ahead of the Game: Trends and Predictions for the Mobile Home Market in Pennsylvania - Pikeland Property Group | C58: 118 | D58: 1 | E58: 1 | F58: 1 | H58: 200 | I58: TRUE | J58: text/html; charset=utf-8 | K58: TRUE | L58: =IFERROR(__xludf.DUMMYFUNCTION("IFNA(REGEXEXTRACT(B58,""[\-|–][^–|\-]+$""))"),"- Pikeland Property Group") -> - Pikeland Property Group
A59: https://www.pikelandpropertygroup.com/blog/faq-items/what-does-an-all-cash-offer-mean/ | B59: What does an “all-cash offer” mean? - Pikeland Property Group | C59: 61 | D59: 1 | E59: 1 | F59: 1 | H59: 200 | I59: TRUE | J59: text/html; charset=utf-8 | K59: TRUE | L59: =IFERROR(__xludf.DUMMYFUNCTION("IFNA(REGEXEXTRACT(B59,""[\-|–][^–|\-]+$""))"),"- Pikeland Property Group") -> - Pikeland Property Group
A60: https://www.pikelandpropertygroup.com/blog/real-estate-professionals-in-pennsylvania/ | B60: 5 Things That Make Pikeland Property Group Unique From Other Real Estate Professionals in Pennsylvania - Pikeland Property Group | C60: 128 | D60: 1 | E60: 1 | F60: 1 | H60: 200 | I60: TRUE | J60: text/html; charset=utf-8 | K60: TRUE | L60: =IFERROR(__xludf.DUMMYFUNCTION("IFNA(REGEXEXTRACT(B60,""[\-|–][^–|\-]+$""))"),"- Pikeland Property Group") -> - Pikeland Property Group
A61: https://www.pikelandpropertygroup.com/blog/faq-items/do-you-pay-fair-prices-for-properties/ | B61: Do you pay fair prices for properties? - Pikeland Property Group | C61: 64 | D61: 1 | E61: 1 | F61: 1 | H61: 200 | I61: TRUE | J61: text/html; charset=utf-8 | K61: TRUE | L61: =IFERROR(__xludf.DUMMYFUNCTION("IFNA(REGEXEXTRACT(B61,""[\-|–][^–|\-]+$""))"),"- Pikeland Property Group") -> - Pikeland Property Group
A62: https://www.pikelandpropertygroup.com/blog/faq-items/are-there-any-fees-or-commissions-to-work-with-you/ | B62: Are there any fees or commissions to work with you? - Pikeland Property Group | C62: 77 | D62: 1 | E62: 1 | F62: 1 | H62: 200 | I62: TRUE | J62: text/html; charset=utf-8 | K62: TRUE | L62: =IFERROR(__xludf.DUMMYFUNCTION("IFNA(REGEXEXTRACT(B62,""[\-|–][^–|\-]+$""))"),"- Pikeland Property Group") -> - Pikeland Property Group
A63: https://www.pikelandpropertygroup.com/blog/faq-items/sell-your-house-fast-in-pennsylvania/ | B63: Sell Your House Fast in Pennsylvania - Pikeland Property Group | C63: 62 | D63: 1 | E63: 1 | F63: 1 | H63: 200 | I63: TRUE | J63: text/html; charset=utf-8 | K63: TRUE | L63: =IFERROR(__xludf.DUMMYFUNCTION("IFNA(REGEXEXTRACT(B63,""[\-|–][^–|\-]+$""))"),"- Pikeland Property Group") -> - Pikeland Property Group
A64: https://www.pikelandpropertygroup.com/sell-your-house-fast-in-reading-pa/ | B64: Sell My House Fast Pennsylvania [market_state] - We buy houses in Pennsylvania - Pikeland Property Group | C64: 104 | D64: 1 | E64: 2 | F64: 10 | H64: 200 | I64: TRUE | J64: text/html; charset=utf-8 | K64: TRUE | L64: =IFERROR(__xludf.DUMMYFUNCTION("IFNA(REGEXEXTRACT(B64,""[\-|–][^–|\-]+$""))"),"- Pikeland Property Group") -> - Pikeland Property Group
A65: https://www.pikelandpropertygroup.com/blog/author/harrisonpikelandpropertygroup-com/page/2/ | B65: Harrison Hall, Author at Pikeland Property Group - Page 2 of 2 | C65: 62 | D65: 1 | E65: 1 | F65: 1 | H65: 200 | I65: TRUE | J65: text/html; charset=utf-8 | K65: TRUE | L65: =IFERROR(__xludf.DUMMYFUNCTION("IFNA(REGEXEXTRACT(B65,""[\-|–][^–|\-]+$""))"),"- Page 2 of 2") -> - Page 2 of 2
A66: https://www.pikelandpropertygroup.com/blog/faq-items/ | B66: FAQs Archive - Pikeland Property Group | C66: 38 | D66: 1 | E66: 1 | F66: 1 | H66: 200 | I66: TRUE | J66: text/html; charset=utf-8 | K66: TRUE | L66: =IFERROR(__xludf.DUMMYFUNCTION("IFNA(REGEXEXTRACT(B66,""[\-|–][^–|\-]+$""))"),"- Pikeland Property Group") -> - Pikeland Property Group
A67: https://www.pikelandpropertygroup.com/sell-house-awn/ | B67: Pikeland Property Group - Sell My House Fast - We Buy Houses for Cash | C67: 69 | D67: 1 | E67: 2 | F67: 3 | H67: 200 | I67: TRUE | J67: text/html; charset=utf-8 | K67: TRUE | L67: =IFERROR(__xludf.DUMMYFUNCTION("IFNA(REGEXEXTRACT(B67,""[\-|–][^–|\-]+$""))"),"- We Buy Houses for Cash") -> - We Buy Houses for Cash
A68: https://www.pikelandpropertygroup.com/sell-your-house-fast-in-philadelphia-pa/ | B68: Sell My House Fast Pennsylvania [market_state] - We buy houses in Pennsylvania - Pikeland Property Group | C68: 104 | D68: 1 | E68: 2 | F68: 10 | H68: 200 | I68: TRUE | J68: text/html; charset=utf-8 | K68: TRUE | L68: =IFERROR(__xludf.DUMMYFUNCTION("IFNA(REGEXEXTRACT(B68,""[\-|–][^–|\-]+$""))"),"- Pikeland Property Group") -> - Pikeland Property Group
A69: https://www.pikelandpropertygroup.com/sell-your-house-fast-in-wilmington-de/ | B69: Sell My House Fast Pennsylvania [market_state] - We buy houses in Pennsylvania - Pikeland Property Group | C69: 104 | D69: 1 | E69: 2 | F69: 10 | H69: 200 | I69: TRUE | J69: text/html; charset=utf-8 | K69: TRUE | L69: =IFERROR(__xludf.DUMMYFUNCTION("IFNA(REGEXEXTRACT(B69,""[\-|–][^–|\-]+$""))"),"- Pikeland Property Group") -> - Pikeland Property Group
A70: https://www.pikelandpropertygroup.com/resource-page/ | B70: Sell My House Fast Philadelphia - We Buy Houses for Cash - Pikeland Property Group | C70: 82 | D70: 1 | E70: 2 | F70: 2 | H70: 200 | I70: TRUE | J70: text/html; charset=utf-8 | K70: TRUE | L70: =IFERROR(__xludf.DUMMYFUNCTION("IFNA(REGEXEXTRACT(B70,""[\-|–][^–|\-]+$""))"),"- Pikeland Property Group") -> - Pikeland Property Group
A71: https://www.pikelandpropertygroup.com/sell-your-house-fast-in-pittsburgh-pa/ | B71: Sell My House Fast Pennsylvania [market_state] - We buy houses in Pennsylvania - Pikeland Property Group | C71: 104 | D71: 1 | E71: 2 | F71: 10 | H71: 200 | I71: TRUE | J71: text/html; charset=utf-8 | K71: TRUE | L71: =IFERROR(__xludf.DUMMYFUNCTION("IFNA(REGEXEXTRACT(B71,""[\-|–][^–|\-]+$""))"),"- Pikeland Property Group") -> - Pikeland Property Group
A72: https://www.pikelandpropertygroup.com/terms-of-user/ | B72: Terms of Use - Pikeland Property Group | C72: 38 | D72: 1 | E72: 1 | F72: 1 | H72: 200 | I72: TRUE | J72: text/html; charset=utf-8 | K72: TRUE | L72: =IFERROR(__xludf.DUMMYFUNCTION("IFNA(REGEXEXTRACT(B72,""[\-|–][^–|\-]+$""))"),"- Pikeland Property Group") -> - Pikeland Property Group
A73: https://www.pikelandpropertygroup.com/sell-your-house-fast-in-phoenixville-pa/ | B73: Sell My House Fast Pennsylvania [market_state] - We buy houses in Pennsylvania - Pikeland Property Group | C73: 104 | D73: 1 | E73: 2 | F73: 10 | H73: 200 | I73: TRUE | J73: text/html; charset=utf-8 | K73: TRUE | L73: =IFERROR(__xludf.DUMMYFUNCTION("IFNA(REGEXEXTRACT(B73,""[\-|–][^–|\-]+$""))"),"- Pikeland Property Group") -> - Pikeland Property Group
A74: https://www.pikelandpropertygroup.com/sell-your-house-fast-in-coatesville-pa/ | B74: Sell My House Fast Pennsylvania [market_state] - We buy houses in Pennsylvania - Pikeland Property Group | C74: 104 | D74: 1 | E74: 2 | F74: 10 | H74: 200 | I74: TRUE | J74: text/html; charset=utf-8 | K74: TRUE | L74: =IFERROR(__xludf.DUMMYFUNCTION("IFNA(REGEXEXTRACT(B74,""[\-|–][^–|\-]+$""))"),"- Pikeland Property Group") -> - Pikeland Property Group
A75: https://www.pikelandpropertygroup.com/sell-your-house-fast-in-upper-darby-pa/ | B75: Sell My House Fast Pennsylvania [market_state] - We buy houses in Pennsylvania - Pikeland Property Group | C75: 104 | D75: 1 | E75: 2 | F75: 10 | H75: 200 | I75: TRUE | J75: text/html; charset=utf-8 | K75: TRUE | L75: =IFERROR(__xludf.DUMMYFUNCTION("IFNA(REGEXEXTRACT(B75,""[\-|–][^–|\-]+$""))"),"- Pikeland Property Group") -> - Pikeland Property Group
A76: https://www.pikelandpropertygroup.com/blog/faq-items/page/2/ | B76: FAQs Archive - Page 2 of 2 - Pikeland Property Group | C76: 52 | D76: 1 | E76: 1 | F76: 1 | H76: 200 | I76: TRUE | J76: text/html; charset=utf-8 | K76: TRUE | L76: =IFERROR(__xludf.DUMMYFUNCTION("IFNA(REGEXEXTRACT(B76,""[\-|–][^–|\-]+$""))"),"- Pikeland Property Group") -> - Pikeland Property Group
A77: https://www.pikelandpropertygroup.com/thank-you/contact/ | B77: Thank You - Pikeland Property Group | C77: 35 | D77: 1 | E77: 2 | F77: 2 | H77: 200 | I77: TRUE | J77: text/html; charset=utf-8 | K77: TRUE | L77: =IFERROR(__xludf.DUMMYFUNCTION("IFNA(REGEXEXTRACT(B77,""[\-|–][^–|\-]+$""))"),"- Pikeland Property Group") -> - Pikeland Property Group
A78: https://www.pikelandpropertygroup.com/sell-your-house-fast-in-york-pa/ | B78: Sell My House Fast Pennsylvania [market_state] - We buy houses in Pennsylvania - Pikeland Property Group | C78: 104 | D78: 1 | E78: 2 | F78: 10 | H78: 200 | I78: TRUE | J78: text/html; charset=utf-8 | K78: TRUE | L78: =IFERROR(__xludf.DUMMYFUNCTION("IFNA(REGEXEXTRACT(B78,""[\-|–][^–|\-]+$""))"),"- Pikeland Property Group") -> - Pikeland Property Group
A79: https://www.pikelandpropertygroup.com/house-information/ | B79: House Information - Pikeland Property Group | C79: 43 | D79: 1 | E79: 1 | F79: 1 | H79: 200 | I79: TRUE | J79: text/html; charset=utf-8 | K79: TRUE | L79: =IFERROR(__xludf.DUMMYFUNCTION("IFNA(REGEXEXTRACT(B79,""[\-|–][^–|\-]+$""))"),"- Pikeland Property Group") -> - Pikeland Property Group
A80: https://www.pikelandpropertygroup.com/sell-your-house-fast-in-lancaster-pa/ | B80: Sell My House Fast Pennsylvania [market_state] - We buy houses in Pennsylvania - Pikeland Property Group | C80: 104 | D80: 1 | E80: 2 | F80: 10 | H80: 200 | I80: TRUE | J80: text/html; charset=utf-8 | K80: TRUE | L80: =IFERROR(__xludf.DUMMYFUNCTION("IFNA(REGEXEXTRACT(B80,""[\-|–][^–|\-]+$""))"),"- Pikeland Property Group") -> - Pikeland Property Group
A81: https://www.pikelandpropertygroup.com/blog/category/sellers/page/2/ | B81: sellers Archives - Page 2 of 2 - Pikeland Property Group | C81: 56 | D81: 1 | E81: 1 | F81: 1 | H81: 200 | I81: TRUE | J81: text/html; charset=utf-8 | K81: TRUE | L81: =IFERROR(__xludf.DUMMYFUNCTION("IFNA(REGEXEXTRACT(B81,""[\-|–][^–|\-]+$""))"),"- Pikeland Property Group") -> - Pikeland Property Group
A82: https://www.pikelandpropertygroup.com/sell-your-house-fast-in-pottstown-pa/ | B82: Sell My House Fast Pennsylvania [market_state] - We buy houses in Pennsylvania - Pikeland Property Group | C82: 104 | D82: 1 | E82: 2 | F82: 10 | H82: 200 | I82: TRUE | J82: text/html; charset=utf-8 | K82: TRUE | L82: =IFERROR(__xludf.DUMMYFUNCTION("IFNA(REGEXEXTRACT(B82,""[\-|–][^–|\-]+$""))"),"- Pikeland Property Group") -> - Pikeland Property Group
A83: https://www.pikelandpropertygroup.com/compare/ | B83: Compare - Pikeland Property Group | C83: 33 | D83: 1 | E83: 1 | F83: 1 | H83: 200 | I83: TRUE | J83: text/html; charset=utf-8 | K83: TRUE | L83: =IFERROR(__xludf.DUMMYFUNCTION("IFNA(REGEXEXTRACT(B83,""[\-|–][^–|\-]+$""))"),"- Pikeland Property Group") -> - Pikeland Property Group
A84: https://www.pikelandpropertygroup.com/avoiding-foreclosure/ | B84: Avoiding Foreclosure - Pikeland Property Group | C84: 46 | D84: 1 | E84: 1 | F84: 1 | H84: 200 | I84: TRUE | J84: text/html; charset=utf-8 | K84: TRUE | L84: =IFERROR(__xludf.DUMMYFUNCTION("IFNA(REGEXEXTRACT(B84,""[\-|–][^–|\-]+$""))"),"- Pikeland Property Group") -> - Pikeland Property Group
A85: https://www.pikelandpropertygroup.com/thank-you/ | B85: Thank You - Pikeland Property Group | C85: 35 | D85: 1 | E85: 2 | F85: 2 | H85: 200 | I85: TRUE | J85: text/html; charset=utf-8 | K85: TRUE | L85: =IFERROR(__xludf.DUMMYFUNCTION("IFNA(REGEXEXTRACT(B85,""[\-|–][^–|\-]+$""))"),"- Pikeland Property Group") -> - Pikeland Property Group
A86: https://www.pikelandpropertygroup.com/faq_category/home/ | B86: Home Archives - Pikeland Property Group | C86: 39 | D86: 1 | E86: 1 | F86: 1 | H86: 200 | I86: FALSE | J86: text/html; charset=utf-8 | K86: TRUE | L86: =IFERROR(__xludf.DUMMYFUNCTION("IFNA(REGEXEXTRACT(B86,""[\-|–][^–|\-]+$""))"),"- Pikeland Property Group") -> - Pikeland Property Group
A87: https://www.pikelandpropertygroup.com/faq_category/how-we-buy-houses/ | B87: How We Buy Houses Archives - Pikeland Property Group | C87: 52 | D87: 1 | E87: 1 | F87: 1 | H87: 200 | I87: FALSE | J87: text/html; charset=utf-8 | K87: TRUE | L87: =IFERROR(__xludf.DUMMYFUNCTION("IFNA(REGEXEXTRACT(B87,""[\-|–][^–|\-]+$""))"),"- Pikeland Property Group") -> - Pikeland Property Group
A88: https://www.pikelandpropertygroup.com/wp-login.php | B88: Log In ‹ Pikeland Property Group — WordPress | C88: 44 | D88: 1 | E88: 1 | F88: 1 | H88: 200 | I88: FALSE | J88: text/html; charset=utf-8 | K88: TRUE | L88: =IFERROR(__xludf.DUMMYFUNCTION("IFNA(REGEXEXTRACT(B88,""[\-|–][^–|\-]+$""))"),"")
A89: https://www.pikelandpropertygroup.com/faq_category/general/ | B89: General Archives - Pikeland Property Group | C89: 42 | D89: 1 | E89: 1 | F89: 1 | H89: 200 | I89: FALSE | J89: text/html; charset=utf-8 | K89: TRUE | L89: =IFERROR(__xludf.DUMMYFUNCTION("IFNA(REGEXEXTRACT(B89,""[\-|–][^–|\-]+$""))"),"- Pikeland Property Group") -> - Pikeland Property Group
A90: https://www.pikelandpropertygroup.com/blog/page/3/ | B90: Blog - Pikeland Property Group | C90: 30 | D90: 1 | E90: 1 | F90: 3 | H90: 200 | I90: FALSE | J90: text/html; charset=utf-8 | K90: TRUE | L90: =IFERROR(__xludf.DUMMYFUNCTION("IFNA(REGEXEXTRACT(B90,""[\-|–][^–|\-]+$""))"),"- Pikeland Property Group") -> - Pikeland Property Group
A91: https://www.pikelandpropertygroup.com/blog/faq_category/general/ | D91: 0 | H91: 404 | I91: FALSE | J91: text/html; charset=utf-8 | K91: FALSE | L91: =IFERROR(__xludf.DUMMYFUNCTION("IFNA(REGEXEXTRACT(B91,""[\-|–][^–|\-]+$""))"),"")
A92: https://www.pikelandpropertygroup.com/blog/fusion_tb_category/header/ | D92: 0 | H92: 301 | I92: FALSE | J92: text/html; charset=utf-8 | K92: FALSE | L92: =IFERROR(__xludf.DUMMYFUNCTION("IFNA(REGEXEXTRACT(B92,""[\-|–][^–|\-]+$""))"),"")
A93: https://www.pikelandpropertygroup.com/blog/fusion_tb_category/content/ | D93: 0 | H93: 301 | I93: FALSE | J93: text/html; charset=utf-8 | K93: FALSE | L93: =IFERROR(__xludf.DUMMYFUNCTION("IFNA(REGEXEXTRACT(B93,""[\-|–][^–|\-]+$""))"),"")
A94: https://www.pikelandpropertygroup.com/blog/element_category/elements/ | D94: 0 | H94: 301 | I94: FALSE | J94: text/html; charset=utf-8 | K94: FALSE | L94: =IFERROR(__xludf.DUMMYFUNCTION("IFNA(REGEXEXTRACT(B94,""[\-|–][^–|\-]+$""))"),"")
A95: https://www.pikelandpropertygroup.com/blog/page/4/ | B95: Blog - Pikeland Property Group | C95: 30 | D95: 1 | H95: 200 | I95: FALSE | J95: text/html; charset=utf-8 | K95: TRUE | L95: =IFERROR(__xludf.DUMMYFUNCTION("IFNA(REGEXEXTRACT(B95,""[\-|–][^–|\-]+$""))"),"- Pikeland Property Group") -> - Pikeland Property Group
A96: https://www.pikelandpropertygroup.com/blog/fusion_tb_category/page_title_bar/ | D96: 0 | H96: 301 | I96: FALSE | J96: text/html; charset=utf-8 | K96: FALSE | L96: =IFERROR(__xludf.DUMMYFUNCTION("IFNA(REGEXEXTRACT(B96,""[\-|–][^–|\-]+$""))"),"")
A97: https://www.pikelandpropertygroup.com/wp-content/uploads/2023/07/How-To-Stop-Foreclosure-Guide.pdf | D97: 0 | H97: 200 | I97: FALSE | J97: application/pdf | K97: FALSE | L97: =IFERROR(__xludf.DUMMYFUNCTION("IFNA(REGEXEXTRACT(B97,""[\-|–][^–|\-]+$""))"),"")
A98: https://www.pikelandpropertygroup.com/blog/element_category/sections/ | D98: 0 | H98: 301 | I98: FALSE | J98: text/html; charset=utf-8 | K98: FALSE | L98: =IFERROR(__xludf.DUMMYFUNCTION("IFNA(REGEXEXTRACT(B98,""[\-|–][^–|\-]+$""))"),"")
A99: https://www.pikelandpropertygroup.com/blog/faq_category/how-we-buy-houses/ | D99: 0 | H99: 301 | I99: FALSE | J99: text/html; charset=utf-8 | K99: FALSE | L99: =IFERROR(__xludf.DUMMYFUNCTION("IFNA(REGEXEXTRACT(B99,""[\-|–][^–|\-]+$""))"),"")
A100: https://www.pikelandpropertygroup.com/blog/faq_category/home/ | D100: 0 | H100: 404 | I100: FALSE | J100: text/html; charset=utf-8 | K100: FALSE | L100: =IFERROR(__xludf.DUMMYFUNCTION("IFNA(REGEXEXTRACT(B100,""[\-|–][^–|\-]+$""))"),"")
...

Sheet Sheet2
A1: FALSE
A2: FALSE
A3: FALSE
A4: FALSE
A5: FALSE
A6: FALSE
A7: FALSE
A8: FALSE
A9: FALSE
A10: FALSE
A11: FALSE
A12: FALSE
... A270: FALSE

Sheet Unique suffix
B1: Count
A2: {=UNIQUE(suffixes!L2:L107)} -> - We Buy Houses for Cash | B2: =COUNTIF(suffixes!L2:L107,"="&A2) -> 3
A3: - Pikeland Property Group | B3: =COUNTIF(suffixes!L3:L108,"="&A3) -> 84
B4: =COUNTIF(suffixes!L4:L109,"="&A4) -> 20
A5: - Page 2 of 2 | B5: =COUNTIF(suffixes!L5:L110,"="&A5) -> 1
