Workbook

Sheet 00 How to Use
A1: Island Luck Competitor Audit — Ranking Focus
A2: Compressed audit. Island Luck benchmarked against Paradise Games, scoped to the factors that most directly drive keyword coverage and rankings.
A3: Scope | B3: Island Luck only, benchmarked against Paradise Games on identical criteria. Technical SEO is deliberately excluded from this pass; it should be audited separately once the content and structural gaps are sized.
A4: What it covers | B4: Casino silo, sports silo, content and guides, and local trust and authority. Each tab is limited to the points that materially affect how many keywords the site can rank for and how well it ranks for them.
A5: How to complete | B5: Work Island Luck end to end first, then Paradise Games. Auditing one site at a time keeps context intact and is far faster than switching per row.
A6: Scoring | B6: 0 = absent · 1 = present but poor · 2 = adequate / market standard · 3 = strong, best in market. N/A where the check does not apply. Scores roll up automatically into the Summary tab.
A7: Evidence rule | B7: Every score needs a finding written beside it. A score with no note is indefensible in a client meeting three weeks later.
A8: Cells you fill in | B8: All cream-shaded cells. Grey and white cells are fixed framework.
A9: Adding rows | B9: Insert inside the existing block, never below the last row, so the Summary formulas continue to cover them.
A10: Tools assumed | B10: Ahrefs or Semrush for keywords, backlinks and share of voice · Screaming Frog for page inventory, schema and internal links · manual site walkthrough for content and product · prompts to ChatGPT, Claude and Perplexity for AI visibility.
A11: Bahamas context | B11: Domestic online gaming runs under the Gaming Act 2014 through licensed Gaming House Operators; casinos serve tourists, web shops serve residents. The addressable market is domestic, so local trust, local payment rails and local content carry more weight than international brand strength. Geo-restriction may serve you different content from outside the jurisdiction — verify what a Nassau IP sees.
A12: Google Sheets | B12: Upload to Drive and open with Google Sheets. Dropdowns, filters and formulas carry across; re-apply freeze panes if Sheets drops them.
A13: Worked example | B13: Audit point: individual game pages indexable · Island Luck: 412 indexable game URLs with RTP and provider data, two clicks from lobby — score 3 · Paradise Games: no game URLs, JS lobby only — score 0 · Gap: roughly 400 long-tail game queries uncontested; their pages are thin on review copy · Priority High — build an indexable game page template and launch with the top 100 titles.

Sheet 01 Profile & Baseline
A1: Profile & Baseline Metrics
A2: Complete first. Fixes the point-in-time context every later finding is read against.
A3: Field | B3: Why it is captured | C3: Island Luck | D3: Paradise Games (Client)
A4: Date audited / auditor | B4: Fixes the point-in-time context for all findings. | C4: 46238 | D4: 46238
A5: Primary domain audited | B5: Root domain, plus any redirecting legacy domains. | C5: islandluck.com | D5: paradisegames.com
A6: Estimated organic traffic (monthly) | B6: Note the tool and date. Do not mix tools between the two sites. | C6: 16800 | D6: 158000
A7: Estimated organic keywords | B7: Total ranking keywords, all silos. The headline number the whole audit explains. | C7: 195 | D7: 66
A8: Domain Rating / Authority Score | B8: Sizes the authority gap and tells us whether links or content are the constraint. | C8: 19 | D8: 19
A9: Referring domains | B9: Total unique linking domains. | C9: 3000 | D9: 3900
A10: Casino URLs indexed | B10: Scale of the casino silo and its keyword ceiling. | C10: 8 | D10: 1; Login required
A11: Sports URLs indexed | B11: Scale of the sports silo and its keyword ceiling. | C11: 1 | D11: 0
A12: Blog / guide URLs indexed | B12: Scale of the content programme. | C12: https://islandluckblogs.wordpress.com/; Over 10 Google pages; | D12: N/A
A13: Physical premises / agent locations | B13: Omnichannel footprint, including Family Islands. | C13: 51 | D13: roughly 35
A14: Sportsbook / casino supplier (observed) | B14: Determines product ceiling and how many pages can legitimately be built. | C14: 32 Sports Silos; 396 casino games when clicking on 'All' | D14: TBD once live site access has been given. Can't view sports 1 and sports 2 on staging.
A15: Headline strengths | B15: Three lines maximum. Written last, after the audit tabs are complete. | C15: N/A | D15: N/A
A16: Headline weaknesses | B16: Three lines maximum. These become our attack points. | C16: N/A | D16: N/A

Sheet 02 Casino Silo
A1: Casino Silo
A2: Casino page inventory, on-page content, keyword coverage and product context. The largest keyword-expansion opportunity.
A3: Ref | B3: Section | C3: Audit point | D3: Why this matters (rationale for the client) | E3: What good looks like (benchmark) | F3: Island Luck — finding | G3: Score | H3: Paradise Games (Client) — finding | I3: Score | J3: Gap / opportunity | K3: Priority | L3: Recommended action
A4: C01 | B4: Silo & Page Inventory | C4: Category page inventory (slots, live casino, table games, jackpots, instant win, numbers/lotto) | D4: Category pages are the head-term entry points for the whole silo. Each missing category is a whole keyword cluster we cannot rank for at all, regardless of how good the rest of the site is. | E4: One indexable, content-supported page per commercial category with real search demand. | F4: 10, including Casino 1, Casino 2, Casino 3, Casino 4, Live Dealers, Scratch Cards, Table Games. Jackpot Games | G4: 2 | H4: 16, Also with Casino silos, live games, featured, new games, Table Games, Scratch, Jackpot Slots, New Games, Top Games | I4: 3
A5: C02 | B5: Silo & Page Inventory | C5: Provider/studio pages (Pragmatic Play, Evolution, Hacksaw, Play'n GO etc.) | D5: Provider searches carry high commercial intent and are the cheapest scalable page type in casino SEO. A provider page can be built once and target dozens of long-tail variants. | E5: A page per major provider with its game library, a studio profile and links to top titles. | F5: Same as PG, but with fragmented URLs | G5: 1 | H5: No pages, but categorised and changes once clicked | I5: 1 | J5: Dedicated pages for each of the Providers, in stead of just filtered. | K5: Medium | L5: Create dedicated pages per Provier
A6: C03 | B6: Silo & Page Inventory | C6: Individual game pages and whether they are indexable | D6: Game-name queries are the single largest volume block in casino search. If Island Luck has no indexable game pages, the entire long tail is uncontested and available to us at low cost. | E6: Indexable page per game with RTP, volatility, provider, paylines and written review copy. | F6: Each casino game has a dedicated page: E.G., https://www.islandluck.com/casino/jack-hammer; https://www.islandluck.com/casino/grand-wheel | G6: 3 | H6: None dedicated, loads under casino | I6: 1 | J6: PG does not have dedicated pages per game, whereas Island Luck does | K6: High | L6: Create dedicated pages that host each casino game
A7: C04 | B7: Silo & Page Inventory | C7: Promotions hub and whether individual offers have persistent URLs | D7: Bonus queries are bottom-funnel and convert immediately. A JS-only promo page captures none of that demand and gives no internal-link target. | E7: A /promotions/ hub plus persistent URLs for evergreen offers. | F7: Does have promotions pages, but using fragmented URLs; e.g., https://www.islandluck.com/promotion?section=Missions | G7: 1 | H7: Same as competitor, but there are overlays with more context | I7: 1 | J7: Opportunity to create dedicated LPs for the promotions | K7: Low | L7: Create dedicated pages for each of the promotions.
A8: C05 | B8: On-Page Content | C8: Word count, placement and depth of copy on category pages | D8: Sets the content bar we must clear to compete, and shows whether the ranking gap is a content-volume problem or a structural one. Two very different budgets. | E8: 500 to 1,200 words of genuinely useful copy placed below the game grid. | F8: N/A | G8: 0 | H8: N/A | I8: 0 | J8: Opportunity to create content to add depth on pages | K8: High | L8: Create content per page for casino pages.
A9: C06 | B9: On-Page Content | C9: Uniqueness of copy across categories and providers (templated vs bespoke) | D9: Templated copy at scale is a visible weakness and is vulnerable to quality-focused updates. If theirs is spun, differentiated pages will overtake them without matching their page count. | E9: Record in full and compare like-for-like against Paradise Games. | F9: N/A | G9: 0 | H9: N/A | I9: 0 | J9: Same as above | K9: High | L9: Same as above
A10: C07 | B10: On-Page Content | C10: Presence of structured game data (RTP, volatility, min/max stake, provider, demo) | D10: Game facts are the substance behind game-page rankings and are exactly what AI assistants extract for 'RTP of X' style queries. Completeness is a citation advantage. | E10: Record in full and compare like-for-like against Paradise Games. | F10: None present | G10: 0 | H10: None present | I10: 0
A11: C08 | B11: On-Page Content | C11: Title tag and H1 patterns across category, provider and game pages | D11: Title patterns are the fastest-shipping ranking lever available and are directly copyable or beatable. They also reveal how they map keywords to page types. | E11: Distinct, keyword-led titles under 60 characters with no template collisions. | F11: No | G11: 0 | H11: No | I11: 0 | J11: Opportunity to include title tags on all pages | K11: Medium | L11: Create unique title tags for all main pages,
A12: C09 | B12: On-Page Content | C12: Internal linking from hub down to category, provider and game pages | D12: Internal linking is how authority reaches the tail. A strong hub with no downward links leaves their own inventory unranked, which is an opening we can exploit quickly. | E12: Record in full and compare like-for-like against Paradise Games. | F12: Only present in the navigation, game tiles and footer | G12: 0 | H12: Only present in navigation, game tiles and footer | I12: 0 | J12: Internal linking opportunity to improve structure | K12: Medium | L12: Implement internal linking; as page content is implemented
A13: C10 | B13: Keywords & SERP | C13: Top-ranking casino keywords, estimated traffic and which page type earns it | D13: Shows which page archetype actually drives their casino traffic, so we build where returns are proven rather than where theory says. | E13: Top 50 casino keywords mapped to landing page type. | F13: TBA | H13: TBA | J13: TBA
A14: C11 | B14: Keywords & SERP | C14: Keyword cannibalisation between lobby, category and game pages | D14: Cannibalisation splits their authority and destabilises their rankings. A single consolidated page from us can displace two of theirs. | E14: Record in full and compare like-for-like against Paradise Games. | F14: None | G14: 0 | H14: None | I14: 0 | J14: Ensure content for all pages are unique when being created and implemented. | K14: High | L14: Ensure content for all pages are unique when being created and implemented.
A15: C12 | B15: Keywords & SERP | C15: Coverage of Bahamas-modified terms (online slots Bahamas, casino games Nassau) | D15: Lower volume but far higher conversion in a domestic-licensed market. If they ignore local modifiers, this is cheap, defensible ground. | E15: Record in full and compare like-for-like against Paradise Games. | F15: N/A - only in footer and terms and conditions | G15: 1 | H15: N/A - only in footer and terms and conditions | I15: 1 | J15: Opportunity to implement additional keyword references to Bahamas | K15: High | L15: Include keywords in the copy of the pages when creating content - specific to Bahamas
A16: C13 | B16: Keywords & SERP | C16: Schema deployed on casino pages (BreadcrumbList, FAQPage, ItemList, VideoGame) | D16: Schema drives SERP feature eligibility and AI parsing. In a vertical where most operators deploy none, it is a fast and defensible edge. | E16: Record in full and compare like-for-like against Paradise Games. | F16: No items detected | G16: 0 | H16: No Items detected | I16: 0 | J16: Opportunity to include schema markup for casino games or casino section. | K16: High | L16: Investigate schema markup for main casino page.
A17: C14 | B17: Product Context | C17: Game library size, provider mix and live casino depth | D17: Library breadth caps how many game pages can ever be built, so it sets the ceiling on our own SEO programme as well as being the top product comparison players make. | E17: Record in full and compare like-for-like against Paradise Games. | F17: Great selection of casino games; just under 400 | G17: 3 | H17: Paradise Games not trailing far behind in terms of casino games - 303. The graphics on casino game tile interactions on hover are far better for the competitor. | I17: 2 | J17: Opportunity to make graphics more appealing when users hover/interact with game tiles | K17: Medium | L17: Create graphics that change when users hover on the game tiles, even if it's just a button overlay that shows "Play Now"
A18: C15 | B18: Product Context | C18: Demo / free play availability without registration | D18: Free-play queries are a large long-tail traffic source. Gating demo behind registration forfeits that traffic entirely. | E18: Record in full and compare like-for-like against Paradise Games. | F18: No | G18: 0 | H18: No | I18: 0 | J18: Opportunity to include demo games for players who'd like to test games first | K18: Low | L18: Find out whether demo play is available.
A19: C16 | B19: Product Context | C19: Numbers, cash pot and asue draw presentation | D19: Culturally specific, high-frequency Bahamian demand that no international competitor targets. How they structure these pages transfers directly to our lottery content. | E19: Record in full and compare like-for-like against Paradise Games. | F19: Numbers on Island Luck presented in table format with infinite scroll until user eventually gets to the bottom. Option to clear search. Also promotional banner in the hero of the page, if users want to jump to a casino game specific to the promotion | G19: 2 | H19: Numbers on results page presented in table-format; users have the ability to go to different pages of the table, depending on what they want to see, No clear function | I19: 2 | J19: Opportunity to include clear function for users to easily clear the search | K19: Low | L19: Create "Clear Search" function for users to easily reset their searches. Include hero banner that promotes popular casino game, or a specific promotion

Sheet 03 Sports Silo
A1: Sports Silo
A2: Sportsbook page inventory, on-page content and keyword coverage, weighted to the US-league demand that dominates Bahamian betting interest.
A3: Ref | B3: Section | C3: Audit point | D3: Why this matters (rationale for the client) | E3: What good looks like (benchmark) | F3: Island Luck — finding | G3: Score | H3: Paradise Games (Client) — finding | I3: Score | J3: Gap / opportunity | K3: Priority | L3: Recommended action
A4: S01 | B4: Silo & Page Inventory | C4: Sport-level page inventory (basketball, American football, baseball, football, boxing, MMA) | D4: The sport set defines which audiences they can rank for at all. Given Bahamian demand skews to NBA, NFL, MLB and boxing, any gap in those is a serious commercial miss. | E4: An indexable, content-supported page per sport with genuine local betting demand.
A5: S02 | B5: Silo & Page Inventory | C5: League and competition pages (NBA, NFL, MLB, NCAA, Premier League, UFC) | D5: League terms carry the bulk of sports search volume and return season after season. These are the workhorse pages of sportsbook SEO. | E5: A page per major league with markets, fixtures, odds and written context.
A6: S03 | B6: Silo & Page Inventory | C6: Team, event and fixture pages and whether they are indexable | D6: Fixture pages capture large, spiky, low-competition demand. Whoever automates this well owns the seasonal tail, and it is the fastest route to keyword volume growth. | E6: Record in full and compare like-for-like against Paradise Games.
A7: S04 | B7: Silo & Page Inventory | C7: Handling of expired events after the fixture passes | D7: Poor expiry handling leaves thousands of thin dead URLs dragging on site quality. Good handling recycles authority season to season. | E7: Persistent evergreen matchup URLs or clean 301s, never mass 404s.
A8: S05 | B8: On-Page Content | C8: Depth and uniqueness of copy on sport and league pages | D8: Sports copy is usually thinner than casino copy, which makes it the easier of the two silos to win. Their word count tells us how little we need to do to beat them. | E8: Record in full and compare like-for-like against Paradise Games.
A9: S06 | B9: On-Page Content | C9: Whether odds and fixtures are server-rendered and crawlable | D9: If live data only appears after JS execution, search engines may index an empty shell. That is a large, quiet ranking opportunity. | E9: Record in full and compare like-for-like against Paradise Games.
A10: S07 | B10: On-Page Content | C10: Betting-market explainer content (spreads, moneyline, totals, parlays, props) | D10: Market education captures informational demand, feeds AI answers and links directly into the relevant market page. It is the bridge between blog and sportsbook. | E10: Record in full and compare like-for-like against Paradise Games.
A11: S08 | B11: On-Page Content | C11: Title and meta templates for league, team and fixture pages | D11: Programmatic title templates are where scaled sportsbook SEO succeeds or fails. Theirs is directly copyable or beatable at almost no cost. | E11: Record in full and compare like-for-like against Paradise Games.
A12: S09 | B12: On-Page Content | C12: Internal linking between sport, league, team and fixture pages | D12: Determines whether their fixture pages get crawled and ranked at all. Weak linking means their inventory exists but does not compete. | E12: Record in full and compare like-for-like against Paradise Games.
A13: S10 | B13: Keywords & SERP | C13: Top-ranking sports keywords and the page types earning them | D13: Tells us whether their sports traffic comes from league pages, fixture pages or the blog, so we concentrate the build where it demonstrably works. | E13: Record in full and compare like-for-like against Paradise Games.
A14: S11 | B14: Keywords & SERP | C14: Coverage of Bahamian and Caribbean sports demand (NBA, NFL, MLB, boxing, athletics) | D14: Content matched to what Bahamians actually watch converts far better than generic global sports coverage, and faces less competition. | E14: Record in full and compare like-for-like against Paradise Games.
A15: S12 | B15: Keywords & SERP | C15: Seasonality lead time (Super Bowl, March Madness, NBA Finals, World Cup) | D15: Publish dates reveal how early they prepare. That sets the deadline we must beat to own the peak. | E15: Record in full and compare like-for-like against Paradise Games.
... A18: S15 | B18: Product Context | C18: Sports promotions: offer types and whether they have their own URLs | D18: Sports offers are event-triggered and reward publishing speed. Persistent URLs turn each one into a recurring ranking asset. | E18: Record in full and compare like-for-like against Paradise Games.

Sheet 04 Content & Guides
A1: Content & Guides
A2: Top-of-funnel content: coverage, E-E-A-T, extraction formatting and internal linking into the money silos.
A3: Ref | B3: Section | C3: Audit point | D3: Why this matters (rationale for the client) | E3: What good looks like (benchmark) | F3: Island Luck — finding | G3: Score | H3: Paradise Games (Client) — finding | I3: Score | J3: Gap / opportunity | K3: Priority | L3: Recommended action
A4: B01 | B4: Structure | C4: Location and URL pattern of the content section (/blog/, /guides/) | D4: Where content sits decides whether its authority flows into the money silos or strands in a disconnected corner. This is a structural decision we must get right before publishing. | E4: Content nested within or tightly linked to the relevant silo, under a clear parent hub.
A5: B02 | B5: Structure | C5: Publishing volume and cadence over the last 12 months | D5: Cadence shows resourcing and intent, and sizes the effort needed to overtake them. A rival publishing weekly is compounding; one publishing quarterly is not defending the space. | E5: Record in full and compare like-for-like against Paradise Games.
A6: B03 | B6: Structure | C6: Whether guides link contextually into casino and sports money pages | D6: This is the entire commercial justification for a content programme. Content that does not link down is a cost centre, not an acquisition channel. | E6: Record in full and compare like-for-like against Paradise Games.
A7: B04 | B7: Topic Coverage | C7: How-to and beginner content (how to bet, how to read odds, how slots work) | D7: Captures top-of-funnel demand in a market where many players are newly converting from in-person web shops to online play. Also the most AI-cited content format. | E7: Record in full and compare like-for-like against Paradise Games.
A8: B05 | B8: Topic Coverage | C8: Game and market explainer content (RTP explained, volatility, spreads, parlays) | D8: Definitional content is what AI assistants quote and the natural internal-link feeder into game, provider and market pages. | E8: Record in full and compare like-for-like against Paradise Games.
A9: B06 | B9: Topic Coverage | C9: Payments, withdrawals and account help content | D9: High-intent, high-anxiety queries. Answering them clearly captures searchers at the exact point of deciding to deposit. | E9: Record in full and compare like-for-like against Paradise Games.
A10: B07 | B10: Topic Coverage | C10: Bahamas-specific content (legality, Gaming Board, local payments, local sport) | D10: The most defensible content territory available. International affiliates cannot match genuine local knowledge, and domestic searchers explicitly look for it. | E10: Record in full and compare like-for-like against Paradise Games.
A11: B08 | B11: Topic Coverage | C11: Sports previews and predictions, and their publishing lead time | D11: Preview content captures pre-event spikes only if published before demand peaks. Their lead time is a directly copyable operational benchmark. | E11: Record in full and compare like-for-like against Paradise Games.
A12: B09 | B12: Quality & Extraction | C12: Author attribution, bios, credentials and update dates | D12: The clearest E-E-A-T gap in the domestic market. Most operators publish anonymously, so named expertise is a cheap and durable differentiator in a trust-sensitive vertical. | E12: Record in full and compare like-for-like against Paradise Games.
A13: B10 | B13: Quality & Extraction | C13: FAQ sections and their schema implementation | D13: Serves both People Also Ask capture and AI extraction, and is the lowest-effort structured content available. | E13: Record in full and compare like-for-like against Paradise Games.
A14: B11 | B14: Quality & Extraction | C14: Formatting for extraction: question headings, direct answers, tables, defined terms | D14: Format determines extractability more than quality does. This becomes the concrete change list for our own content brief templates. | E14: Record in full and compare like-for-like against Paradise Games.
A15: B12 | B15: Quality & Extraction | C15: Featured snippets and PAA results currently won by their content | D15: Each snippet they hold is a specific, winnable target and the closest proxy for how well their content answers real questions. | E15: Record in full and compare like-for-like against Paradise Games.

Sheet 05 Local & Authority
A1: Local & Authority
A2: Trust, local relevance and link authority. Determines whether ranking gaps are a content problem or an authority problem.
A3: Ref | B3: Section | C3: Audit point | D3: Why this matters (rationale for the client) | E3: What good looks like (benchmark) | F3: Island Luck — finding | G3: Score | H3: Paradise Games (Client) — finding | I3: Score | J3: Gap / opportunity | K3: Priority | L3: Recommended action
A4: L01 | B4: Trust & Compliance | C4: Gaming Board licence details displayed, and how prominently | D4: Visible licensing is the strongest trust signal in a domestic market and an explicit E-E-A-T factor for a money-and-life-adjacent vertical. Prominence varies widely and is easily beaten. | E4: Record in full and compare like-for-like against Paradise Games.
A5: L02 | B5: Trust & Compliance | C5: Responsible gambling content and tools (limits, self-exclusion, time-outs) | D5: Compliance expectation, genuine trust signal, and content that ranks for its own queries. Three returns from one build. | E5: Record in full and compare like-for-like against Paradise Games.
A6: L03 | B6: Local Relevance | C6: Local payment methods supported (Sand Dollar, Kanoo, Omni, bank transfer, cash at agent locations) | D6: The most decisive product factor in this market. Cash-in at agent premises has no online equivalent for operators without a network, and it drives its own search demand. | E6: Record in full and compare like-for-like against Paradise Games.
A7: L04 | B7: Local Relevance | C7: Use of Bahamian references, place names and local voice in copy | D7: Local authenticity is the one advantage a domestic operator holds over offshore books and affiliates. Under-using it wastes a structural asset. | E7: Record in full and compare like-for-like against Paradise Games.
A8: L05 | B8: Local Relevance | C8: Family Islands coverage in content and agent listings | D8: Nassau-centric messaging leaves Grand Bahama, Abaco, Eleuthera and Exuma underserved. That content is uncontested and reaches real demand. | E8: Record in full and compare like-for-like against Paradise Games.
A9: L06 | B9: Local Relevance | C9: Geo-targeting signals: local business schema, NAP, contact details, ccTLD usage | D9: Explicit geographic signalling helps a domestic operator outrank larger international domains locally. Most rivals set none of it. | E9: Record in full and compare like-for-like against Paradise Games.
A10: L07 | B10: Authority | C10: Referring domains, Domain Rating and 24-month growth trend | D10: Tells us whether the ranking gap is a content problem or an authority problem. Those need entirely different budgets, so this determines the shape of the recommendation. | E10: Record in full and compare like-for-like against Paradise Games.
A11: L08 | B11: Authority | C11: Bahamian media links specifically (Tribune 242, Nassau Guardian, Eyewitness News) | D11: Local press links carry disproportionate relevance for a domestically licensed brand and are realistically obtainable, unlike global iGaming media. | E11: Record in full and compare like-for-like against Paradise Games.
A12: L09 | B12: Authority | C12: Branded search volume and trend | D12: The truest measure of market share and the best single predictor of non-branded ranking strength in this vertical. | E12: Record in full and compare like-for-like against Paradise Games.
A13: L10 | B13: Authority | C13: Google Business Profiles and local citation coverage for physical locations | D13: With a licensed premises network, local pack visibility is a real acquisition channel that pure-online SEO thinking tends to miss. | E13: Record in full and compare like-for-like against Paradise Games.

Sheet 06 Summary
A1: Summary of Findings
A2: Calculates automatically from the audit tabs. Averages on the 0-3 scale; blanks are ignored until scored.
A3: Area | B3: Section | C3: Island Luck | D3: Paradise Games (Client) | E3: Client gap
A4: Casino Silo | B4: Silo & Page Inventory | C4: =IFERROR(AVERAGEIFS('02 Casino Silo'!$G$4:$G$19,'02 Casino Silo'!$B$4:$B$19,$B4),"") -> 1.75 | D4: =IFERROR(AVERAGEIFS('02 Casino Silo'!$I$4:$I$19,'02 Casino Silo'!$B$4:$B$19,$B4),"") -> 1.5 | E4: =IFERROR(D4-C4,"") -> -0.25
A5: Casino Silo | B5: On-Page Content | C5: =IFERROR(AVERAGEIFS('02 Casino Silo'!$G$4:$G$19,'02 Casino Silo'!$B$4:$B$19,$B5),"") -> 0 | D5: =IFERROR(AVERAGEIFS('02 Casino Silo'!$I$4:$I$19,'02 Casino Silo'!$B$4:$B$19,$B5),"") -> 0 | E5: =IFERROR(D5-C5,"") -> 0
A6: Casino Silo | B6: Keywords & SERP | C6: =IFERROR(AVERAGEIFS('02 Casino Silo'!$G$4:$G$19,'02 Casino Silo'!$B$4:$B$19,$B6),"") -> 0.33333333 | D6: =IFERROR(AVERAGEIFS('02 Casino Silo'!$I$4:$I$19,'02 Casino Silo'!$B$4:$B$19,$B6),"") -> 0.33333333 | E6: =IFERROR(D6-C6,"") -> 0
A7: Casino Silo | B7: Product Context | C7: =IFERROR(AVERAGEIFS('02 Casino Silo'!$G$4:$G$19,'02 Casino Silo'!$B$4:$B$19,$B7),"") -> 1.6666667 | D7: =IFERROR(AVERAGEIFS('02 Casino Silo'!$I$4:$I$19,'02 Casino Silo'!$B$4:$B$19,$B7),"") -> 1.3333333 | E7: =IFERROR(D7-C7,"") -> -0.33333333
A8: Casino Silo | B8: AREA AVERAGE — Casino Silo | C8: =IFERROR(AVERAGE('02 Casino Silo'!$G$4:$G$19),"") -> 0.86666667 | D8: =IFERROR(AVERAGE('02 Casino Silo'!$I$4:$I$19),"") -> 0.73333333 | E8: =IFERROR(D8-C8,"") -> -0.13333333
A9: Sports Silo | B9: Silo & Page Inventory | C9: =IFERROR(AVERAGEIFS('03 Sports Silo'!$G$4:$G$18,'03 Sports Silo'!$B$4:$B$18,$B9),"") | D9: =IFERROR(AVERAGEIFS('03 Sports Silo'!$I$4:$I$18,'03 Sports Silo'!$B$4:$B$18,$B9),"") | E9: =IFERROR(D9-C9,"") -> 0
A10: Sports Silo | B10: On-Page Content | C10: =IFERROR(AVERAGEIFS('03 Sports Silo'!$G$4:$G$18,'03 Sports Silo'!$B$4:$B$18,$B10),"") | D10: =IFERROR(AVERAGEIFS('03 Sports Silo'!$I$4:$I$18,'03 Sports Silo'!$B$4:$B$18,$B10),"") | E10: =IFERROR(D10-C10,"") -> 0
A11: Sports Silo | B11: Keywords & SERP | C11: =IFERROR(AVERAGEIFS('03 Sports Silo'!$G$4:$G$18,'03 Sports Silo'!$B$4:$B$18,$B11),"") | D11: =IFERROR(AVERAGEIFS('03 Sports Silo'!$I$4:$I$18,'03 Sports Silo'!$B$4:$B$18,$B11),"") | E11: =IFERROR(D11-C11,"") -> 0
A12: Sports Silo | B12: Product Context | C12: =IFERROR(AVERAGEIFS('03 Sports Silo'!$G$4:$G$18,'03 Sports Silo'!$B$4:$B$18,$B12),"") | D12: =IFERROR(AVERAGEIFS('03 Sports Silo'!$I$4:$I$18,'03 Sports Silo'!$B$4:$B$18,$B12),"") | E12: =IFERROR(D12-C12,"") -> 0
A13: Sports Silo | B13: AREA AVERAGE — Sports Silo | C13: =IFERROR(AVERAGE('03 Sports Silo'!$G$4:$G$18),"") | D13: =IFERROR(AVERAGE('03 Sports Silo'!$I$4:$I$18),"") | E13: =IFERROR(D13-C13,"") -> 0
A14: Content & Guides | B14: Structure | C14: =IFERROR(AVERAGEIFS('04 Content & Guides'!$G$4:$G$15,'04 Content & Guides'!$B$4:$B$15,$B14),"") | D14: =IFERROR(AVERAGEIFS('04 Content & Guides'!$I$4:$I$15,'04 Content & Guides'!$B$4:$B$15,$B14),"") | E14: =IFERROR(D14-C14,"") -> 0
A15: Content & Guides | B15: Topic Coverage | C15: =IFERROR(AVERAGEIFS('04 Content & Guides'!$G$4:$G$15,'04 Content & Guides'!$B$4:$B$15,$B15),"") | D15: =IFERROR(AVERAGEIFS('04 Content & Guides'!$I$4:$I$15,'04 Content & Guides'!$B$4:$B$15,$B15),"") | E15: =IFERROR(D15-C15,"") -> 0
A16: Content & Guides | B16: Quality & Extraction | C16: =IFERROR(AVERAGEIFS('04 Content & Guides'!$G$4:$G$15,'04 Content & Guides'!$B$4:$B$15,$B16),"") | D16: =IFERROR(AVERAGEIFS('04 Content & Guides'!$I$4:$I$15,'04 Content & Guides'!$B$4:$B$15,$B16),"") | E16: =IFERROR(D16-C16,"") -> 0
A17: Content & Guides | B17: AREA AVERAGE — Content & Guides | C17: =IFERROR(AVERAGE('04 Content & Guides'!$G$4:$G$15),"") | D17: =IFERROR(AVERAGE('04 Content & Guides'!$I$4:$I$15),"") | E17: =IFERROR(D17-C17,"") -> 0
A18: Local & Authority | B18: Trust & Compliance | C18: =IFERROR(AVERAGEIFS('05 Local & Authority'!$G$4:$G$13,'05 Local & Authority'!$B$4:$B$13,$B18),"") | D18: =IFERROR(AVERAGEIFS('05 Local & Authority'!$I$4:$I$13,'05 Local & Authority'!$B$4:$B$13,$B18),"") | E18: =IFERROR(D18-C18,"") -> 0
A19: Local & Authority | B19: Local Relevance | C19: =IFERROR(AVERAGEIFS('05 Local & Authority'!$G$4:$G$13,'05 Local & Authority'!$B$4:$B$13,$B19),"") | D19: =IFERROR(AVERAGEIFS('05 Local & Authority'!$I$4:$I$13,'05 Local & Authority'!$B$4:$B$13,$B19),"") | E19: =IFERROR(D19-C19,"") -> 0
A20: Local & Authority | B20: Authority | C20: =IFERROR(AVERAGEIFS('05 Local & Authority'!$G$4:$G$13,'05 Local & Authority'!$B$4:$B$13,$B20),"") | D20: =IFERROR(AVERAGEIFS('05 Local & Authority'!$I$4:$I$13,'05 Local & Authority'!$B$4:$B$13,$B20),"") | E20: =IFERROR(D20-C20,"") -> 0
A21: Local & Authority | B21: AREA AVERAGE — Local & Authority | C21: =IFERROR(AVERAGE('05 Local & Authority'!$G$4:$G$13),"") | D21: =IFERROR(AVERAGE('05 Local & Authority'!$I$4:$I$13),"") | E21: =IFERROR(D21-C21,"") -> 0
B23: OVERALL POSITION (all areas) | C23: =IFERROR(AVERAGE(C8,C13,C17,C21),"") -> 0.86666667 | D23: =IFERROR(AVERAGE(D8,D13,D17,D21),"") -> 0.73333333 | E23: =IFERROR(D23-C23,"") -> -0.13333333
B24: 0 absent · 1 poor · 2 adequate · 3 strong. A negative client gap is ground to make up.
A26: PRIORITY WORKLOAD
A27: Area | B27: High | C27: Medium | D27: Low | E27: % scored
A28: Casino Silo | B28: =COUNTIFS('02 Casino Silo'!$K$4:$K$19,"High") -> 6 | C28: =COUNTIFS('02 Casino Silo'!$K$4:$K$19,"Medium") -> 4 | D28: =COUNTIFS('02 Casino Silo'!$K$4:$K$19,"Low") -> 3 | E28: =IFERROR(COUNT('02 Casino Silo'!$I$4:$I$19)/16,0) -> 0.9375
A29: Sports Silo | B29: =COUNTIFS('03 Sports Silo'!$K$4:$K$18,"High") -> 0 | C29: =COUNTIFS('03 Sports Silo'!$K$4:$K$18,"Medium") -> 0 | D29: =COUNTIFS('03 Sports Silo'!$K$4:$K$18,"Low") -> 0 | E29: =IFERROR(COUNT('03 Sports Silo'!$I$4:$I$18)/15,0) -> 0
A30: Content & Guides | B30: =COUNTIFS('04 Content & Guides'!$K$4:$K$15,"High") -> 0 | C30: =COUNTIFS('04 Content & Guides'!$K$4:$K$15,"Medium") -> 0 | D30: =COUNTIFS('04 Content & Guides'!$K$4:$K$15,"Low") -> 0 | E30: =IFERROR(COUNT('04 Content & Guides'!$I$4:$I$15)/12,0) -> 0
A31: Local & Authority | B31: =COUNTIFS('05 Local & Authority'!$K$4:$K$13,"High") -> 0 | C31: =COUNTIFS('05 Local & Authority'!$K$4:$K$13,"Medium") -> 0 | D31: =COUNTIFS('05 Local & Authority'!$K$4:$K$13,"Low") -> 0 | E31: =IFERROR(COUNT('05 Local & Authority'!$I$4:$I$13)/10,0) -> 0

Sheet 07 Action Plan
A1: Prioritised Action Plan
A2: Pull every High and Medium priority row through here and sequence it.
A3: Ref | B3: Source tab | C3: Opportunity | D3: Why it matters (client rationale) | E3: Recommended action | F3: Silo | G3: Effort | H3: Impact
